Workbook

Sheet Dashboard
A1: PANDA SHOES INDUSTRY LTD — PURCHASE & PROCUREMENT PERFORMANCE DASHBOARD
A2: ="Report date: "&TEXT(Settings!B4,"dd mmm yyyy")&" | Values in BDT Lakh (1 Lakh = 1,00,000) | Source: Purchase_Register (auto-refresh)" -> Report date: 15 Oct 2026 | Values in BDT Lakh (1 Lakh = 1,00,000) | Source: Purchase_Register (auto-refresh)
A4: PRs Raised | F4: POs Issued | K4: Committed Spend | P4: Paid to Suppliers | U4: Outstanding Payable
A5: =COUNTA(Purchase_Register!$A$6:$A$205) -> 45 | F5: =COUNTA(Purchase_Register!$O$6:$O$205) -> 39 | K5: =SUM(Purchase_Register!$AD$6:$AD$205)/100000 -> 565.19 | P5: =SUM(Purchase_Register!$AI$6:$AI$205)/100000 -> 338.47316 | U5: =SUM(Purchase_Register!$AK$6:$AK$205)/100000 -> 226.71684
A7: Overdue Payable | F7: % Paid | K7: OPEX Committed | P7: CAPEX Committed | U7: Budget Utilisation
A8: =SUMIFS(Purchase_Register!$AK$6:$AK$205,Purchase_Register!$AP$6:$AP$205,">0")/100000 -> 33.237632 | F8: =IFERROR(SUM(Purchase_Register!$AI$6:$AI$205)/SUM(Purchase_Register!$AD$6:$AD$205),0) -> 0.59886615 | K8: =SUMIFS(Purchase_Register!$AD$6:$AD$205,Purchase_Register!$H$6:$H$205,"OPEX")/100000 -> 439.64954 | P8: =SUMIFS(Purchase_Register!$AD$6:$AD$205,Purchase_Register!$H$6:$H$205,"CAPEX")/100000 -> 125.54046 | U8: =IFERROR(Budget_Control!I25/Budget_Control!H25,0) -> 0.44188363
A10: Net Price Variance vs Budget | F10: OTIF Delivery | K10: Avg Days PR → Approval | P10: Avg Days Approval → PO | U10: Avg Lead Time PO → In-house
A11: =SUM(Purchase_Register!$AA$6:$AA$205)/100000 -> 9.6835635 | F11: =IFERROR(COUNTIF(Purchase_Register!$BE$6:$BE$205,"OTIF")/COUNTIF(Purchase_Register!$BE$6:$BE$205,"*OTIF"),0) -> 0.5 | K11: =IFERROR(AVERAGE(Purchase_Register!$AZ$6:$AZ$205),0) -> 2.9285714 | P11: =IFERROR(AVERAGE(Purchase_Register!$BA$6:$BA$205),0) -> 3.0769231 | U11: =IFERROR(AVERAGE(Purchase_Register!$BB$6:$BB$205),0) -> 21.764706
A13: Avg Full Cycle PR → Close | F13: Awaiting Approval | K13: Open POs (not in-house) | P13: Late Deliveries (open + closed) | U13: PO without Approval (control breach)
A14: =IFERROR(AVERAGE(Purchase_Register!$BC$6:$BC$205),0) -> 28.088235 | F14: =COUNTIF(Purchase_Register!$BI$6:$BI$205,"Awaiting Approval") -> 3 | K14: =COUNTIF(Purchase_Register!$BI$6:$BI$205,"PO Issued*")+COUNTIF(Purchase_Register!$BI$6:$BI$205,"Receiving*") -> 5 | P14: =COUNTIF(Purchase_Register!$BD$6:$BD$205,">0") -> 12 | U14: =COUNTIFS(Purchase_Register!$O$6:$O$205,"<>",Purchase_Register!$K$6:$K$205,"<>Approved") -> 0
A16: Savings vs Budget Price | F16: Pending In-house Value | K16: Paid Ahead of Receipt (risk) | P16: In-Full Delivery Rate | U16: High-Priority Actions
A17: =-SUMIF(Purchase_Register!$AA$6:$AA$205,"<0")/100000 -> 3.7346886 | F17: =SUMIFS(Purchase_Register!$AW$6:$AW$205,Purchase_Register!$AY$6:$AY$205,"")/100000 -> 101.05738 | K17: =SUM(Purchase_Register!$AL$6:$AL$205)/100000 -> 42.7851 | P17: =IFERROR(COUNTIFS(Purchase_Register!$BE$6:$BE$205,"*OTIF",Purchase_Register!$AX$6:$AX$205,"All In-house*")/COUNTIF(Purchase_Register!$BE$6:$BE$205,"*OTIF"),0) -> 0.79411765 | U17: =COUNTIF(Purchase_Register!$BL$6:$BL$205,"High") -> 12
A19: ="ACTIONS: "&COUNT(Purchase_Register!$BM$6:$BM$205)&" line(s) — see Action_Tracker" -> ACTIONS: 22 line(s) — see Action_Tracker | F19: =IF(COUNTIF(Purchase_Register!$BJ$6:$BJ$205,"?*")-COUNTIF(Purchase_Register!$BJ$6:$BJ$205,"OK")=0,"DATA CHECK: all register lines complete and consistent ✓","DATA CHECK: "&(COUNTIF(Purchase_Register!$BJ$6:$BJ$205,"?*")-COUNTIF(Purchase_Register!$BJ$6:$BJ$205,"OK"))&" register line(s) need correction — see Data Check column") -> DATA CHECK: 1 register line(s) need correction — see Data Check column | Q19: ="PENDING IN-HOUSE: "&(COUNTIF(Purchase_Register!$AX$6:$AX$205,"Pending*")+COUNTIF(Purchase_Register!$AX$6:$AX$205,"Not Started*"))&" open PO line(s), BDT "&TEXT(SUMIFS(Purchase_Register!$AW$6:$AW$205,Purchase_Register!$AY$6:$AY$205,"")/100000,"#,##0.00")&" Lakh | Short closed: "&COUNTIF(Purchase_Register!$AX$6:$AX$205,"Short Closed*") -> PENDING IN-HOUSE: 5 open PO line(s), BDT 101.06 Lakh | Short closed: 7
A21: MANAGEMENT HIGHLIGHTS — written automatically from the latest data
A22: ="▸ Spend: BDT "&TEXT((SUM(Purchase_Register!$AD$6:$AD$205))/100000,"#,##0.00")&" Lakh committed on "&COUNTA(Purchase_Register!$O$6:$O$205)&" POs — "&TEXT(IFERROR(SUM(Purchase_Register!$AI$6:$AI$205)/SUM(Purchase_Register!$AD$6:$AD$205),0),"0%")&" paid; BDT "&TEXT((SUM(Purchase_Register!$AK$6:$AK$205))/100000,"#,##0.00")&" Lakh outstanding, of which BDT "&TEXT((SUMIFS(Purchase_Register!$AK$6:$AK$205,Purchase_Register!$AP$6:$AP$205,">0"))/100000,"#,##0.00")&" Lakh is overdue." -> ▸ Spend: BDT 565.19 Lakh committed on 39 POs — 60% paid; BDT 226.72 Lakh outstanding, of which BDT 33.24 Lakh is overdue.
A23: ="▸ Concentration: largest supplier is "&IFERROR(INDEX(Supplier_Scorecard!$A$5:$A$34,MATCH(MAX(Supplier_Scorecard!$D$5:$D$34),Supplier_Scorecard!$D$5:$D$34,0)),"-")&" with "&TEXT(MAX(Supplier_Scorecard!$D$5:$D$34),"0%")&" of spend — "&LOWER(Supplier_Scorecard!$C$41)&" (HHI "&TEXT(Supplier_Scorecard!$C$40,"#,##0")&"). Top category: "&Spend_Analysis!$B$6&" at "&TEXT(N(Spend_Analysis!$F$6),"0%")&"; "&COUNTIF(Spend_Analysis!$H$6:$H$25,"A")&" A-class categories carry "&TEXT(SUMIF(Spend_Analysis!$H$6:$H$25,"A",Spend_Analysis!$F$6:$F$25),"0%")&" of spend." -> ▸ Concentration: largest supplier is Savar Leather Works Ltd with 32% of spend — moderately concentrated (HHI 1,959). Top category: Leather & Upper at 32%; 4 A-class categories carry 89% of spend.
A24: ="▸ Supplier performance: "&COUNTIF(Supplier_Scorecard!$R$5:$R$34,"A*")&" rated A-Preferred, "&COUNTIF(Supplier_Scorecard!$R$5:$R$34,"B*")&" B-Approved, "&COUNTIF(Supplier_Scorecard!$R$5:$R$34,"C*")&" C-Review. "&IF(COUNT(Supplier_Scorecard!$Q$5:$Q$34)=0,"No supplier scored yet.","Best: "&INDEX(Supplier_Scorecard!$A$5:$A$34,MATCH(MAX(Supplier_Scorecard!$Q$5:$Q$34),Supplier_Scorecard!$Q$5:$Q$34,0))&" ("&MAX(Supplier_Scorecard!$Q$5:$Q$34)&"); weakest: "&INDEX(Supplier_Scorecard!$A$5:$A$34,MATCH(MIN(Supplier_Scorecard!$Q$5:$Q$34),Supplier_Scorecard!$Q$5:$Q$34,0))&" ("&MIN(Supplier_Scorecard!$Q$5:$Q$34)&").") -> ▸ Supplier performance: 3 rated A-Preferred, 4 B-Approved, 3 C-Review. Best: Chattogram Packaging Ltd (100); weakest: Gazipur Chem Trade (51).
A25: ="▸ Delivery: OTIF "&TEXT(IFERROR(COUNTIF(Purchase_Register!$BE$6:$BE$205,"OTIF")/COUNTIF(Purchase_Register!$BE$6:$BE$205,"*OTIF"),0),"0%")&", in-full "&TEXT(IFERROR(COUNTIFS(Purchase_Register!$BE$6:$BE$205,"*OTIF",Purchase_Register!$AX$6:$AX$205,"All In-house*")/COUNTIF(Purchase_Register!$BE$6:$BE$205,"*OTIF"),0),"0%")&", average lead time "&TEXT(IFERROR(AVERAGE(Purchase_Register!$BB$6:$BB$205),0),"0")&" days. "&COUNTIFS(Purchase_Register!$O$6:$O$205,"<>",Purchase_Register!$AY$6:$AY$205,"",Purchase_Register!$BD$6:$BD$205,">0")&" open PO(s) are late; BDT "&TEXT((SUMIFS(Purchase_Register!$AW$6:$AW$205,Purchase_Register!$AY$6:$AY$205,""))/100000,"#,##0.00")&" Lakh of material still to come in-house; "&COUNTIF(Purchase_Register!$AX$6:$AX$205,"Short Closed*")&" line(s) short-closed." -> ▸ Delivery: OTIF 50%, in-full 79%, average lead time 22 days. 0 open PO(s) are late; BDT 101.06 Lakh of material still to come in-house; 7 line(s) short-closed.
A26: ="▸ Budget & price: "&COUNTIF(Budget_Control!$M$5:$M$24,"Over Budget")&" department(s) over budget, "&COUNTIF(Budget_Control!$M$5:$M$24,"Watch")&" on watch (overall "&TEXT(IFERROR(Budget_Control!$I$25/Budget_Control!$H$25,0),"0%")&" used). Buying vs budget price: BDT "&TEXT((-SUMIF(Purchase_Register!$AA$6:$AA$205,"<0"))/100000,"#,##0.00")&" Lakh saved, BDT "&TEXT((SUMIF(Purchase_Register!$AA$6:$AA$205,">0"))/100000,"#,##0.00")&" Lakh overspent; "&COUNTIF(Purchase_Register!$Z$6:$Z$205,">0")&" line(s) bought dearer than the previous PO." -> ▸ Budget & price: 1 department(s) over budget, 1 on watch (overall 44% used). Buying vs budget price: BDT 3.73 Lakh saved, BDT 13.42 Lakh overspent; 6 line(s) bought dearer than the previous PO.
A27: ="▸ Cash & risk: BDT "&TEXT((SUM(Purchase_Register!$AL$6:$AL$205))/100000,"#,##0.00")&" Lakh paid ahead of goods received; "&COUNTIF(Purchase_Register!$BL$6:$BL$205,"High")&" high, "&COUNTIF(Purchase_Register!$BL$6:$BL$205,"Medium")&" medium and "&COUNTIF(Purchase_Register!$BL$6:$BL$205,"Low")&" low priority action line(s) open; "&COUNTIFS(Purchase_Register!$O$6:$O$205,"<>",Purchase_Register!$K$6:$K$205,"<>Approved")&" PO(s) without approval." -> ▸ Cash & risk: BDT 42.79 Lakh paid ahead of goods received; 12 high, 7 medium and 3 low priority action line(s) open; 0 PO(s) without approval.
A139: CHART DATA (auto-calculated — feeds the charts above)
A140: Category | B140: Committed (Lakh) | C140: Paid (Lakh) | D140: Outstanding (Lakh) | F140: Spend Type | G140: Committed (Lakh) | I140: Finance Status | J140: PO Lines | K140: Value (Lakh) | M140: Month | N140: PO Value (Lakh) | O140: Paid (Lakh) | P140: Due (Lakh) | R140: Supplier (top 10 by spend) | S140: Spend (Lakh) | T140: OTIF % | U140: Score
A141: =Spend_Analysis!B6 -> Leather & Upper | B141: =IF($A141="","",SUMIFS(Purchase_Register!$AD$6:$AD$205,Purchase_Register!$F$6:$F$205,$A141)/100000) -> 178.29948 | C141: =IF($A141="","",SUMIFS(Purchase_Register!$AI$6:$AI$205,Purchase_Register!$F$6:$F$205,$A141)/100000) -> 119.63533 | D141: =IF($A141="","",SUMIFS(Purchase_Register!$AK$6:$AK$205,Purchase_Register!$F$6:$F$205,$A141)/100000) -> 58.664154 | F141: OPEX | G141: =SUMIFS(Purchase_Register!$AD$6:$AD$205,Purchase_Register!$H$6:$H$205,$F141)/100000 -> 439.64954 | I141: Not Paid | J141: =COUNTIF(Purchase_Register!$AM$6:$AM$205,$I141) -> 5 | K141: =SUMIFS(Purchase_Register!$AD$6:$AD$205,Purchase_Register!$AM$6:$AM$205,$I141)/100000 -> 44.915228 | M141: =Cash_Forecast!C5 -> Jul-26 | N141: =Cash_Forecast!F5/100000 -> 49.330286 | O141: =Cash_Forecast!I5/100000 -> 33.576362 | P141: =Cash_Forecast!J5/100000 -> 0 | R141: =INDEX(Supplier_Scorecard!$A$5:$A$34,MATCH(LARGE(Supplier_Scorecard!$S$5:$S$34,1),Supplier_Scorecard!$S$5:$S$34,0))&"" -> Savar Leather Works Ltd | S141: =IF($R141="","",N(INDEX(Supplier_Scorecard!$C$5:$C$34,MATCH(LARGE(Supplier_Scorecard!$S$5:$S$34,1),Supplier_Scorecard!$S$5:$S$34,0)))/100000) -> 178.29948 | T141: =IF($R141="","",INDEX(Supplier_Scorecard!$H$5:$H$34,MATCH(LARGE(Supplier_Scorecard!$S$5:$S$34,1),Supplier_Scorecard!$S$5:$S$34,0))) -> 0.6 | U141: =IF($R141="","",INDEX(Supplier_Scorecard!$Q$5:$Q$34,MATCH(LARGE(Supplier_Scorecard!$S$5:$S$34,1),Supplier_Scorecard!$S$5:$S$34,0))) -> 66
A142: =Spend_Analysis!B7 -> Machinery & Equipment | B142: =IF($A142="","",SUMIFS(Purchase_Register!$AD$6:$AD$205,Purchase_Register!$F$6:$F$205,$A142)/100000) -> 117.92226 | C142: =IF($A142="","",SUMIFS(Purchase_Register!$AI$6:$AI$205,Purchase_Register!$F$6:$F$205,$A142)/100000) -> 66.998694 | D142: =IF($A142="","",SUMIFS(Purchase_Register!$AK$6:$AK$205,Purchase_Register!$F$6:$F$205,$A142)/100000) -> 50.923564 | F142: CAPEX | G142: =SUMIFS(Purchase_Register!$AD$6:$AD$205,Purchase_Register!$H$6:$H$205,$F142)/100000 -> 125.54046 | I142: Initial / Advance Paid | J142: =COUNTIF(Purchase_Register!$AM$6:$AM$205,$I142) -> 9 | K142: =SUMIFS(Purchase_Register!$AD$6:$AD$205,Purchase_Register!$AM$6:$AM$205,$I142)/100000 -> 182.63263 | M142: =Cash_Forecast!C6 -> Aug-26 | N142: =Cash_Forecast!F6/100000 -> 165.19154 | O142: =Cash_Forecast!I6/100000 -> 116.03703 | P142: =Cash_Forecast!J6/100000 -> 14.83293 | R142: =INDEX(Supplier_Scorecard!$A$5:$A$34,MATCH(LARGE(Supplier_Scorecard!$S$5:$S$34,2),Supplier_Scorecard!$S$5:$S$34,0))&"" -> Dongguan Sole Tech Co. | S142: =IF($R142="","",N(INDEX(Supplier_Scorecard!$C$5:$C$34,MATCH(LARGE(Supplier_Scorecard!$S$5:$S$34,2),Supplier_Scorecard!$S$5:$S$34,0)))/100000) -> 105.89897 | T142: =IF($R142="","",INDEX(Supplier_Scorecard!$H$5:$H$34,MATCH(LARGE(Supplier_Scorecard!$S$5:$S$34,2),Supplier_Scorecard!$S$5:$S$34,0))) -> 1 | U142: =IF($R142="","",INDEX(Supplier_Scorecard!$Q$5:$Q$34,MATCH(LARGE(Supplier_Scorecard!$S$5:$S$34,2),Supplier_Scorecard!$S$5:$S$34,0))) -> 98
A143: =Spend_Analysis!B8 -> Sole & Bottom | B143: =IF($A143="","",SUMIFS(Purchase_Register!$AD$6:$AD$205,Purchase_Register!$F$6:$F$205,$A143)/100000) -> 103.98765 | C143: =IF($A143="","",SUMIFS(Purchase_Register!$AI$6:$AI$205,Purchase_Register!$F$6:$F$205,$A143)/100000) -> 35.31309 | D143: =IF($A143="","",SUMIFS(Purchase_Register!$AK$6:$AK$205,Purchase_Register!$F$6:$F$205,$A143)/100000) -> 68.674562 | I143: Partially Paid | J143: =COUNTIF(Purchase_Register!$AM$6:$AM$205,$I143) -> 5 | K143: =SUMIFS(Purchase_Register!$AD$6:$AD$205,Purchase_Register!$AM$6:$AM$205,$I143)/100000 -> 33.66531 | M143: =Cash_Forecast!C7 -> Sep-26 | N143: =Cash_Forecast!F7/100000 -> 95.140112 | O143: =Cash_Forecast!I7/100000 -> 93.218794 | P143: =Cash_Forecast!J7/100000 -> 16.955387 | R143: =INDEX(Supplier_Scorecard!$A$5:$A$34,MATCH(LARGE(Supplier_Scorecard!$S$5:$S$34,3),Supplier_Scorecard!$S$5:$S$34,0))&"" -> Jiangsu Footwear Machinery Co. | S143: =IF($R143="","",N(INDEX(Supplier_Scorecard!$C$5:$C$34,MATCH(LARGE(Supplier_Scorecard!$S$5:$S$34,3),Supplier_Scorecard!$S$5:$S$34,0)))/100000) -> 101.84713 | T143: =IF($R143="","",INDEX(Supplier_Scorecard!$H$5:$H$34,MATCH(LARGE(Supplier_Scorecard!$S$5:$S$34,3),Supplier_Scorecard!$S$5:$S$34,0))) -> 0 | U143: =IF($R143="","",INDEX(Supplier_Scorecard!$Q$5:$Q$34,MATCH(LARGE(Supplier_Scorecard!$S$5:$S$34,3),Supplier_Scorecard!$S$5:$S$34,0))) -> 53
A144: =Spend_Analysis!B9 -> Synthetic & Textile | B144: =IF($A144="","",SUMIFS(Purchase_Register!$AD$6:$AD$205,Purchase_Register!$F$6:$F$205,$A144)/100000) -> 101.05757 | C144: =IF($A144="","",SUMIFS(Purchase_Register!$AI$6:$AI$205,Purchase_Register!$F$6:$F$205,$A144)/100000) -> 81.013451 | D144: =IF($A144="","",SUMIFS(Purchase_Register!$AK$6:$AK$205,Purchase_Register!$F$6:$F$205,$A144)/100000) -> 20.044116 | F144: Stage | G144: Lines | I144: Fully Paid | J144: =COUNTIF(Purchase_Register!$AM$6:$AM$205,$I144) -> 20 | K144: =SUMIFS(Purchase_Register!$AD$6:$AD$205,Purchase_Register!$AM$6:$AM$205,$I144)/100000 -> 244.95765 | M144: =Cash_Forecast!C8 -> Oct-26 | N144: =Cash_Forecast!F8/100000 -> 68.928231 | O144: =Cash_Forecast!I8/100000 -> 39.865209 | P144: =Cash_Forecast!J8/100000 -> 63.374494 | R144: =INDEX(Supplier_Scorecard!$A$5:$A$34,MATCH(LARGE(Supplier_Scorecard!$S$5:$S$34,4),Supplier_Scorecard!$S$5:$S$34,0))&"" -> Bengal Sole Industries | S144: =IF($R144="","",N(INDEX(Supplier_Scorecard!$C$5:$C$34,MATCH(LARGE(Supplier_Scorecard!$S$5:$S$34,4),Supplier_Scorecard!$S$5:$S$34,0)))/100000) -> 86.46225 | T144: =IF($R144="","",INDEX(Supplier_Scorecard!$H$5:$H$34,MATCH(LARGE(Supplier_Scorecard!$S$5:$S$34,4),Supplier_Scorecard!$S$5:$S$34,0))) -> 0.5 | U144: =IF($R144="","",INDEX(Supplier_Scorecard!$Q$5:$Q$34,MATCH(LARGE(Supplier_Scorecard!$S$5:$S$34,4),Supplier_Scorecard!$S$5:$S$34,0))) -> 64
A145: =Spend_Analysis!B10 -> Chemicals & Adhesives | B145: =IF($A145="","",SUMIFS(Purchase_Register!$AD$6:$AD$205,Purchase_Register!$F$6:$F$205,$A145)/100000) -> 23.8392 | C145: =IF($A145="","",SUMIFS(Purchase_Register!$AI$6:$AI$205,Purchase_Register!$F$6:$F$205,$A145)/100000) -> 9.355725 | D145: =IF($A145="","",SUMIFS(Purchase_Register!$AK$6:$AK$205,Purchase_Register!$F$6:$F$205,$A145)/100000) -> 14.483475 | F145: Awaiting Approval | G145: =COUNTIF(Purchase_Register!$BI$6:$BI$205,$F145) -> 3 | M145: =Cash_Forecast!C9 -> Nov-26 | N145: =Cash_Forecast!F9/100000 -> 0 | O145: =Cash_Forecast!I9/100000 -> 0 | P145: =Cash_Forecast!J9/100000 -> 72.534849 | R145: =INDEX(Supplier_Scorecard!$A$5:$A$34,MATCH(LARGE(Supplier_Scorecard!$S$5:$S$34,5),Supplier_Scorecard!$S$5:$S$34,0))&"" -> Dhaka Spares & Tools | S145: =IF($R145="","",N(INDEX(Supplier_Scorecard!$C$5:$C$34,MATCH(LARGE(Supplier_Scorecard!$S$5:$S$34,5),Supplier_Scorecard!$S$5:$S$34,0)))/100000) -> 25.885323 | T145: =IF($R145="","",INDEX(Supplier_Scorecard!$H$5:$H$34,MATCH(LARGE(Supplier_Scorecard!$S$5:$S$34,5),Supplier_Scorecard!$S$5:$S$34,0))) -> 0.33333333 | U145: =IF($R145="","",INDEX(Supplier_Scorecard!$Q$5:$Q$34,MATCH(LARGE(Supplier_Scorecard!$S$5:$S$34,5),Supplier_Scorecard!$S$5:$S$34,0))) -> 65
A146: =Spend_Analysis!B11 -> Trims & Accessories | B146: =IF($A146="","",SUMIFS(Purchase_Register!$AD$6:$AD$205,Purchase_Register!$F$6:$F$205,$A146)/100000) -> 13.310388 | C146: =IF($A146="","",SUMIFS(Purchase_Register!$AI$6:$AI$205,Purchase_Register!$F$6:$F$205,$A146)/100000) -> 7.286202 | D146: =IF($A146="","",SUMIFS(Purchase_Register!$AK$6:$AK$205,Purchase_Register!$F$6:$F$205,$A146)/100000) -> 6.024186 | F146: Approved - PO Pending | G146: =COUNTIF(Purchase_Register!$BI$6:$BI$205,$F146) -> 2 | I146: Aging Bucket | J146: Outstanding (Lakh) | M146: =Cash_Forecast!C10 -> Dec-26 | N146: =Cash_Forecast!F10/100000 -> 0 | O146: =Cash_Forecast!I10/100000 -> 0 | P146: =Cash_Forecast!J10/100000 -> 0 | R146: =INDEX(Supplier_Scorecard!$A$5:$A$34,MATCH(LARGE(Supplier_Scorecard!$S$5:$S$34,6),Supplier_Scorecard!$S$5:$S$34,0))&"" -> Gazipur Chem Trade | S146: =IF($R146="","",N(INDEX(Supplier_Scorecard!$C$5:$C$34,MATCH(LARGE(Supplier_Scorecard!$S$5:$S$34,6),Supplier_Scorecard!$S$5:$S$34,0)))/100000) -> 23.8392 | T146: =IF($R146="","",INDEX(Supplier_Scorecard!$H$5:$H$34,MATCH(LARGE(Supplier_Scorecard!$S$5:$S$34,6),Supplier_Scorecard!$S$5:$S$34,0))) -> 0.5 | U146: =IF($R146="","",INDEX(Supplier_Scorecard!$Q$5:$Q$34,MATCH(LARGE(Supplier_Scorecard!$S$5:$S$34,6),Supplier_Scorecard!$S$5:$S$34,0))) -> 51
A147: =Spend_Analysis!B12 -> Packaging | B147: =IF($A147="","",SUMIFS(Purchase_Register!$AD$6:$AD$205,Purchase_Register!$F$6:$F$205,$A147)/100000) -> 9.345063 | C147: =IF($A147="","",SUMIFS(Purchase_Register!$AI$6:$AI$205,Purchase_Register!$F$6:$F$205,$A147)/100000) -> 9.345063 | D147: =IF($A147="","",SUMIFS(Purchase_Register!$AK$6:$AK$205,Purchase_Register!$F$6:$F$205,$A147)/100000) -> 0 | F147: PO Issued - Awaiting Delivery | G147: =COUNTIF(Purchase_Register!$BI$6:$BI$205,$F147) -> 4 | I147: Not Yet Due | J147: =SUMIFS(Purchase_Register!$AK$6:$AK$205,Purchase_Register!$AQ$6:$AQ$205,$I147)/100000 -> 134.46003 | M147: =Cash_Forecast!C11 -> Jan-27 | N147: =Cash_Forecast!F11/100000 -> 0 | O147: =Cash_Forecast!I11/100000 -> 0 | P147: =Cash_Forecast!J11/100000 -> 0 | R147: =INDEX(Supplier_Scorecard!$A$5:$A$34,MATCH(LARGE(Supplier_Scorecard!$S$5:$S$34,7),Supplier_Scorecard!$S$5:$S$34,0))&"" -> Delta Thread & Trims | S147: =IF($R147="","",N(INDEX(Supplier_Scorecard!$C$5:$C$34,MATCH(LARGE(Supplier_Scorecard!$S$5:$S$34,7),Supplier_Scorecard!$S$5:$S$34,0)))/100000) -> 13.310388 | T147: =IF($R147="","",INDEX(Supplier_Scorecard!$H$5:$H$34,MATCH(LARGE(Supplier_Scorecard!$S$5:$S$34,7),Supplier_Scorecard!$S$5:$S$34,0))) -> 0.4 | U147: =IF($R147="","",INDEX(Supplier_Scorecard!$Q$5:$Q$34,MATCH(LARGE(Supplier_Scorecard!$S$5:$S$34,7),Supplier_Scorecard!$S$5:$S$34,0))) -> 65
A148: =Spend_Analysis!B13 -> IT Equipment | B148: =IF($A148="","",SUMIFS(Purchase_Register!$AD$6:$AD$205,Purchase_Register!$F$6:$F$205,$A148)/100000) -> 7.6182015 | C148: =IF($A148="","",SUMIFS(Purchase_Register!$AI$6:$AI$205,Purchase_Register!$F$6:$F$205,$A148)/100000) -> 3.8091008 | D148: =IF($A148="","",SUMIFS(Purchase_Register!$AK$6:$AK$205,Purchase_Register!$F$6:$F$205,$A148)/100000) -> 3.8091007 | F148: Receiving In-house | G148: =COUNTIF(Purchase_Register!$BI$6:$BI$205,$F148) -> 1 | I148: 1-30 Days | J148: =SUMIFS(Purchase_Register!$AK$6:$AK$205,Purchase_Register!$AQ$6:$AQ$205,$I148)/100000 -> 13.802777 | M148: =Cash_Forecast!C12 -> Feb-27 | N148: =Cash_Forecast!F12/100000 -> 0 | O148: =Cash_Forecast!I12/100000 -> 0 | P148: =Cash_Forecast!J12/100000 -> 0 | R148: =INDEX(Supplier_Scorecard!$A$5:$A$34,MATCH(LARGE(Supplier_Scorecard!$S$5:$S$34,8),Supplier_Scorecard!$S$5:$S$34,0))&"" -> Narayanganj Board Mills | S148: =IF($R148="","",N(INDEX(Supplier_Scorecard!$C$5:$C$34,MATCH(LARGE(Supplier_Scorecard!$S$5:$S$34,8),Supplier_Scorecard!$S$5:$S$34,0)))/100000) -> 12.684 | T148: =IF($R148="","",INDEX(Supplier_Scorecard!$H$5:$H$34,MATCH(LARGE(Supplier_Scorecard!$S$5:$S$34,8),Supplier_Scorecard!$S$5:$S$34,0))) -> 0 | U148: =IF($R148="","",INDEX(Supplier_Scorecard!$Q$5:$Q$34,MATCH(LARGE(Supplier_Scorecard!$S$5:$S$34,8),Supplier_Scorecard!$S$5:$S$34,0))) -> 59
A149: =Spend_Analysis!B14 -> Safety & Facility | B149: =IF($A149="","",SUMIFS(Purchase_Register!$AD$6:$AD$205,Purchase_Register!$F$6:$F$205,$A149)/100000) -> 6.18125 | C149: =IF($A149="","",SUMIFS(Purchase_Register!$AI$6:$AI$205,Purchase_Register!$F$6:$F$205,$A149)/100000) -> 3.65801 | D149: =IF($A149="","",SUMIFS(Purchase_Register!$AK$6:$AK$205,Purchase_Register!$F$6:$F$205,$A149)/100000) -> 2.52324 | F149: In-house Closed - Payment Due | G149: =COUNTIF(Purchase_Register!$BI$6:$BI$205,$F149) -> 16 | I149: 31-60 Days | J149: =SUMIFS(Purchase_Register!$AK$6:$AK$205,Purchase_Register!$AQ$6:$AQ$205,$I149)/100000 -> 5.688675 | M149: =Cash_Forecast!C13 -> Mar-27 | N149: =Cash_Forecast!F13/100000 -> 0 | O149: =Cash_Forecast!I13/100000 -> 0 | P149: =Cash_Forecast!J13/100000 -> 0 | R149: =INDEX(Supplier_Scorecard!$A$5:$A$34,MATCH(LARGE(Supplier_Scorecard!$S$5:$S$34,9),Supplier_Scorecard!$S$5:$S$34,0))&"" -> Chattogram Packaging Ltd | S149: =IF($R149="","",N(INDEX(Supplier_Scorecard!$C$5:$C$34,MATCH(LARGE(Supplier_Scorecard!$S$5:$S$34,9),Supplier_Scorecard!$S$5:$S$34,0)))/100000) -> 9.345063 | T149: =IF($R149="","",INDEX(Supplier_Scorecard!$H$5:$H$34,MATCH(LARGE(Supplier_Scorecard!$S$5:$S$34,9),Supplier_Scorecard!$S$5:$S$34,0))) -> 1 | U149: =IF($R149="","",INDEX(Supplier_Scorecard!$Q$5:$Q$34,MATCH(LARGE(Supplier_Scorecard!$S$5:$S$34,9),Supplier_Scorecard!$S$5:$S$34,0))) -> 100
A150: =Spend_Analysis!B15 -> Spare Parts | B150: =IF($A150="","",SUMIFS(Purchase_Register!$AD$6:$AD$205,Purchase_Register!$F$6:$F$205,$A150)/100000) -> 3.628942 | C150: =IF($A150="","",SUMIFS(Purchase_Register!$AI$6:$AI$205,Purchase_Register!$F$6:$F$205,$A150)/100000) -> 2.058496 | D150: =IF($A150="","",SUMIFS(Purchase_Register!$AK$6:$AK$205,Purchase_Register!$F$6:$F$205,$A150)/100000) -> 1.570446 | F150: Closed | G150: =COUNTIF(Purchase_Register!$BI$6:$BI$205,$F150) -> 18 | I150: 61-90 Days | J150: =SUMIFS(Purchase_Register!$AK$6:$AK$205,Purchase_Register!$AQ$6:$AQ$205,$I150)/100000 -> 13.74618 | M150: =Cash_Forecast!C14 -> Apr-27 | N150: =Cash_Forecast!F14/100000 -> 0 | O150: =Cash_Forecast!I14/100000 -> 0 | P150: =Cash_Forecast!J14/100000 -> 0 | R150: =INDEX(Supplier_Scorecard!$A$5:$A$34,MATCH(LARGE(Supplier_Scorecard!$S$5:$S$34,10),Supplier_Scorecard!$S$5:$S$34,0))&"" -> Tech Point BD | S150: =IF($R150="","",N(INDEX(Supplier_Scorecard!$C$5:$C$34,MATCH(LARGE(Supplier_Scorecard!$S$5:$S$34,10),Supplier_Scorecard!$S$5:$S$34,0)))/100000) -> 7.6182015 | T150: =IF($R150="","",INDEX(Supplier_Scorecard!$H$5:$H$34,MATCH(LARGE(Supplier_Scorecard!$S$5:$S$34,10),Supplier_Scorecard!$S$5:$S$34,0))) -> 1 | U150: =IF($R150="","",INDEX(Supplier_Scorecard!$Q$5:$Q$34,MATCH(LARGE(Supplier_Scorecard!$S$5:$S$34,10),Supplier_Scorecard!$S$5:$S$34,0))) -> 88
F151: Rejected | G151: =COUNTIF(Purchase_Register!$BI$6:$BI$205,$F151) -> 1 | I151: 90+ Days | J151: =SUMIFS(Purchase_Register!$AK$6:$AK$205,Purchase_Register!$AQ$6:$AQ$205,$I151)/100000 -> 0 | M151: =Cash_Forecast!C15 -> May-27 | N151: =Cash_Forecast!F15/100000 -> 0 | O151: =Cash_Forecast!I15/100000 -> 0 | P151: =Cash_Forecast!J15/100000 -> 0
I152: No Due Date | J152: =SUMIFS(Purchase_Register!$AK$6:$AK$205,Purchase_Register!$AQ$6:$AQ$205,$I152)/100000 -> 59.019183 | M152: =Cash_Forecast!C16 -> Jun-27 | N152: =Cash_Forecast!F16/100000 -> 0 | O152: =Cash_Forecast!I16/100000 -> 0 | P152: =Cash_Forecast!J16/100000 -> 0
M153: Department | N153: Budget (Lakh) | O153: Committed (Lakh) | P153: Utilisation
M154: =INDEX(Budget_Control!$A$5:$A$24,MATCH(LARGE(Budget_Control!$N$5:$N$24,1),Budget_Control!$N$5:$N$24,0))&"" -> Lasting & Assembly | N154: =IF($M154="","",N(INDEX(Budget_Control!$H$5:$H$24,MATCH(LARGE(Budget_Control!$N$5:$N$24,1),Budget_Control!$N$5:$N$24,0)))/100000) -> 340 | O154: =IF($M154="","",N(INDEX(Budget_Control!$I$5:$I$24,MATCH(LARGE(Budget_Control!$N$5:$N$24,1),Budget_Control!$N$5:$N$24,0)))/100000) -> 100.69343 | P154: =IF(OR($M154="",N(N154)=0),"",O154/N154) -> 0.29615714
M155: =INDEX(Budget_Control!$A$5:$A$24,MATCH(LARGE(Budget_Control!$N$5:$N$24,2),Budget_Control!$N$5:$N$24,0))&"" -> Cutting | N155: =IF($M155="","",N(INDEX(Budget_Control!$H$5:$H$24,MATCH(LARGE(Budget_Control!$N$5:$N$24,2),Budget_Control!$N$5:$N$24,0)))/100000) -> 320 | O155: =IF($M155="","",N(INDEX(Budget_Control!$I$5:$I$24,MATCH(LARGE(Budget_Control!$N$5:$N$24,2),Budget_Control!$N$5:$N$24,0)))/100000) -> 279.35705 | P155: =IF(OR($M155="",N(N155)=0),"",O155/N155) -> 0.87299078
M156: =INDEX(Budget_Control!$A$5:$A$24,MATCH(LARGE(Budget_Control!$N$5:$N$24,3),Budget_Control!$N$5:$N$24,0))&"" -> Stitching | N156: =IF($M156="","",N(INDEX(Budget_Control!$H$5:$H$24,MATCH(LARGE(Budget_Control!$N$5:$N$24,3),Budget_Control!$N$5:$N$24,0)))/100000) -> 150 | O156: =IF($M156="","",N(INDEX(Budget_Control!$I$5:$I$24,MATCH(LARGE(Budget_Control!$N$5:$N$24,3),Budget_Control!$N$5:$N$24,0)))/100000) -> 13.310388 | P156: =IF(OR($M156="",N(N156)=0),"",O156/N156) -> 0.08873592
M157: =INDEX(Budget_Control!$A$5:$A$24,MATCH(LARGE(Budget_Control!$N$5:$N$24,4),Budget_Control!$N$5:$N$24,0))&"" -> Finishing & Packing | N157: =IF($M157="","",N(INDEX(Budget_Control!$H$5:$H$24,MATCH(LARGE(Budget_Control!$N$5:$N$24,4),Budget_Control!$N$5:$N$24,0)))/100000) -> 140 | O157: =IF($M157="","",N(INDEX(Budget_Control!$I$5:$I$24,MATCH(LARGE(Budget_Control!$N$5:$N$24,4),Budget_Control!$N$5:$N$24,0)))/100000) -> 9.345063 | P157: =IF(OR($M157="",N(N157)=0),"",O157/N157) -> 0.06675045
M158: =INDEX(Budget_Control!$A$5:$A$24,MATCH(LARGE(Budget_Control!$N$5:$N$24,5),Budget_Control!$N$5:$N$24,0))&"" -> Maintenance | N158: =IF($M158="","",N(INDEX(Budget_Control!$H$5:$H$24,MATCH(LARGE(Budget_Control!$N$5:$N$24,5),Budget_Control!$N$5:$N$24,0)))/100000) -> 100 | O158: =IF($M158="","",N(INDEX(Budget_Control!$I$5:$I$24,MATCH(LARGE(Budget_Control!$N$5:$N$24,5),Budget_Control!$N$5:$N$24,0)))/100000) -> 120.38323 | P158: =IF(OR($M158="",N(N158)=0),"",O158/N158) -> 1.2038323
M159: =INDEX(Budget_Control!$A$5:$A$24,MATCH(LARGE(Budget_Control!$N$5:$N$24,6),Budget_Control!$N$5:$N$24,0))&"" -> Product Development | N159: =IF($M159="","",N(INDEX(Budget_Control!$H$5:$H$24,MATCH(LARGE(Budget_Control!$N$5:$N$24,6),Budget_Control!$N$5:$N$24,0)))/100000) -> 60 | O159: =IF($M159="","",N(INDEX(Budget_Control!$I$5:$I$24,MATCH(LARGE(Budget_Control!$N$5:$N$24,6),Budget_Control!$N$5:$N$24,0)))/100000) -> 0 | P159: =IF(OR($M159="",N(N159)=0),"",O159/N159) -> 0
M160: =INDEX(Budget_Control!$A$5:$A$24,MATCH(LARGE(Budget_Control!$N$5:$N$24,7),Budget_Control!$N$5:$N$24,0))&"" -> IT | N160: =IF($M160="","",N(INDEX(Budget_Control!$H$5:$H$24,MATCH(LARGE(Budget_Control!$N$5:$N$24,7),Budget_Control!$N$5:$N$24,0)))/100000) -> 30 | O160: =IF($M160="","",N(INDEX(Budget_Control!$I$5:$I$24,MATCH(LARGE(Budget_Control!$N$5:$N$24,7),Budget_Control!$N$5:$N$24,0)))/100000) -> 7.6182015 | P160: =IF(OR($M160="",N(N160)=0),"",O160/N160) -> 0.25394005
M161: =INDEX(Budget_Control!$A$5:$A$24,MATCH(LARGE(Budget_Control!$N$5:$N$24,8),Budget_Control!$N$5:$N$24,0))&"" -> Store & Warehouse | N161: =IF($M161="","",N(INDEX(Budget_Control!$H$5:$H$24,MATCH(LARGE(Budget_Control!$N$5:$N$24,8),Budget_Control!$N$5:$N$24,0)))/100000) -> 30 | O161: =IF($M161="","",N(INDEX(Budget_Control!$I$5:$I$24,MATCH(LARGE(Budget_Control!$N$5:$N$24,8),Budget_Control!$N$5:$N$24,0)))/100000) -> 0 | P161: =IF(OR($M161="",N(N161)=0),"",O161/N161) -> 0
M162: =INDEX(Budget_Control!$A$5:$A$24,MATCH(LARGE(Budget_Control!$N$5:$N$24,9),Budget_Control!$N$5:$N$24,0))&"" -> Compliance & HSE | N162: =IF($M162="","",N(INDEX(Budget_Control!$H$5:$H$24,MATCH(LARGE(Budget_Control!$N$5:$N$24,9),Budget_Control!$N$5:$N$24,0)))/100000) -> 25 | O162: =IF($M162="","",N(INDEX(Budget_Control!$I$5:$I$24,MATCH(LARGE(Budget_Control!$N$5:$N$24,9),Budget_Control!$N$5:$N$24,0)))/100000) -> 6.18125 | P162: =IF(OR($M162="",N(N162)=0),"",O162/N162) -> 0.24725
M163: =INDEX(Budget_Control!$A$5:$A$24,MATCH(LARGE(Budget_Control!$N$5:$N$24,10),Budget_Control!$N$5:$N$24,0))&"" -> Admin | N163: =IF($M163="","",N(INDEX(Budget_Control!$H$5:$H$24,MATCH(LARGE(Budget_Control!$N$5:$N$24,10),Budget_Control!$N$5:$N$24,0)))/100000) -> 20 | O163: =IF($M163="","",N(INDEX(Budget_Control!$I$5:$I$24,MATCH(LARGE(Budget_Control!$N$5:$N$24,10),Budget_Control!$N$5:$N$24,0)))/100000) -> 0 | P163: =IF(OR($M163="",N(N163)=0),"",O163/N163) -> 0

Sheet Action_Tracker
A1: Action Tracker — what needs attention today
A2: Automatic list from the Purchase Register, sorted High → Medium → Low priority. Fix the cause in the register and the line drops off this list.
C3: High priority | E3: Medium priority | F3: Low priority | G3: Overdue payable (BDT) | I3: Paid ahead of receipt (BDT) | J3: Late open POs
C4: =COUNTIF(Purchase_Register!$BL$6:$BL$205,"High") -> 12 | E4: =COUNTIF(Purchase_Register!$BL$6:$BL$205,"Medium") -> 7 | F4: =COUNTIF(Purchase_Register!$BL$6:$BL$205,"Low") -> 3 | G4: =SUMIFS(Purchase_Register!$AK$6:$AK$205,Purchase_Register!$AP$6:$AP$205,">0") -> 3323763.2 | I4: =SUM(Purchase_Register!$AL$6:$AL$205) -> 4278510 | J4: =COUNTIFS(Purchase_Register!$O$6:$O$205,"<>",Purchase_Register!$AY$6:$AY$205,"",Purchase_Register!$BD$6:$BD$205,">0") -> 0
A6: # | B6: Reg. row | C6: Priority | D6: PR No | E6: Item / Material | F6: Supplier | G6: Department | H6: Current Stage | I6: Pending Material Status | J6: Outstanding Payable (BDT) | K6: Paid Ahead of Receipt (BDT) | L6: Action Required
A7: =IF(ROWS($A$7:A7)>COUNT(Purchase_Register!$BM$6:$BM$205),"",ROWS($A$7:A7)) -> 1 | B7: =IF($A7="","",MATCH(SMALL(Purchase_Register!$BM$6:$BM$205,$A7),Purchase_Register!$BM$6:$BM$205,0)) -> 2 | C7: =IF($B7="","",INDEX(Purchase_Register!$BL$6:$BL$205,$B7)&"") -> High | D7: =IF($B7="","",INDEX(Purchase_Register!$A$6:$A$205,$B7)&"") -> PSIL-PR-2026-0002 | E7: =IF($B7="","",INDEX(Purchase_Register!$E$6:$E$205,$B7)&"") -> Suede Split Leather | F7: =IF($B7="","",INDEX(Purchase_Register!$M$6:$M$205,$B7)&"") -> Savar Leather Works Ltd | G7: =IF($B7="","",INDEX(Purchase_Register!$C$6:$C$205,$B7)&"") -> Cutting | H7: =IF($B7="","",INDEX(Purchase_Register!$BI$6:$BI$205,$B7)&"") -> Closed | I7: =IF($B7="","",INDEX(Purchase_Register!$AX$6:$AX$205,$B7)&"") -> All In-house | J7: =IF($B7="","",N(INDEX(Purchase_Register!$AK$6:$AK$205,$B7))) -> 0 | K7: =IF($B7="","",N(INDEX(Purchase_Register!$AL$6:$AL$205,$B7))) -> 0 | L7: =IF($B7="","",INDEX(Purchase_Register!$BK$6:$BK$205,$B7)&"") -> QC rejected: return / replace;
A8: =IF(ROWS($A$7:A8)>COUNT(Purchase_Register!$BM$6:$BM$205),"",ROWS($A$7:A8)) -> 2 | B8: =IF($A8="","",MATCH(SMALL(Purchase_Register!$BM$6:$BM$205,$A8),Purchase_Register!$BM$6:$BM$205,0)) -> 5 | C8: =IF($B8="","",INDEX(Purchase_Register!$BL$6:$BL$205,$B8)&"") -> High | D8: =IF($B8="","",INDEX(Purchase_Register!$A$6:$A$205,$B8)&"") -> PSIL-PR-2026-0005 | E8: =IF($B8="","",INDEX(Purchase_Register!$E$6:$E$205,$B8)&"") -> Rubber Outsole – Men's Derby | F8: =IF($B8="","",INDEX(Purchase_Register!$M$6:$M$205,$B8)&"") -> Bengal Sole Industries | G8: =IF($B8="","",INDEX(Purchase_Register!$C$6:$C$205,$B8)&"") -> Lasting & Assembly | H8: =IF($B8="","",INDEX(Purchase_Register!$BI$6:$BI$205,$B8)&"") -> In-house Closed - Payment Due | I8: =IF($B8="","",INDEX(Purchase_Register!$AX$6:$AX$205,$B8)&"") -> Short Closed - 561 pair not received | J8: =IF($B8="","",N(INDEX(Purchase_Register!$AK$6:$AK$205,$B8))) -> 1074150 | K8: =IF($B8="","",N(INDEX(Purchase_Register!$AL$6:$AL$205,$B8))) -> 0 | L8: =IF($B8="","",INDEX(Purchase_Register!$BK$6:$BK$205,$B8)&"") -> Pay supplier: 71 days overdue; Short closed: claim balance / credit note;
A9: =IF(ROWS($A$7:A9)>COUNT(Purchase_Register!$BM$6:$BM$205),"",ROWS($A$7:A9)) -> 3 | B9: =IF($A9="","",MATCH(SMALL(Purchase_Register!$BM$6:$BM$205,$A9),Purchase_Register!$BM$6:$BM$205,0)) -> 8 | C9: =IF($B9="","",INDEX(Purchase_Register!$BL$6:$BL$205,$B9)&"") -> High | D9: =IF($B9="","",INDEX(Purchase_Register!$A$6:$A$205,$B9)&"") -> PSIL-PR-2026-0008 | E9: =IF($B9="","",INDEX(Purchase_Register!$E$6:$E$205,$B9)&"") -> PU Adhesive (Solvent Based) | F9: =IF($B9="","",INDEX(Purchase_Register!$M$6:$M$205,$B9)&"") -> Gazipur Chem Trade | G9: =IF($B9="","",INDEX(Purchase_Register!$C$6:$C$205,$B9)&"") -> Lasting & Assembly | H9: =IF($B9="","",INDEX(Purchase_Register!$BI$6:$BI$205,$B9)&"") -> Closed | I9: =IF($B9="","",INDEX(Purchase_Register!$AX$6:$AX$205,$B9)&"") -> Short Closed - 36 kg not received | J9: =IF($B9="","",N(INDEX(Purchase_Register!$AK$6:$AK$205,$B9))) -> 0 | K9: =IF($B9="","",N(INDEX(Purchase_Register!$AL$6:$AL$205,$B9))) -> 16680 | L9: =IF($B9="","",INDEX(Purchase_Register!$BK$6:$BK$205,$B9)&"") -> Short closed: claim balance / credit note BDT 16,680; QC rejected: return / replace;
A10: =IF(ROWS($A$7:A10)>COUNT(Purchase_Register!$BM$6:$BM$205),"",ROWS($A$7:A10)) -> 4 | B10: =IF($A10="","",MATCH(SMALL(Purchase_Register!$BM$6:$BM$205,$A10),Purchase_Register!$BM$6:$BM$205,0)) -> 10 | C10: =IF($B10="","",INDEX(Purchase_Register!$BL$6:$BL$205,$B10)&"") -> High | D10: =IF($B10="","",INDEX(Purchase_Register!$A$6:$A$205,$B10)&"") -> PSIL-PR-2026-0010 | E10: =IF($B10="","",INDEX(Purchase_Register!$E$6:$E$205,$B10)&"") -> Bonded Nylon Thread | F10: =IF($B10="","",INDEX(Purchase_Register!$M$6:$M$205,$B10)&"") -> Delta Thread & Trims | G10: =IF($B10="","",INDEX(Purchase_Register!$C$6:$C$205,$B10)&"") -> Stitching | H10: =IF($B10="","",INDEX(Purchase_Register!$BI$6:$BI$205,$B10)&"") -> In-house Closed - Payment Due | I10: =IF($B10="","",INDEX(Purchase_Register!$AX$6:$AX$205,$B10)&"") -> Short Closed - 49 cone not received | J10: =IF($B10="","",N(INDEX(Purchase_Register!$AK$6:$AK$205,$B10))) -> 300468 | K10: =IF($B10="","",N(INDEX(Purchase_Register!$AL$6:$AL$205,$B10))) -> 0 | L10: =IF($B10="","",INDEX(Purchase_Register!$BK$6:$BK$205,$B10)&"") -> Pay supplier: 70 days overdue; Short closed: claim balance / credit note;
A11: =IF(ROWS($A$7:A11)>COUNT(Purchase_Register!$BM$6:$BM$205),"",ROWS($A$7:A11)) -> 5 | B11: =IF($A11="","",MATCH(SMALL(Purchase_Register!$BM$6:$BM$205,$A11),Purchase_Register!$BM$6:$BM$205,0)) -> 11 | C11: =IF($B11="","",INDEX(Purchase_Register!$BL$6:$BL$205,$B11)&"") -> High | D11: =IF($B11="","",INDEX(Purchase_Register!$A$6:$A$205,$B11)&"") -> PSIL-PR-2026-0011 | E11: =IF($B11="","",INDEX(Purchase_Register!$E$6:$E$205,$B11)&"") -> Metal Eyelets & Hooks | F11: =IF($B11="","",INDEX(Purchase_Register!$M$6:$M$205,$B11)&"") -> Delta Thread & Trims | G11: =IF($B11="","",INDEX(Purchase_Register!$C$6:$C$205,$B11)&"") -> Stitching | H11: =IF($B11="","",INDEX(Purchase_Register!$BI$6:$BI$205,$B11)&"") -> In-house Closed - Payment Due | I11: =IF($B11="","",INDEX(Purchase_Register!$AX$6:$AX$205,$B11)&"") -> All In-house | J11: =IF($B11="","",N(INDEX(Purchase_Register!$AK$6:$AK$205,$B11))) -> 108675 | K11: =IF($B11="","",N(INDEX(Purchase_Register!$AL$6:$AL$205,$B11))) -> 0 | L11: =IF($B11="","",INDEX(Purchase_Register!$BK$6:$BK$205,$B11)&"") -> Pay supplier: 54 days overdue;
A12: =IF(ROWS($A$7:A12)>COUNT(Purchase_Register!$BM$6:$BM$205),"",ROWS($A$7:A12)) -> 6 | B12: =IF($A12="","",MATCH(SMALL(Purchase_Register!$BM$6:$BM$205,$A12),Purchase_Register!$BM$6:$BM$205,0)) -> 12 | C12: =IF($B12="","",INDEX(Purchase_Register!$BL$6:$BL$205,$B12)&"") -> High | D12: =IF($B12="","",INDEX(Purchase_Register!$A$6:$A$205,$B12)&"") -> PSIL-PR-2026-0012 | E12: =IF($B12="","",INDEX(Purchase_Register!$E$6:$E$205,$B12)&"") -> Waxed Cotton Laces | F12: =IF($B12="","",INDEX(Purchase_Register!$M$6:$M$205,$B12)&"") -> Delta Thread & Trims | G12: =IF($B12="","",INDEX(Purchase_Register!$C$6:$C$205,$B12)&"") -> Stitching | H12: =IF($B12="","",INDEX(Purchase_Register!$BI$6:$BI$205,$B12)&"") -> Closed | I12: =IF($B12="","",INDEX(Purchase_Register!$AX$6:$AX$205,$B12)&"") -> All In-house | J12: =IF($B12="","",N(INDEX(Purchase_Register!$AK$6:$AK$205,$B12))) -> 0 | K12: =IF($B12="","",N(INDEX(Purchase_Register!$AL$6:$AL$205,$B12))) -> 0 | L12: =IF($B12="","",INDEX(Purchase_Register!$BK$6:$BK$205,$B12)&"") -> QC rejected: return / replace;
A13: =IF(ROWS($A$7:A13)>COUNT(Purchase_Register!$BM$6:$BM$205),"",ROWS($A$7:A13)) -> 7 | B13: =IF($A13="","",MATCH(SMALL(Purchase_Register!$BM$6:$BM$205,$A13),Purchase_Register!$BM$6:$BM$205,0)) -> 13 | C13: =IF($B13="","",INDEX(Purchase_Register!$BL$6:$BL$205,$B13)&"") -> High | D13: =IF($B13="","",INDEX(Purchase_Register!$A$6:$A$205,$B13)&"") -> PSIL-PR-2026-0013 | E13: =IF($B13="","",INDEX(Purchase_Register!$E$6:$E$205,$B13)&"") -> Cellulose Insole Board | F13: =IF($B13="","",INDEX(Purchase_Register!$M$6:$M$205,$B13)&"") -> Narayanganj Board Mills | G13: =IF($B13="","",INDEX(Purchase_Register!$C$6:$C$205,$B13)&"") -> Cutting | H13: =IF($B13="","",INDEX(Purchase_Register!$BI$6:$BI$205,$B13)&"") -> In-house Closed - Payment Due | I13: =IF($B13="","",INDEX(Purchase_Register!$AX$6:$AX$205,$B13)&"") -> All In-house | J13: =IF($B13="","",N(INDEX(Purchase_Register!$AK$6:$AK$205,$B13))) -> 352800 | K13: =IF($B13="","",N(INDEX(Purchase_Register!$AL$6:$AL$205,$B13))) -> 0 | L13: =IF($B13="","",INDEX(Purchase_Register!$BK$6:$BK$205,$B13)&"") -> Pay supplier: 31 days overdue;
A14: =IF(ROWS($A$7:A14)>COUNT(Purchase_Register!$BM$6:$BM$205),"",ROWS($A$7:A14)) -> 8 | B14: =IF($A14="","",MATCH(SMALL(Purchase_Register!$BM$6:$BM$205,$A14),Purchase_Register!$BM$6:$BM$205,0)) -> 17 | C14: =IF($B14="","",INDEX(Purchase_Register!$BL$6:$BL$205,$B14)&"") -> High | D14: =IF($B14="","",INDEX(Purchase_Register!$A$6:$A$205,$B14)&"") -> PSIL-PR-2026-0017 | E14: =IF($B14="","",INDEX(Purchase_Register!$E$6:$E$205,$B14)&"") -> Sewing Machine Needles & Spares | F14: =IF($B14="","",INDEX(Purchase_Register!$M$6:$M$205,$B14)&"") -> Dhaka Spares & Tools | G14: =IF($B14="","",INDEX(Purchase_Register!$C$6:$C$205,$B14)&"") -> Maintenance | H14: =IF($B14="","",INDEX(Purchase_Register!$BI$6:$BI$205,$B14)&"") -> In-house Closed - Payment Due | I14: =IF($B14="","",INDEX(Purchase_Register!$AX$6:$AX$205,$B14)&"") -> All In-house | J14: =IF($B14="","",N(INDEX(Purchase_Register!$AK$6:$AK$205,$B14))) -> 40248 | K14: =IF($B14="","",N(INDEX(Purchase_Register!$AL$6:$AL$205,$B14))) -> 0 | L14: =IF($B14="","",INDEX(Purchase_Register!$BK$6:$BK$205,$B14)&"") -> Pay supplier: 25 days overdue; QC rejected: return / replace;
A15: =IF(ROWS($A$7:A15)>COUNT(Purchase_Register!$BM$6:$BM$205),"",ROWS($A$7:A15)) -> 9 | B15: =IF($A15="","",MATCH(SMALL(Purchase_Register!$BM$6:$BM$205,$A15),Purchase_Register!$BM$6:$BM$205,0)) -> 18 | C15: =IF($B15="","",INDEX(Purchase_Register!$BL$6:$BL$205,$B15)&"") -> High | D15: =IF($B15="","",INDEX(Purchase_Register!$A$6:$A$205,$B15)&"") -> PSIL-PR-2026-0018 | E15: =IF($B15="","",INDEX(Purchase_Register!$E$6:$E$205,$B15)&"") -> Safety PPE (Masks, Gloves, Goggles) | F15: =IF($B15="","",INDEX(Purchase_Register!$M$6:$M$205,$B15)&"") -> Dhaka Spares & Tools | G15: =IF($B15="","",INDEX(Purchase_Register!$C$6:$C$205,$B15)&"") -> Compliance & HSE | H15: =IF($B15="","",INDEX(Purchase_Register!$BI$6:$BI$205,$B15)&"") -> In-house Closed - Payment Due | I15: =IF($B15="","",INDEX(Purchase_Register!$AX$6:$AX$205,$B15)&"") -> All In-house | J15: =IF($B15="","",N(INDEX(Purchase_Register!$AK$6:$AK$205,$B15))) -> 107392.5 | K15: =IF($B15="","",N(INDEX(Purchase_Register!$AL$6:$AL$205,$B15))) -> 0 | L15: =IF($B15="","",INDEX(Purchase_Register!$BK$6:$BK$205,$B15)&"") -> Pay supplier: 36 days overdue;
A16: =IF(ROWS($A$7:A16)>COUNT(Purchase_Register!$BM$6:$BM$205),"",ROWS($A$7:A16)) -> 10 | B16: =IF($A16="","",MATCH(SMALL(Purchase_Register!$BM$6:$BM$205,$A16),Purchase_Register!$BM$6:$BM$205,0)) -> 24 | C16: =IF($B16="","",INDEX(Purchase_Register!$BL$6:$BL$205,$B16)&"") -> High | D16: =IF($B16="","",INDEX(Purchase_Register!$A$6:$A$205,$B16)&"") -> PSIL-PR-2026-0024 | E16: =IF($B16="","",INDEX(Purchase_Register!$E$6:$E$205,$B16)&"") -> Pig Lining Leather | F16: =IF($B16="","",INDEX(Purchase_Register!$M$6:$M$205,$B16)&"") -> Savar Leather Works Ltd | G16: =IF($B16="","",INDEX(Purchase_Register!$C$6:$C$205,$B16)&"") -> Cutting | H16: =IF($B16="","",INDEX(Purchase_Register!$BI$6:$BI$205,$B16)&"") -> In-house Closed - Payment Due | I16: =IF($B16="","",INDEX(Purchase_Register!$AX$6:$AX$205,$B16)&"") -> All In-house | J16: =IF($B16="","",N(INDEX(Purchase_Register!$AK$6:$AK$205,$B16))) -> 814188.17 | K16: =IF($B16="","",N(INDEX(Purchase_Register!$AL$6:$AL$205,$B16))) -> 0 | L16: =IF($B16="","",INDEX(Purchase_Register!$BK$6:$BK$205,$B16)&"") -> Pay supplier: 22 days overdue; QC rejected: return / replace;
A17: =IF(ROWS($A$7:A17)>COUNT(Purchase_Register!$BM$6:$BM$205),"",ROWS($A$7:A17)) -> 11 | B17: =IF($A17="","",MATCH(SMALL(Purchase_Register!$BM$6:$BM$205,$A17),Purchase_Register!$BM$6:$BM$205,0)) -> 33 | C17: =IF($B17="","",INDEX(Purchase_Register!$BL$6:$BL$205,$B17)&"") -> High | D17: =IF($B17="","",INDEX(Purchase_Register!$A$6:$A$205,$B17)&"") -> PSIL-PR-2026-0033 | E17: =IF($B17="","",INDEX(Purchase_Register!$E$6:$E$205,$B17)&"") -> Cow Nappa Upper Leather | F17: =IF($B17="","",INDEX(Purchase_Register!$M$6:$M$205,$B17)&"") -> Savar Leather Works Ltd | G17: =IF($B17="","",INDEX(Purchase_Register!$C$6:$C$205,$B17)&"") -> Cutting | H17: =IF($B17="","",INDEX(Purchase_Register!$BI$6:$BI$205,$B17)&"") -> Closed | I17: =IF($B17="","",INDEX(Purchase_Register!$AX$6:$AX$205,$B17)&"") -> Short Closed - 915 sqft not received | J17: =IF($B17="","",N(INDEX(Purchase_Register!$AK$6:$AK$205,$B17))) -> 0 | K17: =IF($B17="","",N(INDEX(Purchase_Register!$AL$6:$AL$205,$B17))) -> 281308 | L17: =IF($B17="","",INDEX(Purchase_Register!$BK$6:$BK$205,$B17)&"") -> Short closed: claim balance / credit note BDT 281,308;
A18: =IF(ROWS($A$7:A18)>COUNT(Purchase_Register!$BM$6:$BM$205),"",ROWS($A$7:A18)) -> 12 | B18: =IF($A18="","",MATCH(SMALL(Purchase_Register!$BM$6:$BM$205,$A18),Purchase_Register!$BM$6:$BM$205,0)) -> 34 | C18: =IF($B18="","",INDEX(Purchase_Register!$BL$6:$BL$205,$B18)&"") -> High | D18: =IF($B18="","",INDEX(Purchase_Register!$A$6:$A$205,$B18)&"") -> PSIL-PR-2026-0034 | E18: =IF($B18="","",INDEX(Purchase_Register!$E$6:$E$205,$B18)&"") -> PU Adhesive (Solvent Based) | F18: =IF($B18="","",INDEX(Purchase_Register!$M$6:$M$205,$B18)&"") -> Gazipur Chem Trade | G18: =IF($B18="","",INDEX(Purchase_Register!$C$6:$C$205,$B18)&"") -> Lasting & Assembly | H18: =IF($B18="","",INDEX(Purchase_Register!$BI$6:$BI$205,$B18)&"") -> In-house Closed - Payment Due | I18: =IF($B18="","",INDEX(Purchase_Register!$AX$6:$AX$205,$B18)&"") -> All In-house | J18: =IF($B18="","",N(INDEX(Purchase_Register!$AK$6:$AK$205,$B18))) -> 563730 | K18: =IF($B18="","",N(INDEX(Purchase_Register!$AL$6:$AL$205,$B18))) -> 0 | L18: =IF($B18="","",INDEX(Purchase_Register!$BK$6:$BK$205,$B18)&"") -> QC rejected: return / replace;
... A206: =IF(ROWS($A$7:A206)>COUNT(Purchase_Register!$BM$6:$BM$205),"",ROWS($A$7:A206)) | B206: =IF($A206="","",MATCH(SMALL(Purchase_Register!$BM$6:$BM$205,$A206),Purchase_Register!$BM$6:$BM$205,0)) | C206: =IF($B206="","",INDEX(Purchase_Register!$BL$6:$BL$205,$B206)&"") | D206: =IF($B206="","",INDEX(Purchase_Register!$A$6:$A$205,$B206)&"") | E206: =IF($B206="","",INDEX(Purchase_Register!$E$6:$E$205,$B206)&"") | F206: =IF($B206="","",INDEX(Purchase_Register!$M$6:$M$205,$B206)&"") | G206: =IF($B206="","",INDEX(Purchase_Register!$C$6:$C$205,$B206)&"") | H206: =IF($B206="","",INDEX(Purchase_Register!$BI$6:$BI$205,$B206)&"") | I206: =IF($B206="","",INDEX(Purchase_Register!$AX$6:$AX$205,$B206)&"") | J206: =IF($B206="","",N(INDEX(Purchase_Register!$AK$6:$AK$205,$B206))) | K206: =IF($B206="","",N(INDEX(Purchase_Register!$AL$6:$AL$205,$B206))) | L206: =IF($B206="","",INDEX(Purchase_Register!$BK$6:$BK$205,$B206)&"")

Sheet Purchase_Register
A1: PANDA SHOES INDUSTRY LTD — PURCHASE TRACKING REGISTER (PR → Approval → PO → In-house → Payment)
A2: BLACK cells with WHITE text = data entry (only these can be typed in). ORANGE = required input missing for this stage. GREY = automatic formula (locked). Check the 'Data Check' column — every line should read OK. Capacity: rows 6–205.
A3: ✎ INPUT | B3: ✎ INPUT | C3: ✎ INPUT | D3: ✎ INPUT | E3: ✎ INPUT | F3: ✎ INPUT | G3: ✎ INPUT | H3: ✎ INPUT | I3: ✎ INPUT | J3: ✎ INPUT | K3: ✎ INPUT | L3: ✎ INPUT | M3: ✎ INPUT | N3: ✎ INPUT | O3: ✎ INPUT | P3: ✎ INPUT | Q3: ✎ INPUT | R3: ✎ INPUT | S3: ✎ INPUT | T3: ✎ INPUT | U3: AUTO | V3: ✎ INPUT | W3: AUTO | X3: AUTO | Y3: AUTO | Z3: AUTO | AA3: AUTO | AB3: AUTO | AC3: ✎ INPUT | AD3: AUTO | AE3: ✎ INPUT | AF3: ✎ INPUT | AG3: ✎ INPUT | AH3: ✎ INPUT | AI3: AUTO | AJ3: AUTO | AK3: AUTO | AL3: AUTO | AM3: AUTO | AN3: ✎ INPUT | AO3: ✎ INPUT | AP3: AUTO | AQ3: AUTO | AR3: ✎ INPUT | AS3: ✎ INPUT | AT3: ✎ INPUT | AU3: AUTO | AV3: AUTO | AW3: AUTO | AX3: AUTO | AY3: ✎ INPUT | AZ3: AUTO | BA3: AUTO | BB3: AUTO | BC3: AUTO | BD3: AUTO | BE3: AUTO | BF3: ✎ INPUT | BG3: ✎ INPUT | BH3: ✎ INPUT | BI3: AUTO | BJ3: AUTO | BK3: AUTO | BL3: AUTO | BM3: AUTO | BN3: ✎ INPUT
A4: 1 · REQUISITION & OPEX/CAPEX APPROVAL | M4: 2 · PURCHASE ORDER & VALUE | AE4: 3 · FINANCE STATUS & PAYABLES | AR4: 4 · IN-HOUSE RECEIVING & CYCLE TIME | BF4: 5 · MATERIAL APPROVAL & STAGE
A5: PR No | B5: PR Received Date | C5: Department | D5: Requested By | E5: Item / Material Purchased | F5: Category | G5: Spec / Size / Colour | H5: Spend Type (OPEX / CAPEX) | I5: OPEX / CAPEX Approval Ref | J5: Approval Date | K5: Approval Status | L5: Approved By | M5: Supplier | N5: Local / Import | O5: PO No | P5: PO Date | Q5: Order Quantity | R5: UOM | S5: Unit Price (PO Currency) | T5: Currency | U5: FX Rate to BDT | V5: Budget / Standard Unit Price (BDT) | W5: PO Value (BDT) | X5: Unit Price (BDT) | Y5: Previous PO Unit Price — Same Item (BDT) | Z5: Price Change vs Previous PO % | AA5: Price Variance vs Budget (BDT) | AB5: Price Variance % | AC5: VAT / AIT / Duty % | AD5: Total Price incl. Tax (BDT) | AE5: Payment Terms | AF5: Initial / Advance Paid (BDT) | AG5: Interim Payment (BDT) | AH5: Closing Payment (BDT) | AI5: Total Paid (BDT) | AJ5: % of Payment | AK5: Outstanding Payable (BDT) | AL5: Paid Ahead of Receipt (BDT) | AM5: Finance Status | AN5: Last Payment Date | AO5: Next Payment Due Date | AP5: Days Payment Overdue | AQ5: Payable Aging Bucket | AR5: Supplier Committed Delivery Date | AS5: Starting to In-house Date | AT5: Qty Received In-house | AU5: Received % | AV5: Pending Qty to In-house | AW5: Pending In-house Value (BDT) | AX5: Pending Material Status | AY5: Final In-house Closing Date | AZ5: Days PR → Approval | BA5: Days Approval → PO | BB5: Lead Time PO → In-house Close (days) | BC5: Total Cycle PR → Close (days) | BD5: Delivery Delay (days) | BE5: OTIF | BF5: QC / Material Approval | BG5: Approved Material Photo — File / Link | BH5: Approved Material Picture | BI5: Current Stage | BJ5: Data Check (auto) | BK5: Action Required (auto) | BL5: Action Priority | BM5: Action Sort Key | BN5: Remarks
A6: PSIL-PR-2026-0001 | B6: 46175 | C6: Cutting | D6: Cutting Manager | E6: Cow Nappa Upper Leather | F6: Leather & Upper | G6: 1.2–1.4 mm, Black | H6: OPEX | I6: OPX-2026-101 | J6: 46176 | K6: Approved | L6: GM Operations | M6: Savar Leather Works Ltd | N6: Local | O6: PSIL-PO-2026-0001 | P6: 46181 | Q6: 10500 | R6: sqft | S6: 2.35 | T6: USD | U6: =IF(AND(T6="",S6=""),"",IF(T6="",1,IFERROR(INDEX(Settings!$B$12:$B$16,MATCH(T6,Settings!$A$12:$A$16,0)),1))) -> 122 | V6: 278.93 | W6: =IF(OR(Q6="",S6=""),"",Q6*S6*U6) -> 3010350 | X6: =IF(OR(W6="",N(Q6)=0),"",W6/Q6) -> 286.7 | Y6: =IF(OR(X6="",P6="",E6=""),"",IF(_xlfn.MAXIFS($P$6:$P$205,$E$6:$E$205,E6,$P$6:$P$205,"<"&P6,$X$6:$X$205,">0")=0,"",IFERROR(AVERAGEIFS($X$6:$X$205,$E$6:$E$205,E6,$P$6:$P$205,_xlfn.MAXIFS($P$6:$P$205,$E$6:$E$205,E6,$P$6:$P$205,"<"&P6,$X$6:$X$205,">0"),$X$6:$X$205,">0"),""))) | Z6: =IF(OR(Y6="",X6=""),"",X6/Y6-1) | AA6: =IF(OR(W6="",V6=""),"",W6-Q6*V6) -> 81585 | AB6: =IF(AA6="","",IF(N(V6)*N(Q6)=0,"",AA6/(Q6*V6))) -> 0.027856451 | AC6: 0.05 | AD6: =IF(W6="","",W6*(1+N(AC6))) -> 3160867.5 | AE6: 30% Advance / 70% after In-house | AF6: 948260.25 | AH6: 2212607.2 | AI6: =IF(A6="","",N(AF6)+N(AG6)+N(AH6)) -> 3160867.5 | AJ6: =IF(AD6="","",IF(N(AD6)=0,"",AI6/AD6)) -> 1 | AK6: =IF(AD6="","",IF(AD6-AI6<1,0,ROUND(AD6-AI6,2))) -> 0 | AL6: =IF(OR(O6="",AD6=""),"",MAX(0,ROUND(N(AI6)-(AD6-N(AW6)),0))) -> 0 | AM6: =IF(A6="","",IF(O6="","No PO Yet",IF(AI6=0,"Not Paid",IF(N(AJ6)>=0.999,"Fully Paid",IF(N(AG6)+N(AH6)>0,"Partially Paid","Initial / Advance Paid"))))) -> Fully Paid | AN6: 46203 | AP6: =IF(AK6="","",IF(OR(N(AK6)=0,AO6=""),"",MAX(0,Settings!$B$4-AO6))) | AQ6: =IF(AK6="","",IF(N(AK6)<=0,"",IF(AO6="","No Due Date",IF(Settings!$B$4<=AO6,"Not Yet Due",IF(Settings!$B$4-AO6<=30,"1-30 Days",IF(Settings!$B$4-AO6<=60,"31-60 Days",IF(Settings!$B$4-AO6<=90,"61-90 Days","90+ Days"))))))) | AR6: 46191 | AS6: 46188 | AT6: 10500 | AU6: =IF(Q6="","",IF(N(Q6)=0,"",N(AT6)/Q6)) -> 1 | AV6: =IF(OR(A6="",O6="",Q6=""),"",MAX(0,Q6-N(AT6))) -> 0 | AW6: =IF(OR(AV6="",W6=""),"",IF(N(Q6)=0,0,AV6/Q6*AD6)) -> 0 | AX6: =IF(A6="","",IF(O6="","No PO Yet",IF(Q6="","Order Qty Missing",IF(N(AT6)>=Q6,IF(N(AT6)>Q6,"All In-house (+"&TEXT(N(AT6)-Q6,"#,##0")&" "&R6&" excess)","All In-house"),IF(AY6<>"","Short Closed - "&TEXT(AV6,"#,##0")&" "&R6&" not received",IF(N(AT6)=0,"Not Started - "&TEXT(AV6,"#,##0")&" "&R6&" pending","Pending "&TEXT(AV6,"#,##0")&" "&R6&" ("&TEXT(AU6,"0%")&" received)")))))) -> All In-house | AY6: 46188 | AZ6: =IF(OR(B6="",J6=""),"",J6-B6) -> 1 | BA6: =IF(OR(J6="",P6=""),"",P6-J6) -> 5 | BB6: =IF(OR(P6="",AY6=""),"",AY6-P6) -> 7 | BC6: =IF(OR(B6="",AY6=""),"",AY6-B6) -> 13 | BD6: =IF(OR(AR6="",O6=""),"",MAX(0,IF(AY6="",Settings!$B$4,AY6)-AR6)) -> 0 | BE6: =IF(OR(AY6="",AR6=""),"",IF(AND(AY6<=AR6,N(AU6)>=Settings!$B$6),"OTIF","Not OTIF")) -> OTIF | BF6: Approved | BG6: Photos\PSIL-PR-2026-0001.jpg | BI6: =IF(A6="","",IF(K6="Rejected","Rejected",IF(K6<>"Approved","Awaiting Approval",IF(O6="","Approved - PO Pending",IF(AY6<>"",IF(N(AJ6)>=0.999,"Closed","In-house Closed - Payment Due"),IF(AS6<>"","Receiving In-house","PO Issued - Awaiting Delivery")))))) -> Closed | BJ6: =IF(A6="","",IF(IF(AND(A6<>"",OR(B6="",C6="",E6="",F6="",H6="")),"PR info missing; ","")&IF(AND(K6="Approved",OR(J6="",I6="")),"Approval ref/date missing; ","")&IF(AND(O6<>"",K6<>"Approved"),"PO without approval; ","")&IF(AND(O6<>"",OR(P6="",M6="",Q6="",S6="",T6="")),"PO details missing; ","")&IF(AND(O6<>"",AR6=""),"Committed date missing; ","")&IF(AND(ISNUMBER(J6),ISNUMBER(B6),N(J6)<N(B6)),"Approval dated before PR; ","")&IF(AND(ISNUMBER(P6),ISNUMBER(J6),N(P6)<N(J6)),"PO dated before approval; ","")&IF(AND(ISNUMBER(AY6),ISNUMBER(AS6),N(AY6)<N(AS6)),"Close before in-house start; ","")&IF(AND(AY6<>"",AS6=""),"In-house start date missing; ","")&IF(AND(AY6<>"",AT6=""),"Qty received missing; ","")&IF(AND(AY6<>"",BF6=""),"QC status missing; ","")&IF(N(AT6)>N(Q6)*1.05,"Received > ordered +5%; ","")&IF(AND(N(AI6)>0,AE6=""),"Payment terms missing; ","")&IF(N(AI6)>N(AD6)+1,"Overpaid vs PO; ","")&IF(AND(N(AK6)>0,AY6<>"",AO6=""),"Payment due date missing; ","")="","OK",IF(AND(A6<>"",OR(B6="",C6="",E6="",F6="",H6="")),"PR info missing; ","")&IF(AND(K6="Approved",OR(J6="",I6="")),"Approval ref/date missing; ","")&IF(AND(O6<>"",K6<>"Approved"),"PO without approval; ","")&IF(AND(O6<>"",OR(P6="",M6="",Q6="",S6="",T6="")),"PO details missing; ","")&IF(AND(O6<>"",AR6=""),"Committed date missing; ","")&IF(AND(ISNUMBER(J6),ISNUMBER(B6),N(J6)<N(B6)),"Approval dated before PR; ","")&IF(AND(ISNUMBER(P6),ISNUMBER(J6),N(P6)<N(J6)),"PO dated before approval; ","")&IF(AND(ISNUMBER(AY6),ISNUMBER(AS6),N(AY6)<N(AS6)),"Close before in-house start; ","")&IF(AND(AY6<>"",AS6=""),"In-house start date missing; ","")&IF(AND(AY6<>"",AT6=""),"Qty received missing; ","")&IF(AND(AY6<>"",BF6=""),"QC status missing; ","")&IF(N(AT6)>N(Q6)*1.05,"Received > ordered +5%; ","")&IF(AND(N(AI6)>0,AE6=""),"Payment terms missing; ","")&IF(N(AI6)>N(AD6)+1,"Overpaid vs PO; ","")&IF(AND(N(AK6)>0,AY6<>"",AO6=""),"Payment due date missing; ",""))) -> OK | BK6: =IF(A6="","",IF(N(AP6)>0,"Pay supplier: "&N(AP6)&" days overdue; ","")&IF(AND(O6<>"",AY6="",N(BD6)>0),"Expedite delivery: "&N(BD6)&" days late; ","")&IF(AND(BI6="Awaiting Approval",ISNUMBER(B6),Settings!$B$4-N(B6)>Settings!$B$19),"Get approval: PR waiting "&(Settings!$B$4-N(B6))&" days; ","")&IF(AND(BI6="Approved - PO Pending",ISNUMBER(J6),Settings!$B$4-N(J6)>Settings!$B$20),"Issue PO: approved "&(Settings!$B$4-N(J6))&" days ago; ","")&IF(AND(OR(BI6="Awaiting Approval",BI6="Approved - PO Pending"),N(AB6)>Settings!$B$7),"Negotiate price: "&TEXT(AB6,"0%")&" above budget; ","")&IF(LEFT(AX6,12)="Short Closed","Short closed: claim balance / credit note"&IF(N(AL6)>0," BDT "&TEXT(AL6,"#,##0"),"")&"; ","")&IF(BF6="Rejected","QC rejected: return / replace; ","")&IF(AND(O6<>"",AY6="",N(AL6)>0,N(BD6)>0),"Advance at risk: BDT "&TEXT(AL6,"#,##0")&" paid, goods late; ","")&IF(AND(BJ6<>"",BJ6<>"OK"),"Fix data entry (see Data Check); ","")) | BL6: =IF(BK6="","",IF(OR(N(AP6)>30,AND(AY6="",N(BD6)>15),BF6="Rejected",AND(LEFT(AX6,12)="Short Closed",N(AL6)>0),AND(O6<>"",AY6="",N(AL6)>0,N(BD6)>0)),"High",IF(OR(N(AP6)>0,AND(AY6="",N(BD6)>7),LEFT(AX6,12)="Short Closed",AND(BI6="Awaiting Approval",ISNUMBER(B6),Settings!$B$4-N(B6)>2*Settings!$B$19),AND(BI6="Approved - PO Pending",ISNUMBER(J6),Settings!$B$4-N(J6)>2*Settings!$B$20)),"Medium","Low"))) | BM6: =IF(BL6="","",IF(BL6="High",1,IF(BL6="Medium",2,3))*10000+ROW())
A7: PSIL-PR-2026-0002 | B7: 46178 | C7: Cutting | D7: Cutting Manager | E7: Suede Split Leather | F7: Leather & Upper | G7: 1.6 mm, Taupe | H7: OPEX | I7: OPX-2026-102 | J7: 46180 | K7: Approved | L7: CFO | M7: Savar Leather Works Ltd | N7: Local | O7: PSIL-PO-2026-0002 | P7: 46185 | Q7: 4500 | R7: sqft | S7: 1.76 | T7: USD | U7: =IF(AND(T7="",S7=""),"",IF(T7="",1,IFERROR(INDEX(Settings!$B$12:$B$16,MATCH(T7,Settings!$A$12:$A$16,0)),1))) -> 122 | V7: 196.76 | W7: =IF(OR(Q7="",S7=""),"",Q7*S7*U7) -> 966240 | X7: =IF(OR(W7="",N(Q7)=0),"",W7/Q7) -> 214.72 | Y7: =IF(OR(X7="",P7="",E7=""),"",IF(_xlfn.MAXIFS($P$6:$P$205,$E$6:$E$205,E7,$P$6:$P$205,"<"&P7,$X$6:$X$205,">0")=0,"",IFERROR(AVERAGEIFS($X$6:$X$205,$E$6:$E$205,E7,$P$6:$P$205,_xlfn.MAXIFS($P$6:$P$205,$E$6:$E$205,E7,$P$6:$P$205,"<"&P7,$X$6:$X$205,">0"),$X$6:$X$205,">0"),""))) | Z7: =IF(OR(Y7="",X7=""),"",X7/Y7-1) | AA7: =IF(OR(W7="",V7=""),"",W7-Q7*V7) -> 80820 | AB7: =IF(AA7="","",IF(N(V7)*N(Q7)=0,"",AA7/(Q7*V7))) -> 0.091278715 | AC7: 0.05 | AD7: =IF(W7="","",W7*(1+N(AC7))) -> 1014552 | AE7: 100% Advance | AF7: 1014552 | AI7: =IF(A7="","",N(AF7)+N(AG7)+N(AH7)) -> 1014552 | AJ7: =IF(AD7="","",IF(N(AD7)=0,"",AI7/AD7)) -> 1 | AK7: =IF(AD7="","",IF(AD7-AI7<1,0,ROUND(AD7-AI7,2))) -> 0 | AL7: =IF(OR(O7="",AD7=""),"",MAX(0,ROUND(N(AI7)-(AD7-N(AW7)),0))) -> 0 | AM7: =IF(A7="","",IF(O7="","No PO Yet",IF(AI7=0,"Not Paid",IF(N(AJ7)>=0.999,"Fully Paid",IF(N(AG7)+N(AH7)>0,"Partially Paid","Initial / Advance Paid"))))) -> Fully Paid | AN7: 46186 | AP7: =IF(AK7="","",IF(OR(N(AK7)=0,AO7=""),"",MAX(0,Settings!$B$4-AO7))) | AQ7: =IF(AK7="","",IF(N(AK7)<=0,"",IF(AO7="","No Due Date",IF(Settings!$B$4<=AO7,"Not Yet Due",IF(Settings!$B$4-AO7<=30,"1-30 Days",IF(Settings!$B$4-AO7<=60,"31-60 Days",IF(Settings!$B$4-AO7<=90,"61-90 Days","90+ Days"))))))) | AR7: 46204 | AS7: 46198 | AT7: 4500 | AU7: =IF(Q7="","",IF(N(Q7)=0,"",N(AT7)/Q7)) -> 1 | AV7: =IF(OR(A7="",O7="",Q7=""),"",MAX(0,Q7-N(AT7))) -> 0 | AW7: =IF(OR(AV7="",W7=""),"",IF(N(Q7)=0,0,AV7/Q7*AD7)) -> 0 | AX7: =IF(A7="","",IF(O7="","No PO Yet",IF(Q7="","Order Qty Missing",IF(N(AT7)>=Q7,IF(N(AT7)>Q7,"All In-house (+"&TEXT(N(AT7)-Q7,"#,##0")&" "&R7&" excess)","All In-house"),IF(AY7<>"","Short Closed - "&TEXT(AV7,"#,##0")&" "&R7&" not received",IF(N(AT7)=0,"Not Started - "&TEXT(AV7,"#,##0")&" "&R7&" pending","Pending "&TEXT(AV7,"#,##0")&" "&R7&" ("&TEXT(AU7,"0%")&" received)")))))) -> All In-house | AY7: 46199 | AZ7: =IF(OR(B7="",J7=""),"",J7-B7) -> 2 | BA7: =IF(OR(J7="",P7=""),"",P7-J7) -> 5 | BB7: =IF(OR(P7="",AY7=""),"",AY7-P7) -> 14 | BC7: =IF(OR(B7="",AY7=""),"",AY7-B7) -> 21 | BD7: =IF(OR(AR7="",O7=""),"",MAX(0,IF(AY7="",Settings!$B$4,AY7)-AR7)) -> 0 | BE7: =IF(OR(AY7="",AR7=""),"",IF(AND(AY7<=AR7,N(AU7)>=Settings!$B$6),"OTIF","Not OTIF")) -> OTIF | BF7: Rejected | BI7: =IF(A7="","",IF(K7="Rejected","Rejected",IF(K7<>"Approved","Awaiting Approval",IF(O7="","Approved - PO Pending",IF(AY7<>"",IF(N(AJ7)>=0.999,"Closed","In-house Closed - Payment Due"),IF(AS7<>"","Receiving In-house","PO Issued - Awaiting Delivery")))))) -> Closed | BJ7: =IF(A7="","",IF(IF(AND(A7<>"",OR(B7="",C7="",E7="",F7="",H7="")),"PR info missing; ","")&IF(AND(K7="Approved",OR(J7="",I7="")),"Approval ref/date missing; ","")&IF(AND(O7<>"",K7<>"Approved"),"PO without approval; ","")&IF(AND(O7<>"",OR(P7="",M7="",Q7="",S7="",T7="")),"PO details missing; ","")&IF(AND(O7<>"",AR7=""),"Committed date missing; ","")&IF(AND(ISNUMBER(J7),ISNUMBER(B7),N(J7)<N(B7)),"Approval dated before PR; ","")&IF(AND(ISNUMBER(P7),ISNUMBER(J7),N(P7)<N(J7)),"PO dated before approval; ","")&IF(AND(ISNUMBER(AY7),ISNUMBER(AS7),N(AY7)<N(AS7)),"Close before in-house start; ","")&IF(AND(AY7<>"",AS7=""),"In-house start date missing; ","")&IF(AND(AY7<>"",AT7=""),"Qty received missing; ","")&IF(AND(AY7<>"",BF7=""),"QC status missing; ","")&IF(N(AT7)>N(Q7)*1.05,"Received > ordered +5%; ","")&IF(AND(N(AI7)>0,AE7=""),"Payment terms missing; ","")&IF(N(AI7)>N(AD7)+1,"Overpaid vs PO; ","")&IF(AND(N(AK7)>0,AY7<>"",AO7=""),"Payment due date missing; ","")="","OK",IF(AND(A7<>"",OR(B7="",C7="",E7="",F7="",H7="")),"PR info missing; ","")&IF(AND(K7="Approved",OR(J7="",I7="")),"Approval ref/date missing; ","")&IF(AND(O7<>"",K7<>"Approved"),"PO without approval; ","")&IF(AND(O7<>"",OR(P7="",M7="",Q7="",S7="",T7="")),"PO details missing; ","")&IF(AND(O7<>"",AR7=""),"Committed date missing; ","")&IF(AND(ISNUMBER(J7),ISNUMBER(B7),N(J7)<N(B7)),"Approval dated before PR; ","")&IF(AND(ISNUMBER(P7),ISNUMBER(J7),N(P7)<N(J7)),"PO dated before approval; ","")&IF(AND(ISNUMBER(AY7),ISNUMBER(AS7),N(AY7)<N(AS7)),"Close before in-house start; ","")&IF(AND(AY7<>"",AS7=""),"In-house start date missing; ","")&IF(AND(AY7<>"",AT7=""),"Qty received missing; ","")&IF(AND(AY7<>"",BF7=""),"QC status missing; ","")&IF(N(AT7)>N(Q7)*1.05,"Received > ordered +5%; ","")&IF(AND(N(AI7)>0,AE7=""),"Payment terms missing; ","")&IF(N(AI7)>N(AD7)+1,"Overpaid vs PO; ","")&IF(AND(N(AK7)>0,AY7<>"",AO7=""),"Payment due date missing; ",""))) -> OK | BK7: =IF(A7="","",IF(N(AP7)>0,"Pay supplier: "&N(AP7)&" days overdue; ","")&IF(AND(O7<>"",AY7="",N(BD7)>0),"Expedite delivery: "&N(BD7)&" days late; ","")&IF(AND(BI7="Awaiting Approval",ISNUMBER(B7),Settings!$B$4-N(B7)>Settings!$B$19),"Get approval: PR waiting "&(Settings!$B$4-N(B7))&" days; ","")&IF(AND(BI7="Approved - PO Pending",ISNUMBER(J7),Settings!$B$4-N(J7)>Settings!$B$20),"Issue PO: approved "&(Settings!$B$4-N(J7))&" days ago; ","")&IF(AND(OR(BI7="Awaiting Approval",BI7="Approved - PO Pending"),N(AB7)>Settings!$B$7),"Negotiate price: "&TEXT(AB7,"0%")&" above budget; ","")&IF(LEFT(AX7,12)="Short Closed","Short closed: claim balance / credit note"&IF(N(AL7)>0," BDT "&TEXT(AL7,"#,##0"),"")&"; ","")&IF(BF7="Rejected","QC rejected: return / replace; ","")&IF(AND(O7<>"",AY7="",N(AL7)>0,N(BD7)>0),"Advance at risk: BDT "&TEXT(AL7,"#,##0")&" paid, goods late; ","")&IF(AND(BJ7<>"",BJ7<>"OK"),"Fix data entry (see Data Check); ","")) -> QC rejected: return / replace; | BL7: =IF(BK7="","",IF(OR(N(AP7)>30,AND(AY7="",N(BD7)>15),BF7="Rejected",AND(LEFT(AX7,12)="Short Closed",N(AL7)>0),AND(O7<>"",AY7="",N(AL7)>0,N(BD7)>0)),"High",IF(OR(N(AP7)>0,AND(AY7="",N(BD7)>7),LEFT(AX7,12)="Short Closed",AND(BI7="Awaiting Approval",ISNUMBER(B7),Settings!$B$4-N(B7)>2*Settings!$B$19),AND(BI7="Approved - PO Pending",ISNUMBER(J7),Settings!$B$4-N(J7)>2*Settings!$B$20)),"Medium","Low"))) -> High | BM7: =IF(BL7="","",IF(BL7="High",1,IF(BL7="Medium",2,3))*10000+ROW()) -> 10007
A8: PSIL-PR-2026-0003 | B8: 46181 | C8: Cutting | D8: Cutting Manager | E8: Pig Lining Leather | F8: Leather & Upper | G8: 0.8 mm, Natural | H8: OPEX | I8: OPX-2026-103 | J8: 46183 | K8: Approved | L8: CFO | M8: Savar Leather Works Ltd | N8: Local | O8: PSIL-PO-2026-0003 | P8: 46188 | Q8: 8400 | R8: sqft | S8: 97 | T8: BDT | U8: =IF(AND(T8="",S8=""),"",IF(T8="",1,IFERROR(INDEX(Settings!$B$12:$B$16,MATCH(T8,Settings!$A$12:$A$16,0)),1))) -> 1 | V8: 95.4 | W8: =IF(OR(Q8="",S8=""),"",Q8*S8*U8) -> 814800 | X8: =IF(OR(W8="",N(Q8)=0),"",W8/Q8) -> 97 | Y8: =IF(OR(X8="",P8="",E8=""),"",IF(_xlfn.MAXIFS($P$6:$P$205,$E$6:$E$205,E8,$P$6:$P$205,"<"&P8,$X$6:$X$205,">0")=0,"",IFERROR(AVERAGEIFS($X$6:$X$205,$E$6:$E$205,E8,$P$6:$P$205,_xlfn.MAXIFS($P$6:$P$205,$E$6:$E$205,E8,$P$6:$P$205,"<"&P8,$X$6:$X$205,">0"),$X$6:$X$205,">0"),""))) | Z8: =IF(OR(Y8="",X8=""),"",X8/Y8-1) | AA8: =IF(OR(W8="",V8=""),"",W8-Q8*V8) -> 13440 | AB8: =IF(AA8="","",IF(N(V8)*N(Q8)=0,"",AA8/(Q8*V8))) -> 0.016771488 | AC8: 0.05 | AD8: =IF(W8="","",W8*(1+N(AC8))) -> 855540 | AE8: Credit 30 Days | AH8: 855540 | AI8: =IF(A8="","",N(AF8)+N(AG8)+N(AH8)) -> 855540 | AJ8: =IF(AD8="","",IF(N(AD8)=0,"",AI8/AD8)) -> 1 | AK8: =IF(AD8="","",IF(AD8-AI8<1,0,ROUND(AD8-AI8,2))) -> 0 | AL8: =IF(OR(O8="",AD8=""),"",MAX(0,ROUND(N(AI8)-(AD8-N(AW8)),0))) -> 0 | AM8: =IF(A8="","",IF(O8="","No PO Yet",IF(AI8=0,"Not Paid",IF(N(AJ8)>=0.999,"Fully Paid",IF(N(AG8)+N(AH8)>0,"Partially Paid","Initial / Advance Paid"))))) -> Fully Paid | AN8: 46236 | AP8: =IF(AK8="","",IF(OR(N(AK8)=0,AO8=""),"",MAX(0,Settings!$B$4-AO8))) | AQ8: =IF(AK8="","",IF(N(AK8)<=0,"",IF(AO8="","No Due Date",IF(Settings!$B$4<=AO8,"Not Yet Due",IF(Settings!$B$4-AO8<=30,"1-30 Days",IF(Settings!$B$4-AO8<=60,"31-60 Days",IF(Settings!$B$4-AO8<=90,"61-90 Days","90+ Days"))))))) | AR8: 46207 | AS8: 46206 | AT8: 8400 | AU8: =IF(Q8="","",IF(N(Q8)=0,"",N(AT8)/Q8)) -> 1 | AV8: =IF(OR(A8="",O8="",Q8=""),"",MAX(0,Q8-N(AT8))) -> 0 | AW8: =IF(OR(AV8="",W8=""),"",IF(N(Q8)=0,0,AV8/Q8*AD8)) -> 0 | AX8: =IF(A8="","",IF(O8="","No PO Yet",IF(Q8="","Order Qty Missing",IF(N(AT8)>=Q8,IF(N(AT8)>Q8,"All In-house (+"&TEXT(N(AT8)-Q8,"#,##0")&" "&R8&" excess)","All In-house"),IF(AY8<>"","Short Closed - "&TEXT(AV8,"#,##0")&" "&R8&" not received",IF(N(AT8)=0,"Not Started - "&TEXT(AV8,"#,##0")&" "&R8&" pending","Pending "&TEXT(AV8,"#,##0")&" "&R8&" ("&TEXT(AU8,"0%")&" received)")))))) -> All In-house | AY8: 46206 | AZ8: =IF(OR(B8="",J8=""),"",J8-B8) -> 2 | BA8: =IF(OR(J8="",P8=""),"",P8-J8) -> 5 | BB8: =IF(OR(P8="",AY8=""),"",AY8-P8) -> 18 | BC8: =IF(OR(B8="",AY8=""),"",AY8-B8) -> 25 | BD8: =IF(OR(AR8="",O8=""),"",MAX(0,IF(AY8="",Settings!$B$4,AY8)-AR8)) -> 0 | BE8: =IF(OR(AY8="",AR8=""),"",IF(AND(AY8<=AR8,N(AU8)>=Settings!$B$6),"OTIF","Not OTIF")) -> OTIF | BF8: Approved | BG8: Photos\PSIL-PR-2026-0003.jpg | BI8: =IF(A8="","",IF(K8="Rejected","Rejected",IF(K8<>"Approved","Awaiting Approval",IF(O8="","Approved - PO Pending",IF(AY8<>"",IF(N(AJ8)>=0.999,"Closed","In-house Closed - Payment Due"),IF(AS8<>"","Receiving In-house","PO Issued - Awaiting Delivery")))))) -> Closed | BJ8: =IF(A8="","",IF(IF(AND(A8<>"",OR(B8="",C8="",E8="",F8="",H8="")),"PR info missing; ","")&IF(AND(K8="Approved",OR(J8="",I8="")),"Approval ref/date missing; ","")&IF(AND(O8<>"",K8<>"Approved"),"PO without approval; ","")&IF(AND(O8<>"",OR(P8="",M8="",Q8="",S8="",T8="")),"PO details missing; ","")&IF(AND(O8<>"",AR8=""),"Committed date missing; ","")&IF(AND(ISNUMBER(J8),ISNUMBER(B8),N(J8)<N(B8)),"Approval dated before PR; ","")&IF(AND(ISNUMBER(P8),ISNUMBER(J8),N(P8)<N(J8)),"PO dated before approval; ","")&IF(AND(ISNUMBER(AY8),ISNUMBER(AS8),N(AY8)<N(AS8)),"Close before in-house start; ","")&IF(AND(AY8<>"",AS8=""),"In-house start date missing; ","")&IF(AND(AY8<>"",AT8=""),"Qty received missing; ","")&IF(AND(AY8<>"",BF8=""),"QC status missing; ","")&IF(N(AT8)>N(Q8)*1.05,"Received > ordered +5%; ","")&IF(AND(N(AI8)>0,AE8=""),"Payment terms missing; ","")&IF(N(AI8)>N(AD8)+1,"Overpaid vs PO; ","")&IF(AND(N(AK8)>0,AY8<>"",AO8=""),"Payment due date missing; ","")="","OK",IF(AND(A8<>"",OR(B8="",C8="",E8="",F8="",H8="")),"PR info missing; ","")&IF(AND(K8="Approved",OR(J8="",I8="")),"Approval ref/date missing; ","")&IF(AND(O8<>"",K8<>"Approved"),"PO without approval; ","")&IF(AND(O8<>"",OR(P8="",M8="",Q8="",S8="",T8="")),"PO details missing; ","")&IF(AND(O8<>"",AR8=""),"Committed date missing; ","")&IF(AND(ISNUMBER(J8),ISNUMBER(B8),N(J8)<N(B8)),"Approval dated before PR; ","")&IF(AND(ISNUMBER(P8),ISNUMBER(J8),N(P8)<N(J8)),"PO dated before approval; ","")&IF(AND(ISNUMBER(AY8),ISNUMBER(AS8),N(AY8)<N(AS8)),"Close before in-house start; ","")&IF(AND(AY8<>"",AS8=""),"In-house start date missing; ","")&IF(AND(AY8<>"",AT8=""),"Qty received missing; ","")&IF(AND(AY8<>"",BF8=""),"QC status missing; ","")&IF(N(AT8)>N(Q8)*1.05,"Received > ordered +5%; ","")&IF(AND(N(AI8)>0,AE8=""),"Payment terms missing; ","")&IF(N(AI8)>N(AD8)+1,"Overpaid vs PO; ","")&IF(AND(N(AK8)>0,AY8<>"",AO8=""),"Payment due date missing; ",""))) -> OK | BK8: =IF(A8="","",IF(N(AP8)>0,"Pay supplier: "&N(AP8)&" days overdue; ","")&IF(AND(O8<>"",AY8="",N(BD8)>0),"Expedite delivery: "&N(BD8)&" days late; ","")&IF(AND(BI8="Awaiting Approval",ISNUMBER(B8),Settings!$B$4-N(B8)>Settings!$B$19),"Get approval: PR waiting "&(Settings!$B$4-N(B8))&" days; ","")&IF(AND(BI8="Approved - PO Pending",ISNUMBER(J8),Settings!$B$4-N(J8)>Settings!$B$20),"Issue PO: approved "&(Settings!$B$4-N(J8))&" days ago; ","")&IF(AND(OR(BI8="Awaiting Approval",BI8="Approved - PO Pending"),N(AB8)>Settings!$B$7),"Negotiate price: "&TEXT(AB8,"0%")&" above budget; ","")&IF(LEFT(AX8,12)="Short Closed","Short closed: claim balance / credit note"&IF(N(AL8)>0," BDT "&TEXT(AL8,"#,##0"),"")&"; ","")&IF(BF8="Rejected","QC rejected: return / replace; ","")&IF(AND(O8<>"",AY8="",N(AL8)>0,N(BD8)>0),"Advance at risk: BDT "&TEXT(AL8,"#,##0")&" paid, goods late; ","")&IF(AND(BJ8<>"",BJ8<>"OK"),"Fix data entry (see Data Check); ","")) | BL8: =IF(BK8="","",IF(OR(N(AP8)>30,AND(AY8="",N(BD8)>15),BF8="Rejected",AND(LEFT(AX8,12)="Short Closed",N(AL8)>0),AND(O8<>"",AY8="",N(AL8)>0,N(BD8)>0)),"High",IF(OR(N(AP8)>0,AND(AY8="",N(BD8)>7),LEFT(AX8,12)="Short Closed",AND(BI8="Awaiting Approval",ISNUMBER(B8),Settings!$B$4-N(B8)>2*Settings!$B$19),AND(BI8="Approved - PO Pending",ISNUMBER(J8),Settings!$B$4-N(J8)>2*Settings!$B$20)),"Medium","Low"))) | BM8: =IF(BL8="","",IF(BL8="High",1,IF(BL8="Medium",2,3))*10000+ROW())
A9: PSIL-PR-2026-0004 | B9: 46184 | C9: Cutting | D9: Cutting Manager | E9: PU Synthetic Leather | F9: Synthetic & Textile | G9: 1.0 mm, White, 54" | H9: OPEX | I9: OPX-2026-104 | J9: 46188 | K9: Approved | L9: GM Operations | M9: Dongguan Sole Tech Co. | N9: Import | O9: PSIL-PO-2026-0004 | P9: 46191 | Q9: 7400 | R9: meter | S9: 3.11 | T9: USD | U9: =IF(AND(T9="",S9=""),"",IF(T9="",1,IFERROR(INDEX(Settings!$B$12:$B$16,MATCH(T9,Settings!$A$12:$A$16,0)),1))) -> 122 | V9: 373.98 | W9: =IF(OR(Q9="",S9=""),"",Q9*S9*U9) -> 2807708 | X9: =IF(OR(W9="",N(Q9)=0),"",W9/Q9) -> 379.42 | Y9: =IF(OR(X9="",P9="",E9=""),"",IF(_xlfn.MAXIFS($P$6:$P$205,$E$6:$E$205,E9,$P$6:$P$205,"<"&P9,$X$6:$X$205,">0")=0,"",IFERROR(AVERAGEIFS($X$6:$X$205,$E$6:$E$205,E9,$P$6:$P$205,_xlfn.MAXIFS($P$6:$P$205,$E$6:$E$205,E9,$P$6:$P$205,"<"&P9,$X$6:$X$205,">0"),$X$6:$X$205,">0"),""))) | Z9: =IF(OR(Y9="",X9=""),"",X9/Y9-1) | AA9: =IF(OR(W9="",V9=""),"",W9-Q9*V9) -> 40256 | AB9: =IF(AA9="","",IF(N(V9)*N(Q9)=0,"",AA9/(Q9*V9))) -> 0.014546232 | AC9: 0.15 | AD9: =IF(W9="","",W9*(1+N(AC9))) -> 3228864.2 | AE9: LC at Sight | AH9: 3228864.2 | AI9: =IF(A9="","",N(AF9)+N(AG9)+N(AH9)) -> 3228864.2 | AJ9: =IF(AD9="","",IF(N(AD9)=0,"",AI9/AD9)) -> 1 | AK9: =IF(AD9="","",IF(AD9-AI9<1,0,ROUND(AD9-AI9,2))) -> 0 | AL9: =IF(OR(O9="",AD9=""),"",MAX(0,ROUND(N(AI9)-(AD9-N(AW9)),0))) -> 0 | AM9: =IF(A9="","",IF(O9="","No PO Yet",IF(AI9=0,"Not Paid",IF(N(AJ9)>=0.999,"Fully Paid",IF(N(AG9)+N(AH9)>0,"Partially Paid","Initial / Advance Paid"))))) -> Fully Paid | AN9: 46223 | AP9: =IF(AK9="","",IF(OR(N(AK9)=0,AO9=""),"",MAX(0,Settings!$B$4-AO9))) | AQ9: =IF(AK9="","",IF(N(AK9)<=0,"",IF(AO9="","No Due Date",IF(Settings!$B$4<=AO9,"Not Yet Due",IF(Settings!$B$4-AO9<=30,"1-30 Days",IF(Settings!$B$4-AO9<=60,"31-60 Days",IF(Settings!$B$4-AO9<=90,"61-90 Days","90+ Days"))))))) | AR9: 46233 | AS9: 46229 | AT9: 7400 | AU9: =IF(Q9="","",IF(N(Q9)=0,"",N(AT9)/Q9)) -> 1 | AV9: =IF(OR(A9="",O9="",Q9=""),"",MAX(0,Q9-N(AT9))) -> 0 | AW9: =IF(OR(AV9="",W9=""),"",IF(N(Q9)=0,0,AV9/Q9*AD9)) -> 0 | AX9: =IF(A9="","",IF(O9="","No PO Yet",IF(Q9="","Order Qty Missing",IF(N(AT9)>=Q9,IF(N(AT9)>Q9,"All In-house (+"&TEXT(N(AT9)-Q9,"#,##0")&" "&R9&" excess)","All In-house"),IF(AY9<>"","Short Closed - "&TEXT(AV9,"#,##0")&" "&R9&" not received",IF(N(AT9)=0,"Not Started - "&TEXT(AV9,"#,##0")&" "&R9&" pending","Pending "&TEXT(AV9,"#,##0")&" "&R9&" ("&TEXT(AU9,"0%")&" received)")))))) -> All In-house | AY9: 46230 | AZ9: =IF(OR(B9="",J9=""),"",J9-B9) -> 4 | BA9: =IF(OR(J9="",P9=""),"",P9-J9) -> 3 | BB9: =IF(OR(P9="",AY9=""),"",AY9-P9) -> 39 | BC9: =IF(OR(B9="",AY9=""),"",AY9-B9) -> 46 | BD9: =IF(OR(AR9="",O9=""),"",MAX(0,IF(AY9="",Settings!$B$4,AY9)-AR9)) -> 0 | BE9: =IF(OR(AY9="",AR9=""),"",IF(AND(AY9<=AR9,N(AU9)>=Settings!$B$6),"OTIF","Not OTIF")) -> OTIF | BF9: Approved | BG9: Photos\PSIL-PR-2026-0004.jpg | BI9: =IF(A9="","",IF(K9="Rejected","Rejected",IF(K9<>"Approved","Awaiting Approval",IF(O9="","Approved - PO Pending",IF(AY9<>"",IF(N(AJ9)>=0.999,"Closed","In-house Closed - Payment Due"),IF(AS9<>"","Receiving In-house","PO Issued - Awaiting Delivery")))))) -> Closed | BJ9: =IF(A9="","",IF(IF(AND(A9<>"",OR(B9="",C9="",E9="",F9="",H9="")),"PR info missing; ","")&IF(AND(K9="Approved",OR(J9="",I9="")),"Approval ref/date missing; ","")&IF(AND(O9<>"",K9<>"Approved"),"PO without approval; ","")&IF(AND(O9<>"",OR(P9="",M9="",Q9="",S9="",T9="")),"PO details missing; ","")&IF(AND(O9<>"",AR9=""),"Committed date missing; ","")&IF(AND(ISNUMBER(J9),ISNUMBER(B9),N(J9)<N(B9)),"Approval dated before PR; ","")&IF(AND(ISNUMBER(P9),ISNUMBER(J9),N(P9)<N(J9)),"PO dated before approval; ","")&IF(AND(ISNUMBER(AY9),ISNUMBER(AS9),N(AY9)<N(AS9)),"Close before in-house start; ","")&IF(AND(AY9<>"",AS9=""),"In-house start date missing; ","")&IF(AND(AY9<>"",AT9=""),"Qty received missing; ","")&IF(AND(AY9<>"",BF9=""),"QC status missing; ","")&IF(N(AT9)>N(Q9)*1.05,"Received > ordered +5%; ","")&IF(AND(N(AI9)>0,AE9=""),"Payment terms missing; ","")&IF(N(AI9)>N(AD9)+1,"Overpaid vs PO; ","")&IF(AND(N(AK9)>0,AY9<>"",AO9=""),"Payment due date missing; ","")="","OK",IF(AND(A9<>"",OR(B9="",C9="",E9="",F9="",H9="")),"PR info missing; ","")&IF(AND(K9="Approved",OR(J9="",I9="")),"Approval ref/date missing; ","")&IF(AND(O9<>"",K9<>"Approved"),"PO without approval; ","")&IF(AND(O9<>"",OR(P9="",M9="",Q9="",S9="",T9="")),"PO details missing; ","")&IF(AND(O9<>"",AR9=""),"Committed date missing; ","")&IF(AND(ISNUMBER(J9),ISNUMBER(B9),N(J9)<N(B9)),"Approval dated before PR; ","")&IF(AND(ISNUMBER(P9),ISNUMBER(J9),N(P9)<N(J9)),"PO dated before approval; ","")&IF(AND(ISNUMBER(AY9),ISNUMBER(AS9),N(AY9)<N(AS9)),"Close before in-house start; ","")&IF(AND(AY9<>"",AS9=""),"In-house start date missing; ","")&IF(AND(AY9<>"",AT9=""),"Qty received missing; ","")&IF(AND(AY9<>"",BF9=""),"QC status missing; ","")&IF(N(AT9)>N(Q9)*1.05,"Received > ordered +5%; ","")&IF(AND(N(AI9)>0,AE9=""),"Payment terms missing; ","")&IF(N(AI9)>N(AD9)+1,"Overpaid vs PO; ","")&IF(AND(N(AK9)>0,AY9<>"",AO9=""),"Payment due date missing; ",""))) -> OK | BK9: =IF(A9="","",IF(N(AP9)>0,"Pay supplier: "&N(AP9)&" days overdue; ","")&IF(AND(O9<>"",AY9="",N(BD9)>0),"Expedite delivery: "&N(BD9)&" days late; ","")&IF(AND(BI9="Awaiting Approval",ISNUMBER(B9),Settings!$B$4-N(B9)>Settings!$B$19),"Get approval: PR waiting "&(Settings!$B$4-N(B9))&" days; ","")&IF(AND(BI9="Approved - PO Pending",ISNUMBER(J9),Settings!$B$4-N(J9)>Settings!$B$20),"Issue PO: approved "&(Settings!$B$4-N(J9))&" days ago; ","")&IF(AND(OR(BI9="Awaiting Approval",BI9="Approved - PO Pending"),N(AB9)>Settings!$B$7),"Negotiate price: "&TEXT(AB9,"0%")&" above budget; ","")&IF(LEFT(AX9,12)="Short Closed","Short closed: claim balance / credit note"&IF(N(AL9)>0," BDT "&TEXT(AL9,"#,##0"),"")&"; ","")&IF(BF9="Rejected","QC rejected: return / replace; ","")&IF(AND(O9<>"",AY9="",N(AL9)>0,N(BD9)>0),"Advance at risk: BDT "&TEXT(AL9,"#,##0")&" paid, goods late; ","")&IF(AND(BJ9<>"",BJ9<>"OK"),"Fix data entry (see Data Check); ","")) | BL9: =IF(BK9="","",IF(OR(N(AP9)>30,AND(AY9="",N(BD9)>15),BF9="Rejected",AND(LEFT(AX9,12)="Short Closed",N(AL9)>0),AND(O9<>"",AY9="",N(AL9)>0,N(BD9)>0)),"High",IF(OR(N(AP9)>0,AND(AY9="",N(BD9)>7),LEFT(AX9,12)="Short Closed",AND(BI9="Awaiting Approval",ISNUMBER(B9),Settings!$B$4-N(B9)>2*Settings!$B$19),AND(BI9="Approved - PO Pending",ISNUMBER(J9),Settings!$B$4-N(J9)>2*Settings!$B$20)),"Medium","Low"))) | BM9: =IF(BL9="","",IF(BL9="High",1,IF(BL9="Medium",2,3))*10000+ROW())
A10: PSIL-PR-2026-0005 | B10: 46187 | C10: Lasting & Assembly | D10: Lasting Manager | E10: Rubber Outsole – Men's Derby | F10: Sole & Bottom | G10: Size 39–45, Black | H10: OPEX | I10: OPX-2026-105 | J10: 46188 | K10: Approved | L10: CFO | M10: Bengal Sole Industries | N10: Local | O10: PSIL-PO-2026-0005 | P10: 46193 | Q10: 11000 | R10: pair | S10: 186 | T10: BDT | U10: =IF(AND(T10="",S10=""),"",IF(T10="",1,IFERROR(INDEX(Settings!$B$12:$B$16,MATCH(T10,Settings!$A$12:$A$16,0)),1))) -> 1 | V10: 186.21 | W10: =IF(OR(Q10="",S10=""),"",Q10*S10*U10) -> 2046000 | X10: =IF(OR(W10="",N(Q10)=0),"",W10/Q10) -> 186 | Y10: =IF(OR(X10="",P10="",E10=""),"",IF(_xlfn.MAXIFS($P$6:$P$205,$E$6:$E$205,E10,$P$6:$P$205,"<"&P10,$X$6:$X$205,">0")=0,"",IFERROR(AVERAGEIFS($X$6:$X$205,$E$6:$E$205,E10,$P$6:$P$205,_xlfn.MAXIFS($P$6:$P$205,$E$6:$E$205,E10,$P$6:$P$205,"<"&P10,$X$6:$X$205,">0"),$X$6:$X$205,">0"),""))) | Z10: =IF(OR(Y10="",X10=""),"",X10/Y10-1) | AA10: =IF(OR(W10="",V10=""),"",W10-Q10*V10) -> -2310 | AB10: =IF(AA10="","",IF(N(V10)*N(Q10)=0,"",AA10/(Q10*V10))) -> -0.001127759 | AC10: 0.05 | AD10: =IF(W10="","",W10*(1+N(AC10))) -> 2148300 | AE10: Credit 30 Days | AG10: 1074150 | AI10: =IF(A10="","",N(AF10)+N(AG10)+N(AH10)) -> 1074150 | AJ10: =IF(AD10="","",IF(N(AD10)=0,"",AI10/AD10)) -> 0.5 | AK10: =IF(AD10="","",IF(AD10-AI10<1,0,ROUND(AD10-AI10,2))) -> 1074150 | AL10: =IF(OR(O10="",AD10=""),"",MAX(0,ROUND(N(AI10)-(AD10-N(AW10)),0))) -> 0 | AM10: =IF(A10="","",IF(O10="","No PO Yet",IF(AI10=0,"Not Paid",IF(N(AJ10)>=0.999,"Fully Paid",IF(N(AG10)+N(AH10)>0,"Partially Paid","Initial / Advance Paid"))))) -> Partially Paid | AN10: 46239 | AO10: 46239 | AP10: =IF(AK10="","",IF(OR(N(AK10)=0,AO10=""),"",MAX(0,Settings!$B$4-AO10))) -> 71 | AQ10: =IF(AK10="","",IF(N(AK10)<=0,"",IF(AO10="","No Due Date",IF(Settings!$B$4<=AO10,"Not Yet Due",IF(Settings!$B$4-AO10<=30,"1-30 Days",IF(Settings!$B$4-AO10<=60,"31-60 Days",IF(Settings!$B$4-AO10<=90,"61-90 Days","90+ Days"))))))) -> 61-90 Days | AR10: 46209 | AS10: 46208 | AT10: 10439 | AU10: =IF(Q10="","",IF(N(Q10)=0,"",N(AT10)/Q10)) -> 0.949 | AV10: =IF(OR(A10="",O10="",Q10=""),"",MAX(0,Q10-N(AT10))) -> 561 | AW10: =IF(OR(AV10="",W10=""),"",IF(N(Q10)=0,0,AV10/Q10*AD10)) -> 109563.3 | AX10: =IF(A10="","",IF(O10="","No PO Yet",IF(Q10="","Order Qty Missing",IF(N(AT10)>=Q10,IF(N(AT10)>Q10,"All In-house (+"&TEXT(N(AT10)-Q10,"#,##0")&" "&R10&" excess)","All In-house"),IF(AY10<>"","Short Closed - "&TEXT(AV10,"#,##0")&" "&R10&" not received",IF(N(AT10)=0,"Not Started - "&TEXT(AV10,"#,##0")&" "&R10&" pending","Pending "&TEXT(AV10,"#,##0")&" "&R10&" ("&TEXT(AU10,"0%")&" received)")))))) -> Short Closed - 561 pair not received | AY10: 46209 | AZ10: =IF(OR(B10="",J10=""),"",J10-B10) -> 1 | BA10: =IF(OR(J10="",P10=""),"",P10-J10) -> 5 | BB10: =IF(OR(P10="",AY10=""),"",AY10-P10) -> 16 | BC10: =IF(OR(B10="",AY10=""),"",AY10-B10) -> 22 | BD10: =IF(OR(AR10="",O10=""),"",MAX(0,IF(AY10="",Settings!$B$4,AY10)-AR10)) -> 0 | BE10: =IF(OR(AY10="",AR10=""),"",IF(AND(AY10<=AR10,N(AU10)>=Settings!$B$6),"OTIF","Not OTIF")) -> Not OTIF | BF10: Approved | BG10: Photos\PSIL-PR-2026-0005.jpg | BI10: =IF(A10="","",IF(K10="Rejected","Rejected",IF(K10<>"Approved","Awaiting Approval",IF(O10="","Approved - PO Pending",IF(AY10<>"",IF(N(AJ10)>=0.999,"Closed","In-house Closed - Payment Due"),IF(AS10<>"","Receiving In-house","PO Issued - Awaiting Delivery")))))) -> In-house Closed - Payment Due | BJ10: =IF(A10="","",IF(IF(AND(A10<>"",OR(B10="",C10="",E10="",F10="",H10="")),"PR info missing; ","")&IF(AND(K10="Approved",OR(J10="",I10="")),"Approval ref/date missing; ","")&IF(AND(O10<>"",K10<>"Approved"),"PO without approval; ","")&IF(AND(O10<>"",OR(P10="",M10="",Q10="",S10="",T10="")),"PO details missing; ","")&IF(AND(O10<>"",AR10=""),"Committed date missing; ","")&IF(AND(ISNUMBER(J10),ISNUMBER(B10),N(J10)<N(B10)),"Approval dated before PR; ","")&IF(AND(ISNUMBER(P10),ISNUMBER(J10),N(P10)<N(J10)),"PO dated before approval; ","")&IF(AND(ISNUMBER(AY10),ISNUMBER(AS10),N(AY10)<N(AS10)),"Close before in-house start; ","")&IF(AND(AY10<>"",AS10=""),"In-house start date missing; ","")&IF(AND(AY10<>"",AT10=""),"Qty received missing; ","")&IF(AND(AY10<>"",BF10=""),"QC status missing; ","")&IF(N(AT10)>N(Q10)*1.05,"Received > ordered +5%; ","")&IF(AND(N(AI10)>0,AE10=""),"Payment terms missing; ","")&IF(N(AI10)>N(AD10)+1,"Overpaid vs PO; ","")&IF(AND(N(AK10)>0,AY10<>"",AO10=""),"Payment due date missing; ","")="","OK",IF(AND(A10<>"",OR(B10="",C10="",E10="",F10="",H10="")),"PR info missing; ","")&IF(AND(K10="Approved",OR(J10="",I10="")),"Approval ref/date missing; ","")&IF(AND(O10<>"",K10<>"Approved"),"PO without approval; ","")&IF(AND(O10<>"",OR(P10="",M10="",Q10="",S10="",T10="")),"PO details missing; ","")&IF(AND(O10<>"",AR10=""),"Committed date missing; ","")&IF(AND(ISNUMBER(J10),ISNUMBER(B10),N(J10)<N(B10)),"Approval dated before PR; ","")&IF(AND(ISNUMBER(P10),ISNUMBER(J10),N(P10)<N(J10)),"PO dated before approval; ","")&IF(AND(ISNUMBER(AY10),ISNUMBER(AS10),N(AY10)<N(AS10)),"Close before in-house start; ","")&IF(AND(AY10<>"",AS10=""),"In-house start date missing; ","")&IF(AND(AY10<>"",AT10=""),"Qty received missing; ","")&IF(AND(AY10<>"",BF10=""),"QC status missing; ","")&IF(N(AT10)>N(Q10)*1.05,"Received > ordered +5%; ","")&IF(AND(N(AI10)>0,AE10=""),"Payment terms missing; ","")&IF(N(AI10)>N(AD10)+1,"Overpaid vs PO; ","")&IF(AND(N(AK10)>0,AY10<>"",AO10=""),"Payment due date missing; ",""))) -> OK | BK10: =IF(A10="","",IF(N(AP10)>0,"Pay supplier: "&N(AP10)&" days overdue; ","")&IF(AND(O10<>"",AY10="",N(BD10)>0),"Expedite delivery: "&N(BD10)&" days late; ","")&IF(AND(BI10="Awaiting Approval",ISNUMBER(B10),Settings!$B$4-N(B10)>Settings!$B$19),"Get approval: PR waiting "&(Settings!$B$4-N(B10))&" days; ","")&IF(AND(BI10="Approved - PO Pending",ISNUMBER(J10),Settings!$B$4-N(J10)>Settings!$B$20),"Issue PO: approved "&(Settings!$B$4-N(J10))&" days ago; ","")&IF(AND(OR(BI10="Awaiting Approval",BI10="Approved - PO Pending"),N(AB10)>Settings!$B$7),"Negotiate price: "&TEXT(AB10,"0%")&" above budget; ","")&IF(LEFT(AX10,12)="Short Closed","Short closed: claim balance / credit note"&IF(N(AL10)>0," BDT "&TEXT(AL10,"#,##0"),"")&"; ","")&IF(BF10="Rejected","QC rejected: return / replace; ","")&IF(AND(O10<>"",AY10="",N(AL10)>0,N(BD10)>0),"Advance at risk: BDT "&TEXT(AL10,"#,##0")&" paid, goods late; ","")&IF(AND(BJ10<>"",BJ10<>"OK"),"Fix data entry (see Data Check); ","")) -> Pay supplier: 71 days overdue; Short closed: claim balance / credit note; | BL10: =IF(BK10="","",IF(OR(N(AP10)>30,AND(AY10="",N(BD10)>15),BF10="Rejected",AND(LEFT(AX10,12)="Short Closed",N(AL10)>0),AND(O10<>"",AY10="",N(AL10)>0,N(BD10)>0)),"High",IF(OR(N(AP10)>0,AND(AY10="",N(BD10)>7),LEFT(AX10,12)="Short Closed",AND(BI10="Awaiting Approval",ISNUMBER(B10),Settings!$B$4-N(B10)>2*Settings!$B$19),AND(BI10="Approved - PO Pending",ISNUMBER(J10),Settings!$B$4-N(J10)>2*Settings!$B$20)),"Medium","Low"))) -> High | BM10: =IF(BL10="","",IF(BL10="High",1,IF(BL10="Medium",2,3))*10000+ROW()) -> 10010 | BN10: Price above budget — CFO note on file
A11: PSIL-PR-2026-0006 | B11: 46190 | C11: Lasting & Assembly | D11: Lasting Manager | E11: TPR Outsole – Ladies Casual | F11: Sole & Bottom | G11: Size 35–41, Beige | H11: OPEX | I11: OPX-2026-106 | J11: 46194 | K11: Approved | L11: CFO | M11: Bengal Sole Industries | N11: Local | O11: PSIL-PO-2026-0006 | P11: 46195 | Q11: 6800 | R11: pair | S11: 125 | T11: BDT | U11: =IF(AND(T11="",S11=""),"",IF(T11="",1,IFERROR(INDEX(Settings!$B$12:$B$16,MATCH(T11,Settings!$A$12:$A$16,0)),1))) -> 1 | V11: 120.68 | W11: =IF(OR(Q11="",S11=""),"",Q11*S11*U11) -> 850000 | X11: =IF(OR(W11="",N(Q11)=0),"",W11/Q11) -> 125 | Y11: =IF(OR(X11="",P11="",E11=""),"",IF(_xlfn.MAXIFS($P$6:$P$205,$E$6:$E$205,E11,$P$6:$P$205,"<"&P11,$X$6:$X$205,">0")=0,"",IFERROR(AVERAGEIFS($X$6:$X$205,$E$6:$E$205,E11,$P$6:$P$205,_xlfn.MAXIFS($P$6:$P$205,$E$6:$E$205,E11,$P$6:$P$205,"<"&P11,$X$6:$X$205,">0"),$X$6:$X$205,">0"),""))) | Z11: =IF(OR(Y11="",X11=""),"",X11/Y11-1) | AA11: =IF(OR(W11="",V11=""),"",W11-Q11*V11) -> 29376 | AB11: =IF(AA11="","",IF(N(V11)*N(Q11)=0,"",AA11/(Q11*V11))) -> 0.035797149 | AC11: 0.05 | AD11: =IF(W11="","",W11*(1+N(AC11))) -> 892500 | AE11: 100% Advance | AF11: 892500 | AI11: =IF(A11="","",N(AF11)+N(AG11)+N(AH11)) -> 892500 | AJ11: =IF(AD11="","",IF(N(AD11)=0,"",AI11/AD11)) -> 1 | AK11: =IF(AD11="","",IF(AD11-AI11<1,0,ROUND(AD11-AI11,2))) -> 0 | AL11: =IF(OR(O11="",AD11=""),"",MAX(0,ROUND(N(AI11)-(AD11-N(AW11)),0))) -> 0 | AM11: =IF(A11="","",IF(O11="","No PO Yet",IF(AI11=0,"Not Paid",IF(N(AJ11)>=0.999,"Fully Paid",IF(N(AG11)+N(AH11)>0,"Partially Paid","Initial / Advance Paid"))))) -> Fully Paid | AN11: 46196 | AP11: =IF(AK11="","",IF(OR(N(AK11)=0,AO11=""),"",MAX(0,Settings!$B$4-AO11))) | AQ11: =IF(AK11="","",IF(N(AK11)<=0,"",IF(AO11="","No Due Date",IF(Settings!$B$4<=AO11,"Not Yet Due",IF(Settings!$B$4-AO11<=30,"1-30 Days",IF(Settings!$B$4-AO11<=60,"31-60 Days",IF(Settings!$B$4-AO11<=90,"61-90 Days","90+ Days"))))))) | AR11: 46209 | AS11: 46204 | AT11: 6800 | AU11: =IF(Q11="","",IF(N(Q11)=0,"",N(AT11)/Q11)) -> 1 | AV11: =IF(OR(A11="",O11="",Q11=""),"",MAX(0,Q11-N(AT11))) -> 0 | AW11: =IF(OR(AV11="",W11=""),"",IF(N(Q11)=0,0,AV11/Q11*AD11)) -> 0 | AX11: =IF(A11="","",IF(O11="","No PO Yet",IF(Q11="","Order Qty Missing",IF(N(AT11)>=Q11,IF(N(AT11)>Q11,"All In-house (+"&TEXT(N(AT11)-Q11,"#,##0")&" "&R11&" excess)","All In-house"),IF(AY11<>"","Short Closed - "&TEXT(AV11,"#,##0")&" "&R11&" not received",IF(N(AT11)=0,"Not Started - "&TEXT(AV11,"#,##0")&" "&R11&" pending","Pending "&TEXT(AV11,"#,##0")&" "&R11&" ("&TEXT(AU11,"0%")&" received)")))))) -> All In-house | AY11: 46204 | AZ11: =IF(OR(B11="",J11=""),"",J11-B11) -> 4 | BA11: =IF(OR(J11="",P11=""),"",P11-J11) -> 1 | BB11: =IF(OR(P11="",AY11=""),"",AY11-P11) -> 9 | BC11: =IF(OR(B11="",AY11=""),"",AY11-B11) -> 14 | BD11: =IF(OR(AR11="",O11=""),"",MAX(0,IF(AY11="",Settings!$B$4,AY11)-AR11)) -> 0 | BE11: =IF(OR(AY11="",AR11=""),"",IF(AND(AY11<=AR11,N(AU11)>=Settings!$B$6),"OTIF","Not OTIF")) -> OTIF | BF11: Approved | BG11: Photos\PSIL-PR-2026-0006.jpg | BI11: =IF(A11="","",IF(K11="Rejected","Rejected",IF(K11<>"Approved","Awaiting Approval",IF(O11="","Approved - PO Pending",IF(AY11<>"",IF(N(AJ11)>=0.999,"Closed","In-house Closed - Payment Due"),IF(AS11<>"","Receiving In-house","PO Issued - Awaiting Delivery")))))) -> Closed | BJ11: =IF(A11="","",IF(IF(AND(A11<>"",OR(B11="",C11="",E11="",F11="",H11="")),"PR info missing; ","")&IF(AND(K11="Approved",OR(J11="",I11="")),"Approval ref/date missing; ","")&IF(AND(O11<>"",K11<>"Approved"),"PO without approval; ","")&IF(AND(O11<>"",OR(P11="",M11="",Q11="",S11="",T11="")),"PO details missing; ","")&IF(AND(O11<>"",AR11=""),"Committed date missing; ","")&IF(AND(ISNUMBER(J11),ISNUMBER(B11),N(J11)<N(B11)),"Approval dated before PR; ","")&IF(AND(ISNUMBER(P11),ISNUMBER(J11),N(P11)<N(J11)),"PO dated before approval; ","")&IF(AND(ISNUMBER(AY11),ISNUMBER(AS11),N(AY11)<N(AS11)),"Close before in-house start; ","")&IF(AND(AY11<>"",AS11=""),"In-house start date missing; ","")&IF(AND(AY11<>"",AT11=""),"Qty received missing; ","")&IF(AND(AY11<>"",BF11=""),"QC status missing; ","")&IF(N(AT11)>N(Q11)*1.05,"Received > ordered +5%; ","")&IF(AND(N(AI11)>0,AE11=""),"Payment terms missing; ","")&IF(N(AI11)>N(AD11)+1,"Overpaid vs PO; ","")&IF(AND(N(AK11)>0,AY11<>"",AO11=""),"Payment due date missing; ","")="","OK",IF(AND(A11<>"",OR(B11="",C11="",E11="",F11="",H11="")),"PR info missing; ","")&IF(AND(K11="Approved",OR(J11="",I11="")),"Approval ref/date missing; ","")&IF(AND(O11<>"",K11<>"Approved"),"PO without approval; ","")&IF(AND(O11<>"",OR(P11="",M11="",Q11="",S11="",T11="")),"PO details missing; ","")&IF(AND(O11<>"",AR11=""),"Committed date missing; ","")&IF(AND(ISNUMBER(J11),ISNUMBER(B11),N(J11)<N(B11)),"Approval dated before PR; ","")&IF(AND(ISNUMBER(P11),ISNUMBER(J11),N(P11)<N(J11)),"PO dated before approval; ","")&IF(AND(ISNUMBER(AY11),ISNUMBER(AS11),N(AY11)<N(AS11)),"Close before in-house start; ","")&IF(AND(AY11<>"",AS11=""),"In-house start date missing; ","")&IF(AND(AY11<>"",AT11=""),"Qty received missing; ","")&IF(AND(AY11<>"",BF11=""),"QC status missing; ","")&IF(N(AT11)>N(Q11)*1.05,"Received > ordered +5%; ","")&IF(AND(N(AI11)>0,AE11=""),"Payment terms missing; ","")&IF(N(AI11)>N(AD11)+1,"Overpaid vs PO; ","")&IF(AND(N(AK11)>0,AY11<>"",AO11=""),"Payment due date missing; ",""))) -> OK | BK11: =IF(A11="","",IF(N(AP11)>0,"Pay supplier: "&N(AP11)&" days overdue; ","")&IF(AND(O11<>"",AY11="",N(BD11)>0),"Expedite delivery: "&N(BD11)&" days late; ","")&IF(AND(BI11="Awaiting Approval",ISNUMBER(B11),Settings!$B$4-N(B11)>Settings!$B$19),"Get approval: PR waiting "&(Settings!$B$4-N(B11))&" days; ","")&IF(AND(BI11="Approved - PO Pending",ISNUMBER(J11),Settings!$B$4-N(J11)>Settings!$B$20),"Issue PO: approved "&(Settings!$B$4-N(J11))&" days ago; ","")&IF(AND(OR(BI11="Awaiting Approval",BI11="Approved - PO Pending"),N(AB11)>Settings!$B$7),"Negotiate price: "&TEXT(AB11,"0%")&" above budget; ","")&IF(LEFT(AX11,12)="Short Closed","Short closed: claim balance / credit note"&IF(N(AL11)>0," BDT "&TEXT(AL11,"#,##0"),"")&"; ","")&IF(BF11="Rejected","QC rejected: return / replace; ","")&IF(AND(O11<>"",AY11="",N(AL11)>0,N(BD11)>0),"Advance at risk: BDT "&TEXT(AL11,"#,##0")&" paid, goods late; ","")&IF(AND(BJ11<>"",BJ11<>"OK"),"Fix data entry (see Data Check); ","")) | BL11: =IF(BK11="","",IF(OR(N(AP11)>30,AND(AY11="",N(BD11)>15),BF11="Rejected",AND(LEFT(AX11,12)="Short Closed",N(AL11)>0),AND(O11<>"",AY11="",N(AL11)>0,N(BD11)>0)),"High",IF(OR(N(AP11)>0,AND(AY11="",N(BD11)>7),LEFT(AX11,12)="Short Closed",AND(BI11="Awaiting Approval",ISNUMBER(B11),Settings!$B$4-N(B11)>2*Settings!$B$19),AND(BI11="Approved - PO Pending",ISNUMBER(J11),Settings!$B$4-N(J11)>2*Settings!$B$20)),"Medium","Low"))) | BM11: =IF(BL11="","",IF(BL11="High",1,IF(BL11="Medium",2,3))*10000+ROW())
A12: PSIL-PR-2026-0007 | B12: 46194 | C12: Lasting & Assembly | D12: Lasting Manager | E12: EVA Midsole Sheet | F12: Sole & Bottom | G12: 6 mm, Shore 45A | H12: OPEX | I12: OPX-2026-107 | J12: 46198 | K12: Approved | L12: GM Operations | M12: Dongguan Sole Tech Co. | N12: Import | O12: PSIL-PO-2026-0007 | P12: 46199 | Q12: 4800 | R12: sheet | S12: 10.1 | T12: CNY | U12: =IF(AND(T12="",S12=""),"",IF(T12="",1,IFERROR(INDEX(Settings!$B$12:$B$16,MATCH(T12,Settings!$A$12:$A$16,0)),1))) -> 17 | V12: 159.41 | W12: =IF(OR(Q12="",S12=""),"",Q12*S12*U12) -> 824160 | X12: =IF(OR(W12="",N(Q12)=0),"",W12/Q12) -> 171.7 | Y12: =IF(OR(X12="",P12="",E12=""),"",IF(_xlfn.MAXIFS($P$6:$P$205,$E$6:$E$205,E12,$P$6:$P$205,"<"&P12,$X$6:$X$205,">0")=0,"",IFERROR(AVERAGEIFS($X$6:$X$205,$E$6:$E$205,E12,$P$6:$P$205,_xlfn.MAXIFS($P$6:$P$205,$E$6:$E$205,E12,$P$6:$P$205,"<"&P12,$X$6:$X$205,">0"),$X$6:$X$205,">0"),""))) | Z12: =IF(OR(Y12="",X12=""),"",X12/Y12-1) | AA12: =IF(OR(W12="",V12=""),"",W12-Q12*V12) -> 58992 | AB12: =IF(AA12="","",IF(N(V12)*N(Q12)=0,"",AA12/(Q12*V12))) -> 0.077096794 | AC12: 0.15 | AD12: =IF(W12="","",W12*(1+N(AC12))) -> 947784 | AE12: LC at Sight | AH12: 947784 | AI12: =IF(A12="","",N(AF12)+N(AG12)+N(AH12)) -> 947784 | AJ12: =IF(AD12="","",IF(N(AD12)=0,"",AI12/AD12)) -> 1 | AK12: =IF(AD12="","",IF(AD12-AI12<1,0,ROUND(AD12-AI12,2))) -> 0 | AL12: =IF(OR(O12="",AD12=""),"",MAX(0,ROUND(N(AI12)-(AD12-N(AW12)),0))) -> 0 | AM12: =IF(A12="","",IF(O12="","No PO Yet",IF(AI12=0,"Not Paid",IF(N(AJ12)>=0.999,"Fully Paid",IF(N(AG12)+N(AH12)>0,"Partially Paid","Initial / Advance Paid"))))) -> Fully Paid | AN12: 46238 | AP12: =IF(AK12="","",IF(OR(N(AK12)=0,AO12=""),"",MAX(0,Settings!$B$4-AO12))) | AQ12: =IF(AK12="","",IF(N(AK12)<=0,"",IF(AO12="","No Due Date",IF(Settings!$B$4<=AO12,"Not Yet Due",IF(Settings!$B$4-AO12<=30,"1-30 Days",IF(Settings!$B$4-AO12<=60,"31-60 Days",IF(Settings!$B$4-AO12<=90,"61-90 Days","90+ Days"))))))) | AR12: 46248 | AS12: 46247 | AT12: 4800 | AU12: =IF(Q12="","",IF(N(Q12)=0,"",N(AT12)/Q12)) -> 1 | AV12: =IF(OR(A12="",O12="",Q12=""),"",MAX(0,Q12-N(AT12))) -> 0 | AW12: =IF(OR(AV12="",W12=""),"",IF(N(Q12)=0,0,AV12/Q12*AD12)) -> 0 | AX12: =IF(A12="","",IF(O12="","No PO Yet",IF(Q12="","Order Qty Missing",IF(N(AT12)>=Q12,IF(N(AT12)>Q12,"All In-house (+"&TEXT(N(AT12)-Q12,"#,##0")&" "&R12&" excess)","All In-house"),IF(AY12<>"","Short Closed - "&TEXT(AV12,"#,##0")&" "&R12&" not received",IF(N(AT12)=0,"Not Started - "&TEXT(AV12,"#,##0")&" "&R12&" pending","Pending "&TEXT(AV12,"#,##0")&" "&R12&" ("&TEXT(AU12,"0%")&" received)")))))) -> All In-house | AY12: 46248 | AZ12: =IF(OR(B12="",J12=""),"",J12-B12) -> 4 | BA12: =IF(OR(J12="",P12=""),"",P12-J12) -> 1 | BB12: =IF(OR(P12="",AY12=""),"",AY12-P12) -> 49 | BC12: =IF(OR(B12="",AY12=""),"",AY12-B12) -> 54 | BD12: =IF(OR(AR12="",O12=""),"",MAX(0,IF(AY12="",Settings!$B$4,AY12)-AR12)) -> 0 | BE12: =IF(OR(AY12="",AR12=""),"",IF(AND(AY12<=AR12,N(AU12)>=Settings!$B$6),"OTIF","Not OTIF")) -> OTIF | BF12: Approved | BG12: Photos\PSIL-PR-2026-0007.jpg | BI12: =IF(A12="","",IF(K12="Rejected","Rejected",IF(K12<>"Approved","Awaiting Approval",IF(O12="","Approved - PO Pending",IF(AY12<>"",IF(N(AJ12)>=0.999,"Closed","In-house Closed - Payment Due"),IF(AS12<>"","Receiving In-house","PO Issued - Awaiting Delivery")))))) -> Closed | BJ12: =IF(A12="","",IF(IF(AND(A12<>"",OR(B12="",C12="",E12="",F12="",H12="")),"PR info missing; ","")&IF(AND(K12="Approved",OR(J12="",I12="")),"Approval ref/date missing; ","")&IF(AND(O12<>"",K12<>"Approved"),"PO without approval; ","")&IF(AND(O12<>"",OR(P12="",M12="",Q12="",S12="",T12="")),"PO details missing; ","")&IF(AND(O12<>"",AR12=""),"Committed date missing; ","")&IF(AND(ISNUMBER(J12),ISNUMBER(B12),N(J12)<N(B12)),"Approval dated before PR; ","")&IF(AND(ISNUMBER(P12),ISNUMBER(J12),N(P12)<N(J12)),"PO dated before approval; ","")&IF(AND(ISNUMBER(AY12),ISNUMBER(AS12),N(AY12)<N(AS12)),"Close before in-house start; ","")&IF(AND(AY12<>"",AS12=""),"In-house start date missing; ","")&IF(AND(AY12<>"",AT12=""),"Qty received missing; ","")&IF(AND(AY12<>"",BF12=""),"QC status missing; ","")&IF(N(AT12)>N(Q12)*1.05,"Received > ordered +5%; ","")&IF(AND(N(AI12)>0,AE12=""),"Payment terms missing; ","")&IF(N(AI12)>N(AD12)+1,"Overpaid vs PO; ","")&IF(AND(N(AK12)>0,AY12<>"",AO12=""),"Payment due date missing; ","")="","OK",IF(AND(A12<>"",OR(B12="",C12="",E12="",F12="",H12="")),"PR info missing; ","")&IF(AND(K12="Approved",OR(J12="",I12="")),"Approval ref/date missing; ","")&IF(AND(O12<>"",K12<>"Approved"),"PO without approval; ","")&IF(AND(O12<>"",OR(P12="",M12="",Q12="",S12="",T12="")),"PO details missing; ","")&IF(AND(O12<>"",AR12=""),"Committed date missing; ","")&IF(AND(ISNUMBER(J12),ISNUMBER(B12),N(J12)<N(B12)),"Approval dated before PR; ","")&IF(AND(ISNUMBER(P12),ISNUMBER(J12),N(P12)<N(J12)),"PO dated before approval; ","")&IF(AND(ISNUMBER(AY12),ISNUMBER(AS12),N(AY12)<N(AS12)),"Close before in-house start; ","")&IF(AND(AY12<>"",AS12=""),"In-house start date missing; ","")&IF(AND(AY12<>"",AT12=""),"Qty received missing; ","")&IF(AND(AY12<>"",BF12=""),"QC status missing; ","")&IF(N(AT12)>N(Q12)*1.05,"Received > ordered +5%; ","")&IF(AND(N(AI12)>0,AE12=""),"Payment terms missing; ","")&IF(N(AI12)>N(AD12)+1,"Overpaid vs PO; ","")&IF(AND(N(AK12)>0,AY12<>"",AO12=""),"Payment due date missing; ",""))) -> OK | BK12: =IF(A12="","",IF(N(AP12)>0,"Pay supplier: "&N(AP12)&" days overdue; ","")&IF(AND(O12<>"",AY12="",N(BD12)>0),"Expedite delivery: "&N(BD12)&" days late; ","")&IF(AND(BI12="Awaiting Approval",ISNUMBER(B12),Settings!$B$4-N(B12)>Settings!$B$19),"Get approval: PR waiting "&(Settings!$B$4-N(B12))&" days; ","")&IF(AND(BI12="Approved - PO Pending",ISNUMBER(J12),Settings!$B$4-N(J12)>Settings!$B$20),"Issue PO: approved "&(Settings!$B$4-N(J12))&" days ago; ","")&IF(AND(OR(BI12="Awaiting Approval",BI12="Approved - PO Pending"),N(AB12)>Settings!$B$7),"Negotiate price: "&TEXT(AB12,"0%")&" above budget; ","")&IF(LEFT(AX12,12)="Short Closed","Short closed: claim balance / credit note"&IF(N(AL12)>0," BDT "&TEXT(AL12,"#,##0"),"")&"; ","")&IF(BF12="Rejected","QC rejected: return / replace; ","")&IF(AND(O12<>"",AY12="",N(AL12)>0,N(BD12)>0),"Advance at risk: BDT "&TEXT(AL12,"#,##0")&" paid, goods late; ","")&IF(AND(BJ12<>"",BJ12<>"OK"),"Fix data entry (see Data Check); ","")) | BL12: =IF(BK12="","",IF(OR(N(AP12)>30,AND(AY12="",N(BD12)>15),BF12="Rejected",AND(LEFT(AX12,12)="Short Closed",N(AL12)>0),AND(O12<>"",AY12="",N(AL12)>0,N(BD12)>0)),"High",IF(OR(N(AP12)>0,AND(AY12="",N(BD12)>7),LEFT(AX12,12)="Short Closed",AND(BI12="Awaiting Approval",ISNUMBER(B12),Settings!$B$4-N(B12)>2*Settings!$B$19),AND(BI12="Approved - PO Pending",ISNUMBER(J12),Settings!$B$4-N(J12)>2*Settings!$B$20)),"Medium","Low"))) | BM12: =IF(BL12="","",IF(BL12="High",1,IF(BL12="Medium",2,3))*10000+ROW())
A13: PSIL-PR-2026-0008 | B13: 46196 | C13: Lasting & Assembly | D13: Lasting Manager | E13: PU Adhesive (Solvent Based) | F13: Chemicals & Adhesives | G13: 15 kg drum | H13: OPEX | I13: OPX-2026-108 | J13: 46200 | K13: Approved | L13: CFO | M13: Gazipur Chem Trade | N13: Local | O13: PSIL-PO-2026-0008 | P13: 46202 | Q13: 1100 | R13: kg | S13: 431 | T13: BDT | U13: =IF(AND(T13="",S13=""),"",IF(T13="",1,IFERROR(INDEX(Settings!$B$12:$B$16,MATCH(T13,Settings!$A$12:$A$16,0)),1))) -> 1 | V13: 407.49 | W13: =IF(OR(Q13="",S13=""),"",Q13*S13*U13) -> 474100 | X13: =IF(OR(W13="",N(Q13)=0),"",W13/Q13) -> 431 | Y13: =IF(OR(X13="",P13="",E13=""),"",IF(_xlfn.MAXIFS($P$6:$P$205,$E$6:$E$205,E13,$P$6:$P$205,"<"&P13,$X$6:$X$205,">0")=0,"",IFERROR(AVERAGEIFS($X$6:$X$205,$E$6:$E$205,E13,$P$6:$P$205,_xlfn.MAXIFS($P$6:$P$205,$E$6:$E$205,E13,$P$6:$P$205,"<"&P13,$X$6:$X$205,">0"),$X$6:$X$205,">0"),""))) | Z13: =IF(OR(Y13="",X13=""),"",X13/Y13-1) | AA13: =IF(OR(W13="",V13=""),"",W13-Q13*V13) -> 25861 | AB13: =IF(AA13="","",IF(N(V13)*N(Q13)=0,"",AA13/(Q13*V13))) -> 0.057694667 | AC13: 0.075 | AD13: =IF(W13="","",W13*(1+N(AC13))) -> 509657.5 | AE13: 100% Advance | AF13: 509657.5 | AI13: =IF(A13="","",N(AF13)+N(AG13)+N(AH13)) -> 509657.5 | AJ13: =IF(AD13="","",IF(N(AD13)=0,"",AI13/AD13)) -> 1 | AK13: =IF(AD13="","",IF(AD13-AI13<1,0,ROUND(AD13-AI13,2))) -> 0 | AL13: =IF(OR(O13="",AD13=""),"",MAX(0,ROUND(N(AI13)-(AD13-N(AW13)),0))) -> 16680 | AM13: =IF(A13="","",IF(O13="","No PO Yet",IF(AI13=0,"Not Paid",IF(N(AJ13)>=0.999,"Fully Paid",IF(N(AG13)+N(AH13)>0,"Partially Paid","Initial / Advance Paid"))))) -> Fully Paid | AN13: 46203 | AP13: =IF(AK13="","",IF(OR(N(AK13)=0,AO13=""),"",MAX(0,Settings!$B$4-AO13))) | AQ13: =IF(AK13="","",IF(N(AK13)<=0,"",IF(AO13="","No Due Date",IF(Settings!$B$4<=AO13,"Not Yet Due",IF(Settings!$B$4-AO13<=30,"1-30 Days",IF(Settings!$B$4-AO13<=60,"31-60 Days",IF(Settings!$B$4-AO13<=90,"61-90 Days","90+ Days"))))))) | AR13: 46219 | AS13: 46227 | AT13: 1064 | AU13: =IF(Q13="","",IF(N(Q13)=0,"",N(AT13)/Q13)) -> 0.96727273 | AV13: =IF(OR(A13="",O13="",Q13=""),"",MAX(0,Q13-N(AT13))) -> 36 | AW13: =IF(OR(AV13="",W13=""),"",IF(N(Q13)=0,0,AV13/Q13*AD13)) -> 16679.7 | AX13: =IF(A13="","",IF(O13="","No PO Yet",IF(Q13="","Order Qty Missing",IF(N(AT13)>=Q13,IF(N(AT13)>Q13,"All In-house (+"&TEXT(N(AT13)-Q13,"#,##0")&" "&R13&" excess)","All In-house"),IF(AY13<>"","Short Closed - "&TEXT(AV13,"#,##0")&" "&R13&" not received",IF(N(AT13)=0,"Not Started - "&TEXT(AV13,"#,##0")&" "&R13&" pending","Pending "&TEXT(AV13,"#,##0")&" "&R13&" ("&TEXT(AU13,"0%")&" received)")))))) -> Short Closed - 36 kg not received | AY13: 46229 | AZ13: =IF(OR(B13="",J13=""),"",J13-B13) -> 4 | BA13: =IF(OR(J13="",P13=""),"",P13-J13) -> 2 | BB13: =IF(OR(P13="",AY13=""),"",AY13-P13) -> 27 | BC13: =IF(OR(B13="",AY13=""),"",AY13-B13) -> 33 | BD13: =IF(OR(AR13="",O13=""),"",MAX(0,IF(AY13="",Settings!$B$4,AY13)-AR13)) -> 10 | BE13: =IF(OR(AY13="",AR13=""),"",IF(AND(AY13<=AR13,N(AU13)>=Settings!$B$6),"OTIF","Not OTIF")) -> Not OTIF | BF13: Rejected | BI13: =IF(A13="","",IF(K13="Rejected","Rejected",IF(K13<>"Approved","Awaiting Approval",IF(O13="","Approved - PO Pending",IF(AY13<>"",IF(N(AJ13)>=0.999,"Closed","In-house Closed - Payment Due"),IF(AS13<>"","Receiving In-house","PO Issued - Awaiting Delivery")))))) -> Closed | BJ13: =IF(A13="","",IF(IF(AND(A13<>"",OR(B13="",C13="",E13="",F13="",H13="")),"PR info missing; ","")&IF(AND(K13="Approved",OR(J13="",I13="")),"Approval ref/date missing; ","")&IF(AND(O13<>"",K13<>"Approved"),"PO without approval; ","")&IF(AND(O13<>"",OR(P13="",M13="",Q13="",S13="",T13="")),"PO details missing; ","")&IF(AND(O13<>"",AR13=""),"Committed date missing; ","")&IF(AND(ISNUMBER(J13),ISNUMBER(B13),N(J13)<N(B13)),"Approval dated before PR; ","")&IF(AND(ISNUMBER(P13),ISNUMBER(J13),N(P13)<N(J13)),"PO dated before approval; ","")&IF(AND(ISNUMBER(AY13),ISNUMBER(AS13),N(AY13)<N(AS13)),"Close before in-house start; ","")&IF(AND(AY13<>"",AS13=""),"In-house start date missing; ","")&IF(AND(AY13<>"",AT13=""),"Qty received missing; ","")&IF(AND(AY13<>"",BF13=""),"QC status missing; ","")&IF(N(AT13)>N(Q13)*1.05,"Received > ordered +5%; ","")&IF(AND(N(AI13)>0,AE13=""),"Payment terms missing; ","")&IF(N(AI13)>N(AD13)+1,"Overpaid vs PO; ","")&IF(AND(N(AK13)>0,AY13<>"",AO13=""),"Payment due date missing; ","")="","OK",IF(AND(A13<>"",OR(B13="",C13="",E13="",F13="",H13="")),"PR info missing; ","")&IF(AND(K13="Approved",OR(J13="",I13="")),"Approval ref/date missing; ","")&IF(AND(O13<>"",K13<>"Approved"),"PO without approval; ","")&IF(AND(O13<>"",OR(P13="",M13="",Q13="",S13="",T13="")),"PO details missing; ","")&IF(AND(O13<>"",AR13=""),"Committed date missing; ","")&IF(AND(ISNUMBER(J13),ISNUMBER(B13),N(J13)<N(B13)),"Approval dated before PR; ","")&IF(AND(ISNUMBER(P13),ISNUMBER(J13),N(P13)<N(J13)),"PO dated before approval; ","")&IF(AND(ISNUMBER(AY13),ISNUMBER(AS13),N(AY13)<N(AS13)),"Close before in-house start; ","")&IF(AND(AY13<>"",AS13=""),"In-house start date missing; ","")&IF(AND(AY13<>"",AT13=""),"Qty received missing; ","")&IF(AND(AY13<>"",BF13=""),"QC status missing; ","")&IF(N(AT13)>N(Q13)*1.05,"Received > ordered +5%; ","")&IF(AND(N(AI13)>0,AE13=""),"Payment terms missing; ","")&IF(N(AI13)>N(AD13)+1,"Overpaid vs PO; ","")&IF(AND(N(AK13)>0,AY13<>"",AO13=""),"Payment due date missing; ",""))) -> OK | BK13: =IF(A13="","",IF(N(AP13)>0,"Pay supplier: "&N(AP13)&" days overdue; ","")&IF(AND(O13<>"",AY13="",N(BD13)>0),"Expedite delivery: "&N(BD13)&" days late; ","")&IF(AND(BI13="Awaiting Approval",ISNUMBER(B13),Settings!$B$4-N(B13)>Settings!$B$19),"Get approval: PR waiting "&(Settings!$B$4-N(B13))&" days; ","")&IF(AND(BI13="Approved - PO Pending",ISNUMBER(J13),Settings!$B$4-N(J13)>Settings!$B$20),"Issue PO: approved "&(Settings!$B$4-N(J13))&" days ago; ","")&IF(AND(OR(BI13="Awaiting Approval",BI13="Approved - PO Pending"),N(AB13)>Settings!$B$7),"Negotiate price: "&TEXT(AB13,"0%")&" above budget; ","")&IF(LEFT(AX13,12)="Short Closed","Short closed: claim balance / credit note"&IF(N(AL13)>0," BDT "&TEXT(AL13,"#,##0"),"")&"; ","")&IF(BF13="Rejected","QC rejected: return / replace; ","")&IF(AND(O13<>"",AY13="",N(AL13)>0,N(BD13)>0),"Advance at risk: BDT "&TEXT(AL13,"#,##0")&" paid, goods late; ","")&IF(AND(BJ13<>"",BJ13<>"OK"),"Fix data entry (see Data Check); ","")) -> Short closed: claim balance / credit note BDT 16,680; QC rejected: return / replace; | BL13: =IF(BK13="","",IF(OR(N(AP13)>30,AND(AY13="",N(BD13)>15),BF13="Rejected",AND(LEFT(AX13,12)="Short Closed",N(AL13)>0),AND(O13<>"",AY13="",N(AL13)>0,N(BD13)>0)),"High",IF(OR(N(AP13)>0,AND(AY13="",N(BD13)>7),LEFT(AX13,12)="Short Closed",AND(BI13="Awaiting Approval",ISNUMBER(B13),Settings!$B$4-N(B13)>2*Settings!$B$19),AND(BI13="Approved - PO Pending",ISNUMBER(J13),Settings!$B$4-N(J13)>2*Settings!$B$20)),"Medium","Low"))) -> High | BM13: =IF(BL13="","",IF(BL13="High",1,IF(BL13="Medium",2,3))*10000+ROW()) -> 10013
A14: PSIL-PR-2026-0009 | B14: 46200 | C14: Lasting & Assembly | D14: Lasting Manager | E14: Primer & Halogenating Agent | F14: Chemicals & Adhesives | G14: Rubber sole primer | H14: OPEX | I14: OPX-2026-109 | J14: 46204 | K14: Approved | L14: CFO | M14: Gazipur Chem Trade | N14: Local | O14: PSIL-PO-2026-0009 | P14: 46206 | Q14: 700 | R14: kg | S14: 566 | T14: BDT | U14: =IF(AND(T14="",S14=""),"",IF(T14="",1,IFERROR(INDEX(Settings!$B$12:$B$16,MATCH(T14,Settings!$A$12:$A$16,0)),1))) -> 1 | V14: 525.7 | W14: =IF(OR(Q14="",S14=""),"",Q14*S14*U14) -> 396200 | X14: =IF(OR(W14="",N(Q14)=0),"",W14/Q14) -> 566 | Y14: =IF(OR(X14="",P14="",E14=""),"",IF(_xlfn.MAXIFS($P$6:$P$205,$E$6:$E$205,E14,$P$6:$P$205,"<"&P14,$X$6:$X$205,">0")=0,"",IFERROR(AVERAGEIFS($X$6:$X$205,$E$6:$E$205,E14,$P$6:$P$205,_xlfn.MAXIFS($P$6:$P$205,$E$6:$E$205,E14,$P$6:$P$205,"<"&P14,$X$6:$X$205,">0"),$X$6:$X$205,">0"),""))) | Z14: =IF(OR(Y14="",X14=""),"",X14/Y14-1) | AA14: =IF(OR(W14="",V14=""),"",W14-Q14*V14) -> 28210 | AB14: =IF(AA14="","",IF(N(V14)*N(Q14)=0,"",AA14/(Q14*V14))) -> 0.076659692 | AC14: 0.075 | AD14: =IF(W14="","",W14*(1+N(AC14))) -> 425915 | AE14: Credit 30 Days | AH14: 425915 | AI14: =IF(A14="","",N(AF14)+N(AG14)+N(AH14)) -> 425915 | AJ14: =IF(AD14="","",IF(N(AD14)=0,"",AI14/AD14)) -> 1 | AK14: =IF(AD14="","",IF(AD14-AI14<1,0,ROUND(AD14-AI14,2))) -> 0 | AL14: =IF(OR(O14="",AD14=""),"",MAX(0,ROUND(N(AI14)-(AD14-N(AW14)),0))) -> 0 | AM14: =IF(A14="","",IF(O14="","No PO Yet",IF(AI14=0,"Not Paid",IF(N(AJ14)>=0.999,"Fully Paid",IF(N(AG14)+N(AH14)>0,"Partially Paid","Initial / Advance Paid"))))) -> Fully Paid | AN14: 46250 | AP14: =IF(AK14="","",IF(OR(N(AK14)=0,AO14=""),"",MAX(0,Settings!$B$4-AO14))) | AQ14: =IF(AK14="","",IF(N(AK14)<=0,"",IF(AO14="","No Due Date",IF(Settings!$B$4<=AO14,"Not Yet Due",IF(Settings!$B$4-AO14<=30,"1-30 Days",IF(Settings!$B$4-AO14<=60,"31-60 Days",IF(Settings!$B$4-AO14<=90,"61-90 Days","90+ Days"))))))) | AR14: 46217 | AS14: 46213 | AT14: 700 | AU14: =IF(Q14="","",IF(N(Q14)=0,"",N(AT14)/Q14)) -> 1 | AV14: =IF(OR(A14="",O14="",Q14=""),"",MAX(0,Q14-N(AT14))) -> 0 | AW14: =IF(OR(AV14="",W14=""),"",IF(N(Q14)=0,0,AV14/Q14*AD14)) -> 0 | AX14: =IF(A14="","",IF(O14="","No PO Yet",IF(Q14="","Order Qty Missing",IF(N(AT14)>=Q14,IF(N(AT14)>Q14,"All In-house (+"&TEXT(N(AT14)-Q14,"#,##0")&" "&R14&" excess)","All In-house"),IF(AY14<>"","Short Closed - "&TEXT(AV14,"#,##0")&" "&R14&" not received",IF(N(AT14)=0,"Not Started - "&TEXT(AV14,"#,##0")&" "&R14&" pending","Pending "&TEXT(AV14,"#,##0")&" "&R14&" ("&TEXT(AU14,"0%")&" received)")))))) -> All In-house | AY14: 46214 | AZ14: =IF(OR(B14="",J14=""),"",J14-B14) -> 4 | BA14: =IF(OR(J14="",P14=""),"",P14-J14) -> 2 | BB14: =IF(OR(P14="",AY14=""),"",AY14-P14) -> 8 | BC14: =IF(OR(B14="",AY14=""),"",AY14-B14) -> 14 | BD14: =IF(OR(AR14="",O14=""),"",MAX(0,IF(AY14="",Settings!$B$4,AY14)-AR14)) -> 0 | BE14: =IF(OR(AY14="",AR14=""),"",IF(AND(AY14<=AR14,N(AU14)>=Settings!$B$6),"OTIF","Not OTIF")) -> OTIF | BF14: Approved | BG14: Photos\PSIL-PR-2026-0009.jpg | BI14: =IF(A14="","",IF(K14="Rejected","Rejected",IF(K14<>"Approved","Awaiting Approval",IF(O14="","Approved - PO Pending",IF(AY14<>"",IF(N(AJ14)>=0.999,"Closed","In-house Closed - Payment Due"),IF(AS14<>"","Receiving In-house","PO Issued - Awaiting Delivery")))))) -> Closed | BJ14: =IF(A14="","",IF(IF(AND(A14<>"",OR(B14="",C14="",E14="",F14="",H14="")),"PR info missing; ","")&IF(AND(K14="Approved",OR(J14="",I14="")),"Approval ref/date missing; ","")&IF(AND(O14<>"",K14<>"Approved"),"PO without approval; ","")&IF(AND(O14<>"",OR(P14="",M14="",Q14="",S14="",T14="")),"PO details missing; ","")&IF(AND(O14<>"",AR14=""),"Committed date missing; ","")&IF(AND(ISNUMBER(J14),ISNUMBER(B14),N(J14)<N(B14)),"Approval dated before PR; ","")&IF(AND(ISNUMBER(P14),ISNUMBER(J14),N(P14)<N(J14)),"PO dated before approval; ","")&IF(AND(ISNUMBER(AY14),ISNUMBER(AS14),N(AY14)<N(AS14)),"Close before in-house start; ","")&IF(AND(AY14<>"",AS14=""),"In-house start date missing; ","")&IF(AND(AY14<>"",AT14=""),"Qty received missing; ","")&IF(AND(AY14<>"",BF14=""),"QC status missing; ","")&IF(N(AT14)>N(Q14)*1.05,"Received > ordered +5%; ","")&IF(AND(N(AI14)>0,AE14=""),"Payment terms missing; ","")&IF(N(AI14)>N(AD14)+1,"Overpaid vs PO; ","")&IF(AND(N(AK14)>0,AY14<>"",AO14=""),"Payment due date missing; ","")="","OK",IF(AND(A14<>"",OR(B14="",C14="",E14="",F14="",H14="")),"PR info missing; ","")&IF(AND(K14="Approved",OR(J14="",I14="")),"Approval ref/date missing; ","")&IF(AND(O14<>"",K14<>"Approved"),"PO without approval; ","")&IF(AND(O14<>"",OR(P14="",M14="",Q14="",S14="",T14="")),"PO details missing; ","")&IF(AND(O14<>"",AR14=""),"Committed date missing; ","")&IF(AND(ISNUMBER(J14),ISNUMBER(B14),N(J14)<N(B14)),"Approval dated before PR; ","")&IF(AND(ISNUMBER(P14),ISNUMBER(J14),N(P14)<N(J14)),"PO dated before approval; ","")&IF(AND(ISNUMBER(AY14),ISNUMBER(AS14),N(AY14)<N(AS14)),"Close before in-house start; ","")&IF(AND(AY14<>"",AS14=""),"In-house start date missing; ","")&IF(AND(AY14<>"",AT14=""),"Qty received missing; ","")&IF(AND(AY14<>"",BF14=""),"QC status missing; ","")&IF(N(AT14)>N(Q14)*1.05,"Received > ordered +5%; ","")&IF(AND(N(AI14)>0,AE14=""),"Payment terms missing; ","")&IF(N(AI14)>N(AD14)+1,"Overpaid vs PO; ","")&IF(AND(N(AK14)>0,AY14<>"",AO14=""),"Payment due date missing; ",""))) -> OK | BK14: =IF(A14="","",IF(N(AP14)>0,"Pay supplier: "&N(AP14)&" days overdue; ","")&IF(AND(O14<>"",AY14="",N(BD14)>0),"Expedite delivery: "&N(BD14)&" days late; ","")&IF(AND(BI14="Awaiting Approval",ISNUMBER(B14),Settings!$B$4-N(B14)>Settings!$B$19),"Get approval: PR waiting "&(Settings!$B$4-N(B14))&" days; ","")&IF(AND(BI14="Approved - PO Pending",ISNUMBER(J14),Settings!$B$4-N(J14)>Settings!$B$20),"Issue PO: approved "&(Settings!$B$4-N(J14))&" days ago; ","")&IF(AND(OR(BI14="Awaiting Approval",BI14="Approved - PO Pending"),N(AB14)>Settings!$B$7),"Negotiate price: "&TEXT(AB14,"0%")&" above budget; ","")&IF(LEFT(AX14,12)="Short Closed","Short closed: claim balance / credit note"&IF(N(AL14)>0," BDT "&TEXT(AL14,"#,##0"),"")&"; ","")&IF(BF14="Rejected","QC rejected: return / replace; ","")&IF(AND(O14<>"",AY14="",N(AL14)>0,N(BD14)>0),"Advance at risk: BDT "&TEXT(AL14,"#,##0")&" paid, goods late; ","")&IF(AND(BJ14<>"",BJ14<>"OK"),"Fix data entry (see Data Check); ","")) | BL14: =IF(BK14="","",IF(OR(N(AP14)>30,AND(AY14="",N(BD14)>15),BF14="Rejected",AND(LEFT(AX14,12)="Short Closed",N(AL14)>0),AND(O14<>"",AY14="",N(AL14)>0,N(BD14)>0)),"High",IF(OR(N(AP14)>0,AND(AY14="",N(BD14)>7),LEFT(AX14,12)="Short Closed",AND(BI14="Awaiting Approval",ISNUMBER(B14),Settings!$B$4-N(B14)>2*Settings!$B$19),AND(BI14="Approved - PO Pending",ISNUMBER(J14),Settings!$B$4-N(J14)>2*Settings!$B$20)),"Medium","Low"))) | BM14: =IF(BL14="","",IF(BL14="High",1,IF(BL14="Medium",2,3))*10000+ROW())
A15: PSIL-PR-2026-0010 | B15: 46202 | C15: Stitching | D15: Stitching Manager | E15: Bonded Nylon Thread | F15: Trims & Accessories | G15: Tex 70, Black | H15: OPEX | I15: OPX-2026-110 | J15: 46205 | K15: Approved | L15: GM Operations | M15: Delta Thread & Trims | N15: Local | O15: PSIL-PO-2026-0010 | P15: 46207 | Q15: 1400 | R15: cone | S15: 292 | T15: BDT | U15: =IF(AND(T15="",S15=""),"",IF(T15="",1,IFERROR(INDEX(Settings!$B$12:$B$16,MATCH(T15,Settings!$A$12:$A$16,0)),1))) -> 1 | V15: 308.49 | W15: =IF(OR(Q15="",S15=""),"",Q15*S15*U15) -> 408800 | X15: =IF(OR(W15="",N(Q15)=0),"",W15/Q15) -> 292 | Y15: =IF(OR(X15="",P15="",E15=""),"",IF(_xlfn.MAXIFS($P$6:$P$205,$E$6:$E$205,E15,$P$6:$P$205,"<"&P15,$X$6:$X$205,">0")=0,"",IFERROR(AVERAGEIFS($X$6:$X$205,$E$6:$E$205,E15,$P$6:$P$205,_xlfn.MAXIFS($P$6:$P$205,$E$6:$E$205,E15,$P$6:$P$205,"<"&P15,$X$6:$X$205,">0"),$X$6:$X$205,">0"),""))) | Z15: =IF(OR(Y15="",X15=""),"",X15/Y15-1) | AA15: =IF(OR(W15="",V15=""),"",W15-Q15*V15) -> -23086 | AB15: =IF(AA15="","",IF(N(V15)*N(Q15)=0,"",AA15/(Q15*V15))) -> -0.053453921 | AC15: 0.05 | AD15: =IF(W15="","",W15*(1+N(AC15))) -> 429240 | AE15: 30% Advance / 70% after In-house | AF15: 128772 | AI15: =IF(A15="","",N(AF15)+N(AG15)+N(AH15)) -> 128772 | AJ15: =IF(AD15="","",IF(N(AD15)=0,"",AI15/AD15)) -> 0.3 | AK15: =IF(AD15="","",IF(AD15-AI15<1,0,ROUND(AD15-AI15,2))) -> 300468 | AL15: =IF(OR(O15="",AD15=""),"",MAX(0,ROUND(N(AI15)-(AD15-N(AW15)),0))) -> 0 | AM15: =IF(A15="","",IF(O15="","No PO Yet",IF(AI15=0,"Not Paid",IF(N(AJ15)>=0.999,"Fully Paid",IF(N(AG15)+N(AH15)>0,"Partially Paid","Initial / Advance Paid"))))) -> Initial / Advance Paid | AN15: 46209 | AO15: 46240 | AP15: =IF(AK15="","",IF(OR(N(AK15)=0,AO15=""),"",MAX(0,Settings!$B$4-AO15))) -> 70 | AQ15: =IF(AK15="","",IF(N(AK15)<=0,"",IF(AO15="","No Due Date",IF(Settings!$B$4<=AO15,"Not Yet Due",IF(Settings!$B$4-AO15<=30,"1-30 Days",IF(Settings!$B$4-AO15<=60,"31-60 Days",IF(Settings!$B$4-AO15<=90,"61-90 Days","90+ Days"))))))) -> 61-90 Days | AR15: 46228 | AS15: 46222 | AT15: 1351 | AU15: =IF(Q15="","",IF(N(Q15)=0,"",N(AT15)/Q15)) -> 0.965 | AV15: =IF(OR(A15="",O15="",Q15=""),"",MAX(0,Q15-N(AT15))) -> 49 | AW15: =IF(OR(AV15="",W15=""),"",IF(N(Q15)=0,0,AV15/Q15*AD15)) -> 15023.4 | AX15: =IF(A15="","",IF(O15="","No PO Yet",IF(Q15="","Order Qty Missing",IF(N(AT15)>=Q15,IF(N(AT15)>Q15,"All In-house (+"&TEXT(N(AT15)-Q15,"#,##0")&" "&R15&" excess)","All In-house"),IF(AY15<>"","Short Closed - "&TEXT(AV15,"#,##0")&" "&R15&" not received",IF(N(AT15)=0,"Not Started - "&TEXT(AV15,"#,##0")&" "&R15&" pending","Pending "&TEXT(AV15,"#,##0")&" "&R15&" ("&TEXT(AU15,"0%")&" received)")))))) -> Short Closed - 49 cone not received | AY15: 46225 | AZ15: =IF(OR(B15="",J15=""),"",J15-B15) -> 3 | BA15: =IF(OR(J15="",P15=""),"",P15-J15) -> 2 | BB15: =IF(OR(P15="",AY15=""),"",AY15-P15) -> 18 | BC15: =IF(OR(B15="",AY15=""),"",AY15-B15) -> 23 | BD15: =IF(OR(AR15="",O15=""),"",MAX(0,IF(AY15="",Settings!$B$4,AY15)-AR15)) -> 0 | BE15: =IF(OR(AY15="",AR15=""),"",IF(AND(AY15<=AR15,N(AU15)>=Settings!$B$6),"OTIF","Not OTIF")) -> Not OTIF | BF15: Approved | BG15: Photos\PSIL-PR-2026-0010.jpg | BI15: =IF(A15="","",IF(K15="Rejected","Rejected",IF(K15<>"Approved","Awaiting Approval",IF(O15="","Approved - PO Pending",IF(AY15<>"",IF(N(AJ15)>=0.999,"Closed","In-house Closed - Payment Due"),IF(AS15<>"","Receiving In-house","PO Issued - Awaiting Delivery")))))) -> In-house Closed - Payment Due | BJ15: =IF(A15="","",IF(IF(AND(A15<>"",OR(B15="",C15="",E15="",F15="",H15="")),"PR info missing; ","")&IF(AND(K15="Approved",OR(J15="",I15="")),"Approval ref/date missing; ","")&IF(AND(O15<>"",K15<>"Approved"),"PO without approval; ","")&IF(AND(O15<>"",OR(P15="",M15="",Q15="",S15="",T15="")),"PO details missing; ","")&IF(AND(O15<>"",AR15=""),"Committed date missing; ","")&IF(AND(ISNUMBER(J15),ISNUMBER(B15),N(J15)<N(B15)),"Approval dated before PR; ","")&IF(AND(ISNUMBER(P15),ISNUMBER(J15),N(P15)<N(J15)),"PO dated before approval; ","")&IF(AND(ISNUMBER(AY15),ISNUMBER(AS15),N(AY15)<N(AS15)),"Close before in-house start; ","")&IF(AND(AY15<>"",AS15=""),"In-house start date missing; ","")&IF(AND(AY15<>"",AT15=""),"Qty received missing; ","")&IF(AND(AY15<>"",BF15=""),"QC status missing; ","")&IF(N(AT15)>N(Q15)*1.05,"Received > ordered +5%; ","")&IF(AND(N(AI15)>0,AE15=""),"Payment terms missing; ","")&IF(N(AI15)>N(AD15)+1,"Overpaid vs PO; ","")&IF(AND(N(AK15)>0,AY15<>"",AO15=""),"Payment due date missing; ","")="","OK",IF(AND(A15<>"",OR(B15="",C15="",E15="",F15="",H15="")),"PR info missing; ","")&IF(AND(K15="Approved",OR(J15="",I15="")),"Approval ref/date missing; ","")&IF(AND(O15<>"",K15<>"Approved"),"PO without approval; ","")&IF(AND(O15<>"",OR(P15="",M15="",Q15="",S15="",T15="")),"PO details missing; ","")&IF(AND(O15<>"",AR15=""),"Committed date missing; ","")&IF(AND(ISNUMBER(J15),ISNUMBER(B15),N(J15)<N(B15)),"Approval dated before PR; ","")&IF(AND(ISNUMBER(P15),ISNUMBER(J15),N(P15)<N(J15)),"PO dated before approval; ","")&IF(AND(ISNUMBER(AY15),ISNUMBER(AS15),N(AY15)<N(AS15)),"Close before in-house start; ","")&IF(AND(AY15<>"",AS15=""),"In-house start date missing; ","")&IF(AND(AY15<>"",AT15=""),"Qty received missing; ","")&IF(AND(AY15<>"",BF15=""),"QC status missing; ","")&IF(N(AT15)>N(Q15)*1.05,"Received > ordered +5%; ","")&IF(AND(N(AI15)>0,AE15=""),"Payment terms missing; ","")&IF(N(AI15)>N(AD15)+1,"Overpaid vs PO; ","")&IF(AND(N(AK15)>0,AY15<>"",AO15=""),"Payment due date missing; ",""))) -> OK | BK15: =IF(A15="","",IF(N(AP15)>0,"Pay supplier: "&N(AP15)&" days overdue; ","")&IF(AND(O15<>"",AY15="",N(BD15)>0),"Expedite delivery: "&N(BD15)&" days late; ","")&IF(AND(BI15="Awaiting Approval",ISNUMBER(B15),Settings!$B$4-N(B15)>Settings!$B$19),"Get approval: PR waiting "&(Settings!$B$4-N(B15))&" days; ","")&IF(AND(BI15="Approved - PO Pending",ISNUMBER(J15),Settings!$B$4-N(J15)>Settings!$B$20),"Issue PO: approved "&(Settings!$B$4-N(J15))&" days ago; ","")&IF(AND(OR(BI15="Awaiting Approval",BI15="Approved - PO Pending"),N(AB15)>Settings!$B$7),"Negotiate price: "&TEXT(AB15,"0%")&" above budget; ","")&IF(LEFT(AX15,12)="Short Closed","Short closed: claim balance / credit note"&IF(N(AL15)>0," BDT "&TEXT(AL15,"#,##0"),"")&"; ","")&IF(BF15="Rejected","QC rejected: return / replace; ","")&IF(AND(O15<>"",AY15="",N(AL15)>0,N(BD15)>0),"Advance at risk: BDT "&TEXT(AL15,"#,##0")&" paid, goods late; ","")&IF(AND(BJ15<>"",BJ15<>"OK"),"Fix data entry (see Data Check); ","")) -> Pay supplier: 70 days overdue; Short closed: claim balance / credit note; | BL15: =IF(BK15="","",IF(OR(N(AP15)>30,AND(AY15="",N(BD15)>15),BF15="Rejected",AND(LEFT(AX15,12)="Short Closed",N(AL15)>0),AND(O15<>"",AY15="",N(AL15)>0,N(BD15)>0)),"High",IF(OR(N(AP15)>0,AND(AY15="",N(BD15)>7),LEFT(AX15,12)="Short Closed",AND(BI15="Awaiting Approval",ISNUMBER(B15),Settings!$B$4-N(B15)>2*Settings!$B$19),AND(BI15="Approved - PO Pending",ISNUMBER(J15),Settings!$B$4-N(J15)>2*Settings!$B$20)),"Medium","Low"))) -> High | BM15: =IF(BL15="","",IF(BL15="High",1,IF(BL15="Medium",2,3))*10000+ROW()) -> 10015
A16: PSIL-PR-2026-0011 | B16: 46205 | C16: Stitching | D16: Stitching Manager | E16: Metal Eyelets & Hooks | F16: Trims & Accessories | G16: Antique brass, 5 mm | H16: OPEX | I16: OPX-2026-111 | J16: 46209 | K16: Approved | L16: CFO | M16: Delta Thread & Trims | N16: Local | O16: PSIL-PO-2026-0011 | P16: 46211 | Q16: 900 | R16: gross | S16: 230 | T16: BDT | U16: =IF(AND(T16="",S16=""),"",IF(T16="",1,IFERROR(INDEX(Settings!$B$12:$B$16,MATCH(T16,Settings!$A$12:$A$16,0)),1))) -> 1 | V16: 229.75 | W16: =IF(OR(Q16="",S16=""),"",Q16*S16*U16) -> 207000 | X16: =IF(OR(W16="",N(Q16)=0),"",W16/Q16) -> 230 | Y16: =IF(OR(X16="",P16="",E16=""),"",IF(_xlfn.MAXIFS($P$6:$P$205,$E$6:$E$205,E16,$P$6:$P$205,"<"&P16,$X$6:$X$205,">0")=0,"",IFERROR(AVERAGEIFS($X$6:$X$205,$E$6:$E$205,E16,$P$6:$P$205,_xlfn.MAXIFS($P$6:$P$205,$E$6:$E$205,E16,$P$6:$P$205,"<"&P16,$X$6:$X$205,">0"),$X$6:$X$205,">0"),""))) | Z16: =IF(OR(Y16="",X16=""),"",X16/Y16-1) | AA16: =IF(OR(W16="",V16=""),"",W16-Q16*V16) -> 225 | AB16: =IF(AA16="","",IF(N(V16)*N(Q16)=0,"",AA16/(Q16*V16))) -> 0.0010881393 | AC16: 0.05 | AD16: =IF(W16="","",W16*(1+N(AC16))) -> 217350 | AE16: Credit 30 Days | AG16: 108675 | AI16: =IF(A16="","",N(AF16)+N(AG16)+N(AH16)) -> 108675 | AJ16: =IF(AD16="","",IF(N(AD16)=0,"",AI16/AD16)) -> 0.5 | AK16: =IF(AD16="","",IF(AD16-AI16<1,0,ROUND(AD16-AI16,2))) -> 108675 | AL16: =IF(OR(O16="",AD16=""),"",MAX(0,ROUND(N(AI16)-(AD16-N(AW16)),0))) -> 0 | AM16: =IF(A16="","",IF(O16="","No PO Yet",IF(AI16=0,"Not Paid",IF(N(AJ16)>=0.999,"Fully Paid",IF(N(AG16)+N(AH16)>0,"Partially Paid","Initial / Advance Paid"))))) -> Partially Paid | AN16: 46256 | AO16: 46256 | AP16: =IF(AK16="","",IF(OR(N(AK16)=0,AO16=""),"",MAX(0,Settings!$B$4-AO16))) -> 54 | AQ16: =IF(AK16="","",IF(N(AK16)<=0,"",IF(AO16="","No Due Date",IF(Settings!$B$4<=AO16,"Not Yet Due",IF(Settings!$B$4-AO16<=30,"1-30 Days",IF(Settings!$B$4-AO16<=60,"31-60 Days",IF(Settings!$B$4-AO16<=90,"61-90 Days","90+ Days"))))))) -> 31-60 Days | AR16: 46222 | AS16: 46225 | AT16: 900 | AU16: =IF(Q16="","",IF(N(Q16)=0,"",N(AT16)/Q16)) -> 1 | AV16: =IF(OR(A16="",O16="",Q16=""),"",MAX(0,Q16-N(AT16))) -> 0 | AW16: =IF(OR(AV16="",W16=""),"",IF(N(Q16)=0,0,AV16/Q16*AD16)) -> 0 | AX16: =IF(A16="","",IF(O16="","No PO Yet",IF(Q16="","Order Qty Missing",IF(N(AT16)>=Q16,IF(N(AT16)>Q16,"All In-house (+"&TEXT(N(AT16)-Q16,"#,##0")&" "&R16&" excess)","All In-house"),IF(AY16<>"","Short Closed - "&TEXT(AV16,"#,##0")&" "&R16&" not received",IF(N(AT16)=0,"Not Started - "&TEXT(AV16,"#,##0")&" "&R16&" pending","Pending "&TEXT(AV16,"#,##0")&" "&R16&" ("&TEXT(AU16,"0%")&" received)")))))) -> All In-house | AY16: 46226 | AZ16: =IF(OR(B16="",J16=""),"",J16-B16) -> 4 | BA16: =IF(OR(J16="",P16=""),"",P16-J16) -> 2 | BB16: =IF(OR(P16="",AY16=""),"",AY16-P16) -> 15 | BC16: =IF(OR(B16="",AY16=""),"",AY16-B16) -> 21 | BD16: =IF(OR(AR16="",O16=""),"",MAX(0,IF(AY16="",Settings!$B$4,AY16)-AR16)) -> 4 | BE16: =IF(OR(AY16="",AR16=""),"",IF(AND(AY16<=AR16,N(AU16)>=Settings!$B$6),"OTIF","Not OTIF")) -> Not OTIF | BF16: Approved | BG16: Photos\PSIL-PR-2026-0011.jpg | BI16: =IF(A16="","",IF(K16="Rejected","Rejected",IF(K16<>"Approved","Awaiting Approval",IF(O16="","Approved - PO Pending",IF(AY16<>"",IF(N(AJ16)>=0.999,"Closed","In-house Closed - Payment Due"),IF(AS16<>"","Receiving In-house","PO Issued - Awaiting Delivery")))))) -> In-house Closed - Payment Due | BJ16: =IF(A16="","",IF(IF(AND(A16<>"",OR(B16="",C16="",E16="",F16="",H16="")),"PR info missing; ","")&IF(AND(K16="Approved",OR(J16="",I16="")),"Approval ref/date missing; ","")&IF(AND(O16<>"",K16<>"Approved"),"PO without approval; ","")&IF(AND(O16<>"",OR(P16="",M16="",Q16="",S16="",T16="")),"PO details missing; ","")&IF(AND(O16<>"",AR16=""),"Committed date missing; ","")&IF(AND(ISNUMBER(J16),ISNUMBER(B16),N(J16)<N(B16)),"Approval dated before PR; ","")&IF(AND(ISNUMBER(P16),ISNUMBER(J16),N(P16)<N(J16)),"PO dated before approval; ","")&IF(AND(ISNUMBER(AY16),ISNUMBER(AS16),N(AY16)<N(AS16)),"Close before in-house start; ","")&IF(AND(AY16<>"",AS16=""),"In-house start date missing; ","")&IF(AND(AY16<>"",AT16=""),"Qty received missing; ","")&IF(AND(AY16<>"",BF16=""),"QC status missing; ","")&IF(N(AT16)>N(Q16)*1.05,"Received > ordered +5%; ","")&IF(AND(N(AI16)>0,AE16=""),"Payment terms missing; ","")&IF(N(AI16)>N(AD16)+1,"Overpaid vs PO; ","")&IF(AND(N(AK16)>0,AY16<>"",AO16=""),"Payment due date missing; ","")="","OK",IF(AND(A16<>"",OR(B16="",C16="",E16="",F16="",H16="")),"PR info missing; ","")&IF(AND(K16="Approved",OR(J16="",I16="")),"Approval ref/date missing; ","")&IF(AND(O16<>"",K16<>"Approved"),"PO without approval; ","")&IF(AND(O16<>"",OR(P16="",M16="",Q16="",S16="",T16="")),"PO details missing; ","")&IF(AND(O16<>"",AR16=""),"Committed date missing; ","")&IF(AND(ISNUMBER(J16),ISNUMBER(B16),N(J16)<N(B16)),"Approval dated before PR; ","")&IF(AND(ISNUMBER(P16),ISNUMBER(J16),N(P16)<N(J16)),"PO dated before approval; ","")&IF(AND(ISNUMBER(AY16),ISNUMBER(AS16),N(AY16)<N(AS16)),"Close before in-house start; ","")&IF(AND(AY16<>"",AS16=""),"In-house start date missing; ","")&IF(AND(AY16<>"",AT16=""),"Qty received missing; ","")&IF(AND(AY16<>"",BF16=""),"QC status missing; ","")&IF(N(AT16)>N(Q16)*1.05,"Received > ordered +5%; ","")&IF(AND(N(AI16)>0,AE16=""),"Payment terms missing; ","")&IF(N(AI16)>N(AD16)+1,"Overpaid vs PO; ","")&IF(AND(N(AK16)>0,AY16<>"",AO16=""),"Payment due date missing; ",""))) -> OK | BK16: =IF(A16="","",IF(N(AP16)>0,"Pay supplier: "&N(AP16)&" days overdue; ","")&IF(AND(O16<>"",AY16="",N(BD16)>0),"Expedite delivery: "&N(BD16)&" days late; ","")&IF(AND(BI16="Awaiting Approval",ISNUMBER(B16),Settings!$B$4-N(B16)>Settings!$B$19),"Get approval: PR waiting "&(Settings!$B$4-N(B16))&" days; ","")&IF(AND(BI16="Approved - PO Pending",ISNUMBER(J16),Settings!$B$4-N(J16)>Settings!$B$20),"Issue PO: approved "&(Settings!$B$4-N(J16))&" days ago; ","")&IF(AND(OR(BI16="Awaiting Approval",BI16="Approved - PO Pending"),N(AB16)>Settings!$B$7),"Negotiate price: "&TEXT(AB16,"0%")&" above budget; ","")&IF(LEFT(AX16,12)="Short Closed","Short closed: claim balance / credit note"&IF(N(AL16)>0," BDT "&TEXT(AL16,"#,##0"),"")&"; ","")&IF(BF16="Rejected","QC rejected: return / replace; ","")&IF(AND(O16<>"",AY16="",N(AL16)>0,N(BD16)>0),"Advance at risk: BDT "&TEXT(AL16,"#,##0")&" paid, goods late; ","")&IF(AND(BJ16<>"",BJ16<>"OK"),"Fix data entry (see Data Check); ","")) -> Pay supplier: 54 days overdue; | BL16: =IF(BK16="","",IF(OR(N(AP16)>30,AND(AY16="",N(BD16)>15),BF16="Rejected",AND(LEFT(AX16,12)="Short Closed",N(AL16)>0),AND(O16<>"",AY16="",N(AL16)>0,N(BD16)>0)),"High",IF(OR(N(AP16)>0,AND(AY16="",N(BD16)>7),LEFT(AX16,12)="Short Closed",AND(BI16="Awaiting Approval",ISNUMBER(B16),Settings!$B$4-N(B16)>2*Settings!$B$19),AND(BI16="Approved - PO Pending",ISNUMBER(J16),Settings!$B$4-N(J16)>2*Settings!$B$20)),"Medium","Low"))) -> High | BM16: =IF(BL16="","",IF(BL16="High",1,IF(BL16="Medium",2,3))*10000+ROW()) -> 10016
A17: PSIL-PR-2026-0012 | B17: 46209 | C17: Stitching | D17: Stitching Manager | E17: Waxed Cotton Laces | F17: Trims & Accessories | G17: 120 cm, Brown | H17: OPEX | I17: OPX-2026-112 | J17: 46210 | K17: Approved | L17: CFO | M17: Delta Thread & Trims | N17: Local | O17: PSIL-PO-2026-0012 | P17: 46215 | Q17: 11700 | R17: pair | S17: 15.15 | T17: BDT | U17: =IF(AND(T17="",S17=""),"",IF(T17="",1,IFERROR(INDEX(Settings!$B$12:$B$16,MATCH(T17,Settings!$A$12:$A$16,0)),1))) -> 1 | V17: 14.1 | W17: =IF(OR(Q17="",S17=""),"",Q17*S17*U17) -> 177255 | X17: =IF(OR(W17="",N(Q17)=0),"",W17/Q17) -> 15.15 | Y17: =IF(OR(X17="",P17="",E17=""),"",IF(_xlfn.MAXIFS($P$6:$P$205,$E$6:$E$205,E17,$P$6:$P$205,"<"&P17,$X$6:$X$205,">0")=0,"",IFERROR(AVERAGEIFS($X$6:$X$205,$E$6:$E$205,E17,$P$6:$P$205,_xlfn.MAXIFS($P$6:$P$205,$E$6:$E$205,E17,$P$6:$P$205,"<"&P17,$X$6:$X$205,">0"),$X$6:$X$205,">0"),""))) | Z17: =IF(OR(Y17="",X17=""),"",X17/Y17-1) | AA17: =IF(OR(W17="",V17=""),"",W17-Q17*V17) -> 12285 | AB17: =IF(AA17="","",IF(N(V17)*N(Q17)=0,"",AA17/(Q17*V17))) -> 0.074468085 | AC17: 0.05 | AD17: =IF(W17="","",W17*(1+N(AC17))) -> 186117.75 | AE17: Credit 30 Days | AH17: 186117.75 | AI17: =IF(A17="","",N(AF17)+N(AG17)+N(AH17)) -> 186117.75 | AJ17: =IF(AD17="","",IF(N(AD17)=0,"",AI17/AD17)) -> 1 | AK17: =IF(AD17="","",IF(AD17-AI17<1,0,ROUND(AD17-AI17,2))) -> 0 | AL17: =IF(OR(O17="",AD17=""),"",MAX(0,ROUND(N(AI17)-(AD17-N(AW17)),0))) -> 0 | AM17: =IF(A17="","",IF(O17="","No PO Yet",IF(AI17=0,"Not Paid",IF(N(AJ17)>=0.999,"Fully Paid",IF(N(AG17)+N(AH17)>0,"Partially Paid","Initial / Advance Paid"))))) -> Fully Paid | AN17: 46261 | AP17: =IF(AK17="","",IF(OR(N(AK17)=0,AO17=""),"",MAX(0,Settings!$B$4-AO17))) | AQ17: =IF(AK17="","",IF(N(AK17)<=0,"",IF(AO17="","No Due Date",IF(Settings!$B$4<=AO17,"Not Yet Due",IF(Settings!$B$4-AO17<=30,"1-30 Days",IF(Settings!$B$4-AO17<=60,"31-60 Days",IF(Settings!$B$4-AO17<=90,"61-90 Days","90+ Days"))))))) | AR17: 46231 | AS17: 46229 | AT17: 11700 | AU17: =IF(Q17="","",IF(N(Q17)=0,"",N(AT17)/Q17)) -> 1 | AV17: =IF(OR(A17="",O17="",Q17=""),"",MAX(0,Q17-N(AT17))) -> 0 | AW17: =IF(OR(AV17="",W17=""),"",IF(N(Q17)=0,0,AV17/Q17*AD17)) -> 0 | AX17: =IF(A17="","",IF(O17="","No PO Yet",IF(Q17="","Order Qty Missing",IF(N(AT17)>=Q17,IF(N(AT17)>Q17,"All In-house (+"&TEXT(N(AT17)-Q17,"#,##0")&" "&R17&" excess)","All In-house"),IF(AY17<>"","Short Closed - "&TEXT(AV17,"#,##0")&" "&R17&" not received",IF(N(AT17)=0,"Not Started - "&TEXT(AV17,"#,##0")&" "&R17&" pending","Pending "&TEXT(AV17,"#,##0")&" "&R17&" ("&TEXT(AU17,"0%")&" received)")))))) -> All In-house | AY17: 46231 | AZ17: =IF(OR(B17="",J17=""),"",J17-B17) -> 1 | BA17: =IF(OR(J17="",P17=""),"",P17-J17) -> 5 | BB17: =IF(OR(P17="",AY17=""),"",AY17-P17) -> 16 | BC17: =IF(OR(B17="",AY17=""),"",AY17-B17) -> 22 | BD17: =IF(OR(AR17="",O17=""),"",MAX(0,IF(AY17="",Settings!$B$4,AY17)-AR17)) -> 0 | BE17: =IF(OR(AY17="",AR17=""),"",IF(AND(AY17<=AR17,N(AU17)>=Settings!$B$6),"OTIF","Not OTIF")) -> OTIF | BF17: Rejected | BI17: =IF(A17="","",IF(K17="Rejected","Rejected",IF(K17<>"Approved","Awaiting Approval",IF(O17="","Approved - PO Pending",IF(AY17<>"",IF(N(AJ17)>=0.999,"Closed","In-house Closed - Payment Due"),IF(AS17<>"","Receiving In-house","PO Issued - Awaiting Delivery")))))) -> Closed | BJ17: =IF(A17="","",IF(IF(AND(A17<>"",OR(B17="",C17="",E17="",F17="",H17="")),"PR info missing; ","")&IF(AND(K17="Approved",OR(J17="",I17="")),"Approval ref/date missing; ","")&IF(AND(O17<>"",K17<>"Approved"),"PO without approval; ","")&IF(AND(O17<>"",OR(P17="",M17="",Q17="",S17="",T17="")),"PO details missing; ","")&IF(AND(O17<>"",AR17=""),"Committed date missing; ","")&IF(AND(ISNUMBER(J17),ISNUMBER(B17),N(J17)<N(B17)),"Approval dated before PR; ","")&IF(AND(ISNUMBER(P17),ISNUMBER(J17),N(P17)<N(J17)),"PO dated before approval; ","")&IF(AND(ISNUMBER(AY17),ISNUMBER(AS17),N(AY17)<N(AS17)),"Close before in-house start; ","")&IF(AND(AY17<>"",AS17=""),"In-house start date missing; ","")&IF(AND(AY17<>"",AT17=""),"Qty received missing; ","")&IF(AND(AY17<>"",BF17=""),"QC status missing; ","")&IF(N(AT17)>N(Q17)*1.05,"Received > ordered +5%; ","")&IF(AND(N(AI17)>0,AE17=""),"Payment terms missing; ","")&IF(N(AI17)>N(AD17)+1,"Overpaid vs PO; ","")&IF(AND(N(AK17)>0,AY17<>"",AO17=""),"Payment due date missing; ","")="","OK",IF(AND(A17<>"",OR(B17="",C17="",E17="",F17="",H17="")),"PR info missing; ","")&IF(AND(K17="Approved",OR(J17="",I17="")),"Approval ref/date missing; ","")&IF(AND(O17<>"",K17<>"Approved"),"PO without approval; ","")&IF(AND(O17<>"",OR(P17="",M17="",Q17="",S17="",T17="")),"PO details missing; ","")&IF(AND(O17<>"",AR17=""),"Committed date missing; ","")&IF(AND(ISNUMBER(J17),ISNUMBER(B17),N(J17)<N(B17)),"Approval dated before PR; ","")&IF(AND(ISNUMBER(P17),ISNUMBER(J17),N(P17)<N(J17)),"PO dated before approval; ","")&IF(AND(ISNUMBER(AY17),ISNUMBER(AS17),N(AY17)<N(AS17)),"Close before in-house start; ","")&IF(AND(AY17<>"",AS17=""),"In-house start date missing; ","")&IF(AND(AY17<>"",AT17=""),"Qty received missing; ","")&IF(AND(AY17<>"",BF17=""),"QC status missing; ","")&IF(N(AT17)>N(Q17)*1.05,"Received > ordered +5%; ","")&IF(AND(N(AI17)>0,AE17=""),"Payment terms missing; ","")&IF(N(AI17)>N(AD17)+1,"Overpaid vs PO; ","")&IF(AND(N(AK17)>0,AY17<>"",AO17=""),"Payment due date missing; ",""))) -> OK | BK17: =IF(A17="","",IF(N(AP17)>0,"Pay supplier: "&N(AP17)&" days overdue; ","")&IF(AND(O17<>"",AY17="",N(BD17)>0),"Expedite delivery: "&N(BD17)&" days late; ","")&IF(AND(BI17="Awaiting Approval",ISNUMBER(B17),Settings!$B$4-N(B17)>Settings!$B$19),"Get approval: PR waiting "&(Settings!$B$4-N(B17))&" days; ","")&IF(AND(BI17="Approved - PO Pending",ISNUMBER(J17),Settings!$B$4-N(J17)>Settings!$B$20),"Issue PO: approved "&(Settings!$B$4-N(J17))&" days ago; ","")&IF(AND(OR(BI17="Awaiting Approval",BI17="Approved - PO Pending"),N(AB17)>Settings!$B$7),"Negotiate price: "&TEXT(AB17,"0%")&" above budget; ","")&IF(LEFT(AX17,12)="Short Closed","Short closed: claim balance / credit note"&IF(N(AL17)>0," BDT "&TEXT(AL17,"#,##0"),"")&"; ","")&IF(BF17="Rejected","QC rejected: return / replace; ","")&IF(AND(O17<>"",AY17="",N(AL17)>0,N(BD17)>0),"Advance at risk: BDT "&TEXT(AL17,"#,##0")&" paid, goods late; ","")&IF(AND(BJ17<>"",BJ17<>"OK"),"Fix data entry (see Data Check); ","")) -> QC rejected: return / replace; | BL17: =IF(BK17="","",IF(OR(N(AP17)>30,AND(AY17="",N(BD17)>15),BF17="Rejected",AND(LEFT(AX17,12)="Short Closed",N(AL17)>0),AND(O17<>"",AY17="",N(AL17)>0,N(BD17)>0)),"High",IF(OR(N(AP17)>0,AND(AY17="",N(BD17)>7),LEFT(AX17,12)="Short Closed",AND(BI17="Awaiting Approval",ISNUMBER(B17),Settings!$B$4-N(B17)>2*Settings!$B$19),AND(BI17="Approved - PO Pending",ISNUMBER(J17),Settings!$B$4-N(J17)>2*Settings!$B$20)),"Medium","Low"))) -> High | BM17: =IF(BL17="","",IF(BL17="High",1,IF(BL17="Medium",2,3))*10000+ROW()) -> 10017
A18: PSIL-PR-2026-0013 | B18: 46211 | C18: Cutting | D18: Cutting Manager | E18: Cellulose Insole Board | F18: Synthetic & Textile | G18: 2.0 mm, 1x1.5 m | H18: OPEX | I18: OPX-2026-113 | J18: 46214 | K18: Approved | L18: GM Operations | M18: Narayanganj Board Mills | N18: Local | O18: PSIL-PO-2026-0013 | P18: 46218 | Q18: 2000 | R18: sheet | S18: 336 | T18: BDT | U18: =IF(AND(T18="",S18=""),"",IF(T18="",1,IFERROR(INDEX(Settings!$B$12:$B$16,MATCH(T18,Settings!$A$12:$A$16,0)),1))) -> 1 | V18: 332.74 | W18: =IF(OR(Q18="",S18=""),"",Q18*S18*U18) -> 672000 | X18: =IF(OR(W18="",N(Q18)=0),"",W18/Q18) -> 336 | Y18: =IF(OR(X18="",P18="",E18=""),"",IF(_xlfn.MAXIFS($P$6:$P$205,$E$6:$E$205,E18,$P$6:$P$205,"<"&P18,$X$6:$X$205,">0")=0,"",IFERROR(AVERAGEIFS($X$6:$X$205,$E$6:$E$205,E18,$P$6:$P$205,_xlfn.MAXIFS($P$6:$P$205,$E$6:$E$205,E18,$P$6:$P$205,"<"&P18,$X$6:$X$205,">0"),$X$6:$X$205,">0"),""))) | Z18: =IF(OR(Y18="",X18=""),"",X18/Y18-1) | AA18: =IF(OR(W18="",V18=""),"",W18-Q18*V18) -> 6520 | AB18: =IF(AA18="","",IF(N(V18)*N(Q18)=0,"",AA18/(Q18*V18))) -> 0.0097974394 | AC18: 0.05 | AD18: =IF(W18="","",W18*(1+N(AC18))) -> 705600 | AE18: Credit 30 Days | AG18: 352800 | AI18: =IF(A18="","",N(AF18)+N(AG18)+N(AH18)) -> 352800 | AJ18: =IF(AD18="","",IF(N(AD18)=0,"",AI18/AD18)) -> 0.5 | AK18: =IF(AD18="","",IF(AD18-AI18<1,0,ROUND(AD18-AI18,2))) -> 352800 | AL18: =IF(OR(O18="",AD18=""),"",MAX(0,ROUND(N(AI18)-(AD18-N(AW18)),0))) -> 0 | AM18: =IF(A18="","",IF(O18="","No PO Yet",IF(AI18=0,"Not Paid",IF(N(AJ18)>=0.999,"Fully Paid",IF(N(AG18)+N(AH18)>0,"Partially Paid","Initial / Advance Paid"))))) -> Partially Paid | AN18: 46279 | AO18: 46279 | AP18: =IF(AK18="","",IF(OR(N(AK18)=0,AO18=""),"",MAX(0,Settings!$B$4-AO18))) -> 31 | AQ18: =IF(AK18="","",IF(N(AK18)<=0,"",IF(AO18="","No Due Date",IF(Settings!$B$4<=AO18,"Not Yet Due",IF(Settings!$B$4-AO18<=30,"1-30 Days",IF(Settings!$B$4-AO18<=60,"31-60 Days",IF(Settings!$B$4-AO18<=90,"61-90 Days","90+ Days"))))))) -> 31-60 Days | AR18: 46241 | AS18: 46249 | AT18: 2000 | AU18: =IF(Q18="","",IF(N(Q18)=0,"",N(AT18)/Q18)) -> 1 | AV18: =IF(OR(A18="",O18="",Q18=""),"",MAX(0,Q18-N(AT18))) -> 0 | AW18: =IF(OR(AV18="",W18=""),"",IF(N(Q18)=0,0,AV18/Q18*AD18)) -> 0 | AX18: =IF(A18="","",IF(O18="","No PO Yet",IF(Q18="","Order Qty Missing",IF(N(AT18)>=Q18,IF(N(AT18)>Q18,"All In-house (+"&TEXT(N(AT18)-Q18,"#,##0")&" "&R18&" excess)","All In-house"),IF(AY18<>"","Short Closed - "&TEXT(AV18,"#,##0")&" "&R18&" not received",IF(N(AT18)=0,"Not Started - "&TEXT(AV18,"#,##0")&" "&R18&" pending","Pending "&TEXT(AV18,"#,##0")&" "&R18&" ("&TEXT(AU18,"0%")&" received)")))))) -> All In-house | AY18: 46249 | AZ18: =IF(OR(B18="",J18=""),"",J18-B18) -> 3 | BA18: =IF(OR(J18="",P18=""),"",P18-J18) -> 4 | BB18: =IF(OR(P18="",AY18=""),"",AY18-P18) -> 31 | BC18: =IF(OR(B18="",AY18=""),"",AY18-B18) -> 38 | BD18: =IF(OR(AR18="",O18=""),"",MAX(0,IF(AY18="",Settings!$B$4,AY18)-AR18)) -> 8 | BE18: =IF(OR(AY18="",AR18=""),"",IF(AND(AY18<=AR18,N(AU18)>=Settings!$B$6),"OTIF","Not OTIF")) -> Not OTIF | BF18: Approved | BG18: Photos\PSIL-PR-2026-0013.jpg | BI18: =IF(A18="","",IF(K18="Rejected","Rejected",IF(K18<>"Approved","Awaiting Approval",IF(O18="","Approved - PO Pending",IF(AY18<>"",IF(N(AJ18)>=0.999,"Closed","In-house Closed - Payment Due"),IF(AS18<>"","Receiving In-house","PO Issued - Awaiting Delivery")))))) -> In-house Closed - Payment Due | BJ18: =IF(A18="","",IF(IF(AND(A18<>"",OR(B18="",C18="",E18="",F18="",H18="")),"PR info missing; ","")&IF(AND(K18="Approved",OR(J18="",I18="")),"Approval ref/date missing; ","")&IF(AND(O18<>"",K18<>"Approved"),"PO without approval; ","")&IF(AND(O18<>"",OR(P18="",M18="",Q18="",S18="",T18="")),"PO details missing; ","")&IF(AND(O18<>"",AR18=""),"Committed date missing; ","")&IF(AND(ISNUMBER(J18),ISNUMBER(B18),N(J18)<N(B18)),"Approval dated before PR; ","")&IF(AND(ISNUMBER(P18),ISNUMBER(J18),N(P18)<N(J18)),"PO dated before approval; ","")&IF(AND(ISNUMBER(AY18),ISNUMBER(AS18),N(AY18)<N(AS18)),"Close before in-house start; ","")&IF(AND(AY18<>"",AS18=""),"In-house start date missing; ","")&IF(AND(AY18<>"",AT18=""),"Qty received missing; ","")&IF(AND(AY18<>"",BF18=""),"QC status missing; ","")&IF(N(AT18)>N(Q18)*1.05,"Received > ordered +5%; ","")&IF(AND(N(AI18)>0,AE18=""),"Payment terms missing; ","")&IF(N(AI18)>N(AD18)+1,"Overpaid vs PO; ","")&IF(AND(N(AK18)>0,AY18<>"",AO18=""),"Payment due date missing; ","")="","OK",IF(AND(A18<>"",OR(B18="",C18="",E18="",F18="",H18="")),"PR info missing; ","")&IF(AND(K18="Approved",OR(J18="",I18="")),"Approval ref/date missing; ","")&IF(AND(O18<>"",K18<>"Approved"),"PO without approval; ","")&IF(AND(O18<>"",OR(P18="",M18="",Q18="",S18="",T18="")),"PO details missing; ","")&IF(AND(O18<>"",AR18=""),"Committed date missing; ","")&IF(AND(ISNUMBER(J18),ISNUMBER(B18),N(J18)<N(B18)),"Approval dated before PR; ","")&IF(AND(ISNUMBER(P18),ISNUMBER(J18),N(P18)<N(J18)),"PO dated before approval; ","")&IF(AND(ISNUMBER(AY18),ISNUMBER(AS18),N(AY18)<N(AS18)),"Close before in-house start; ","")&IF(AND(AY18<>"",AS18=""),"In-house start date missing; ","")&IF(AND(AY18<>"",AT18=""),"Qty received missing; ","")&IF(AND(AY18<>"",BF18=""),"QC status missing; ","")&IF(N(AT18)>N(Q18)*1.05,"Received > ordered +5%; ","")&IF(AND(N(AI18)>0,AE18=""),"Payment terms missing; ","")&IF(N(AI18)>N(AD18)+1,"Overpaid vs PO; ","")&IF(AND(N(AK18)>0,AY18<>"",AO18=""),"Payment due date missing; ",""))) -> OK | BK18: =IF(A18="","",IF(N(AP18)>0,"Pay supplier: "&N(AP18)&" days overdue; ","")&IF(AND(O18<>"",AY18="",N(BD18)>0),"Expedite delivery: "&N(BD18)&" days late; ","")&IF(AND(BI18="Awaiting Approval",ISNUMBER(B18),Settings!$B$4-N(B18)>Settings!$B$19),"Get approval: PR waiting "&(Settings!$B$4-N(B18))&" days; ","")&IF(AND(BI18="Approved - PO Pending",ISNUMBER(J18),Settings!$B$4-N(J18)>Settings!$B$20),"Issue PO: approved "&(Settings!$B$4-N(J18))&" days ago; ","")&IF(AND(OR(BI18="Awaiting Approval",BI18="Approved - PO Pending"),N(AB18)>Settings!$B$7),"Negotiate price: "&TEXT(AB18,"0%")&" above budget; ","")&IF(LEFT(AX18,12)="Short Closed","Short closed: claim balance / credit note"&IF(N(AL18)>0," BDT "&TEXT(AL18,"#,##0"),"")&"; ","")&IF(BF18="Rejected","QC rejected: return / replace; ","")&IF(AND(O18<>"",AY18="",N(AL18)>0,N(BD18)>0),"Advance at risk: BDT "&TEXT(AL18,"#,##0")&" paid, goods late; ","")&IF(AND(BJ18<>"",BJ18<>"OK"),"Fix data entry (see Data Check); ","")) -> Pay supplier: 31 days overdue; | BL18: =IF(BK18="","",IF(OR(N(AP18)>30,AND(AY18="",N(BD18)>15),BF18="Rejected",AND(LEFT(AX18,12)="Short Closed",N(AL18)>0),AND(O18<>"",AY18="",N(AL18)>0,N(BD18)>0)),"High",IF(OR(N(AP18)>0,AND(AY18="",N(BD18)>7),LEFT(AX18,12)="Short Closed",AND(BI18="Awaiting Approval",ISNUMBER(B18),Settings!$B$4-N(B18)>2*Settings!$B$19),AND(BI18="Approved - PO Pending",ISNUMBER(J18),Settings!$B$4-N(J18)>2*Settings!$B$20)),"Medium","Low"))) -> High | BM18: =IF(BL18="","",IF(BL18="High",1,IF(BL18="Medium",2,3))*10000+ROW()) -> 10018
A19: PSIL-PR-2026-0014 | B19: 46213 | C19: Cutting | D19: Cutting Manager | E19: Toe Puff & Counter Sheet | F19: Synthetic & Textile | G19: Thermoplastic 1.2 mm | H19: OPEX | I19: OPX-2026-114 | J19: 46214 | K19: Approved | L19: GM Operations | M19: Dongguan Sole Tech Co. | N19: Import | O19: PSIL-PO-2026-0014 | P19: 46219 | Q19: 3700 | R19: sheet | S19: 3.35 | T19: USD | U19: =IF(AND(T19="",S19=""),"",IF(T19="",1,IFERROR(INDEX(Settings!$B$12:$B$16,MATCH(T19,Settings!$A$12:$A$16,0)),1))) -> 122 | V19: 418.36 | W19: =IF(OR(Q19="",S19=""),"",Q19*S19*U19) -> 1512190 | X19: =IF(OR(W19="",N(Q19)=0),"",W19/Q19) -> 408.7 | Y19: =IF(OR(X19="",P19="",E19=""),"",IF(_xlfn.MAXIFS($P$6:$P$205,$E$6:$E$205,E19,$P$6:$P$205,"<"&P19,$X$6:$X$205,">0")=0,"",IFERROR(AVERAGEIFS($X$6:$X$205,$E$6:$E$205,E19,$P$6:$P$205,_xlfn.MAXIFS($P$6:$P$205,$E$6:$E$205,E19,$P$6:$P$205,"<"&P19,$X$6:$X$205,">0"),$X$6:$X$205,">0"),""))) | Z19: =IF(OR(Y19="",X19=""),"",X19/Y19-1) | AA19: =IF(OR(W19="",V19=""),"",W19-Q19*V19) -> -35742 | AB19: =IF(AA19="","",IF(N(V19)*N(Q19)=0,"",AA19/(Q19*V19))) -> -0.023090162 | AC19: 0.15 | AD19: =IF(W19="","",W19*(1+N(AC19))) -> 1739018.5 | AE19: LC at Sight | AH19: 1739018.5 | AI19: =IF(A19="","",N(AF19)+N(AG19)+N(AH19)) -> 1739018.5 | AJ19: =IF(AD19="","",IF(N(AD19)=0,"",AI19/AD19)) -> 1 | AK19: =IF(AD19="","",IF(AD19-AI19<1,0,ROUND(AD19-AI19,2))) -> 0 | AL19: =IF(OR(O19="",AD19=""),"",MAX(0,ROUND(N(AI19)-(AD19-N(AW19)),0))) -> 0 | AM19: =IF(A19="","",IF(O19="","No PO Yet",IF(AI19=0,"Not Paid",IF(N(AJ19)>=0.999,"Fully Paid",IF(N(AG19)+N(AH19)>0,"Partially Paid","Initial / Advance Paid"))))) -> Fully Paid | AN19: 46255 | AP19: =IF(AK19="","",IF(OR(N(AK19)=0,AO19=""),"",MAX(0,Settings!$B$4-AO19))) | AQ19: =IF(AK19="","",IF(N(AK19)<=0,"",IF(AO19="","No Due Date",IF(Settings!$B$4<=AO19,"Not Yet Due",IF(Settings!$B$4-AO19<=30,"1-30 Days",IF(Settings!$B$4-AO19<=60,"31-60 Days",IF(Settings!$B$4-AO19<=90,"61-90 Days","90+ Days"))))))) | AR19: 46265 | AS19: 46261 | AT19: 3700 | AU19: =IF(Q19="","",IF(N(Q19)=0,"",N(AT19)/Q19)) -> 1 | AV19: =IF(OR(A19="",O19="",Q19=""),"",MAX(0,Q19-N(AT19))) -> 0 | AW19: =IF(OR(AV19="",W19=""),"",IF(N(Q19)=0,0,AV19/Q19*AD19)) -> 0 | AX19: =IF(A19="","",IF(O19="","No PO Yet",IF(Q19="","Order Qty Missing",IF(N(AT19)>=Q19,IF(N(AT19)>Q19,"All In-house (+"&TEXT(N(AT19)-Q19,"#,##0")&" "&R19&" excess)","All In-house"),IF(AY19<>"","Short Closed - "&TEXT(AV19,"#,##0")&" "&R19&" not received",IF(N(AT19)=0,"Not Started - "&TEXT(AV19,"#,##0")&" "&R19&" pending","Pending "&TEXT(AV19,"#,##0")&" "&R19&" ("&TEXT(AU19,"0%")&" received)")))))) -> All In-house | AY19: 46263 | AZ19: =IF(OR(B19="",J19=""),"",J19-B19) -> 1 | BA19: =IF(OR(J19="",P19=""),"",P19-J19) -> 5 | BB19: =IF(OR(P19="",AY19=""),"",AY19-P19) -> 44 | BC19: =IF(OR(B19="",AY19=""),"",AY19-B19) -> 50 | BD19: =IF(OR(AR19="",O19=""),"",MAX(0,IF(AY19="",Settings!$B$4,AY19)-AR19)) -> 0 | BE19: =IF(OR(AY19="",AR19=""),"",IF(AND(AY19<=AR19,N(AU19)>=Settings!$B$6),"OTIF","Not OTIF")) -> OTIF | BF19: Approved | BG19: Photos\PSIL-PR-2026-0014.jpg | BI19: =IF(A19="","",IF(K19="Rejected","Rejected",IF(K19<>"Approved","Awaiting Approval",IF(O19="","Approved - PO Pending",IF(AY19<>"",IF(N(AJ19)>=0.999,"Closed","In-house Closed - Payment Due"),IF(AS19<>"","Receiving In-house","PO Issued - Awaiting Delivery")))))) -> Closed | BJ19: =IF(A19="","",IF(IF(AND(A19<>"",OR(B19="",C19="",E19="",F19="",H19="")),"PR info missing; ","")&IF(AND(K19="Approved",OR(J19="",I19="")),"Approval ref/date missing; ","")&IF(AND(O19<>"",K19<>"Approved"),"PO without approval; ","")&IF(AND(O19<>"",OR(P19="",M19="",Q19="",S19="",T19="")),"PO details missing; ","")&IF(AND(O19<>"",AR19=""),"Committed date missing; ","")&IF(AND(ISNUMBER(J19),ISNUMBER(B19),N(J19)<N(B19)),"Approval dated before PR; ","")&IF(AND(ISNUMBER(P19),ISNUMBER(J19),N(P19)<N(J19)),"PO dated before approval; ","")&IF(AND(ISNUMBER(AY19),ISNUMBER(AS19),N(AY19)<N(AS19)),"Close before in-house start; ","")&IF(AND(AY19<>"",AS19=""),"In-house start date missing; ","")&IF(AND(AY19<>"",AT19=""),"Qty received missing; ","")&IF(AND(AY19<>"",BF19=""),"QC status missing; ","")&IF(N(AT19)>N(Q19)*1.05,"Received > ordered +5%; ","")&IF(AND(N(AI19)>0,AE19=""),"Payment terms missing; ","")&IF(N(AI19)>N(AD19)+1,"Overpaid vs PO; ","")&IF(AND(N(AK19)>0,AY19<>"",AO19=""),"Payment due date missing; ","")="","OK",IF(AND(A19<>"",OR(B19="",C19="",E19="",F19="",H19="")),"PR info missing; ","")&IF(AND(K19="Approved",OR(J19="",I19="")),"Approval ref/date missing; ","")&IF(AND(O19<>"",K19<>"Approved"),"PO without approval; ","")&IF(AND(O19<>"",OR(P19="",M19="",Q19="",S19="",T19="")),"PO details missing; ","")&IF(AND(O19<>"",AR19=""),"Committed date missing; ","")&IF(AND(ISNUMBER(J19),ISNUMBER(B19),N(J19)<N(B19)),"Approval dated before PR; ","")&IF(AND(ISNUMBER(P19),ISNUMBER(J19),N(P19)<N(J19)),"PO dated before approval; ","")&IF(AND(ISNUMBER(AY19),ISNUMBER(AS19),N(AY19)<N(AS19)),"Close before in-house start; ","")&IF(AND(AY19<>"",AS19=""),"In-house start date missing; ","")&IF(AND(AY19<>"",AT19=""),"Qty received missing; ","")&IF(AND(AY19<>"",BF19=""),"QC status missing; ","")&IF(N(AT19)>N(Q19)*1.05,"Received > ordered +5%; ","")&IF(AND(N(AI19)>0,AE19=""),"Payment terms missing; ","")&IF(N(AI19)>N(AD19)+1,"Overpaid vs PO; ","")&IF(AND(N(AK19)>0,AY19<>"",AO19=""),"Payment due date missing; ",""))) -> OK | BK19: =IF(A19="","",IF(N(AP19)>0,"Pay supplier: "&N(AP19)&" days overdue; ","")&IF(AND(O19<>"",AY19="",N(BD19)>0),"Expedite delivery: "&N(BD19)&" days late; ","")&IF(AND(BI19="Awaiting Approval",ISNUMBER(B19),Settings!$B$4-N(B19)>Settings!$B$19),"Get approval: PR waiting "&(Settings!$B$4-N(B19))&" days; ","")&IF(AND(BI19="Approved - PO Pending",ISNUMBER(J19),Settings!$B$4-N(J19)>Settings!$B$20),"Issue PO: approved "&(Settings!$B$4-N(J19))&" days ago; ","")&IF(AND(OR(BI19="Awaiting Approval",BI19="Approved - PO Pending"),N(AB19)>Settings!$B$7),"Negotiate price: "&TEXT(AB19,"0%")&" above budget; ","")&IF(LEFT(AX19,12)="Short Closed","Short closed: claim balance / credit note"&IF(N(AL19)>0," BDT "&TEXT(AL19,"#,##0"),"")&"; ","")&IF(BF19="Rejected","QC rejected: return / replace; ","")&IF(AND(O19<>"",AY19="",N(AL19)>0,N(BD19)>0),"Advance at risk: BDT "&TEXT(AL19,"#,##0")&" paid, goods late; ","")&IF(AND(BJ19<>"",BJ19<>"OK"),"Fix data entry (see Data Check); ","")) | BL19: =IF(BK19="","",IF(OR(N(AP19)>30,AND(AY19="",N(BD19)>15),BF19="Rejected",AND(LEFT(AX19,12)="Short Closed",N(AL19)>0),AND(O19<>"",AY19="",N(AL19)>0,N(BD19)>0)),"High",IF(OR(N(AP19)>0,AND(AY19="",N(BD19)>7),LEFT(AX19,12)="Short Closed",AND(BI19="Awaiting Approval",ISNUMBER(B19),Settings!$B$4-N(B19)>2*Settings!$B$19),AND(BI19="Approved - PO Pending",ISNUMBER(J19),Settings!$B$4-N(J19)>2*Settings!$B$20)),"Medium","Low"))) | BM19: =IF(BL19="","",IF(BL19="High",1,IF(BL19="Medium",2,3))*10000+ROW()) | BN19: Price above budget — CFO note on file
A20: PSIL-PR-2026-0015 | B20: 46217 | C20: Finishing & Packing | D20: Finishing Manager | E20: Shoe Box – Printed | F20: Packaging | G20: Kraft, 3-ply, branded | H20: OPEX | I20: OPX-2026-115 | J20: 46219 | K20: Approved | L20: CFO | M20: Chattogram Packaging Ltd | N20: Local | O20: PSIL-PO-2026-0015 | P20: 46223 | Q20: 17300 | R20: pcs | S20: 39.22 | T20: BDT | U20: =IF(AND(T20="",S20=""),"",IF(T20="",1,IFERROR(INDEX(Settings!$B$12:$B$16,MATCH(T20,Settings!$A$12:$A$16,0)),1))) -> 1 | V20: 38.66 | W20: =IF(OR(Q20="",S20=""),"",Q20*S20*U20) -> 678506 | X20: =IF(OR(W20="",N(Q20)=0),"",W20/Q20) -> 39.22 | Y20: =IF(OR(X20="",P20="",E20=""),"",IF(_xlfn.MAXIFS($P$6:$P$205,$E$6:$E$205,E20,$P$6:$P$205,"<"&P20,$X$6:$X$205,">0")=0,"",IFERROR(AVERAGEIFS($X$6:$X$205,$E$6:$E$205,E20,$P$6:$P$205,_xlfn.MAXIFS($P$6:$P$205,$E$6:$E$205,E20,$P$6:$P$205,"<"&P20,$X$6:$X$205,">0"),$X$6:$X$205,">0"),""))) | Z20: =IF(OR(Y20="",X20=""),"",X20/Y20-1) | AA20: =IF(OR(W20="",V20=""),"",W20-Q20*V20) -> 9688 | AB20: =IF(AA20="","",IF(N(V20)*N(Q20)=0,"",AA20/(Q20*V20))) -> 0.014485256 | AC20: 0.05 | AD20: =IF(W20="","",W20*(1+N(AC20))) -> 712431.3 | AE20: Credit 30 Days | AH20: 712431.3 | AI20: =IF(A20="","",N(AF20)+N(AG20)+N(AH20)) -> 712431.3 | AJ20: =IF(AD20="","",IF(N(AD20)=0,"",AI20/AD20)) -> 1 | AK20: =IF(AD20="","",IF(AD20-AI20<1,0,ROUND(AD20-AI20,2))) -> 0 | AL20: =IF(OR(O20="",AD20=""),"",MAX(0,ROUND(N(AI20)-(AD20-N(AW20)),0))) -> 0 | AM20: =IF(A20="","",IF(O20="","No PO Yet",IF(AI20=0,"Not Paid",IF(N(AJ20)>=0.999,"Fully Paid",IF(N(AG20)+N(AH20)>0,"Partially Paid","Initial / Advance Paid"))))) -> Fully Paid | AN20: 46274 | AP20: =IF(AK20="","",IF(OR(N(AK20)=0,AO20=""),"",MAX(0,Settings!$B$4-AO20))) | AQ20: =IF(AK20="","",IF(N(AK20)<=0,"",IF(AO20="","No Due Date",IF(Settings!$B$4<=AO20,"Not Yet Due",IF(Settings!$B$4-AO20<=30,"1-30 Days",IF(Settings!$B$4-AO20<=60,"31-60 Days",IF(Settings!$B$4-AO20<=90,"61-90 Days","90+ Days"))))))) | AR20: 46244 | AS20: 46241 | AT20: 17300 | AU20: =IF(Q20="","",IF(N(Q20)=0,"",N(AT20)/Q20)) -> 1 | AV20: =IF(OR(A20="",O20="",Q20=""),"",MAX(0,Q20-N(AT20))) -> 0 | AW20: =IF(OR(AV20="",W20=""),"",IF(N(Q20)=0,0,AV20/Q20*AD20)) -> 0 | AX20: =IF(A20="","",IF(O20="","No PO Yet",IF(Q20="","Order Qty Missing",IF(N(AT20)>=Q20,IF(N(AT20)>Q20,"All In-house (+"&TEXT(N(AT20)-Q20,"#,##0")&" "&R20&" excess)","All In-house"),IF(AY20<>"","Short Closed - "&TEXT(AV20,"#,##0")&" "&R20&" not received",IF(N(AT20)=0,"Not Started - "&TEXT(AV20,"#,##0")&" "&R20&" pending","Pending "&TEXT(AV20,"#,##0")&" "&R20&" ("&TEXT(AU20,"0%")&" received)")))))) -> All In-house | AY20: 46244 | AZ20: =IF(OR(B20="",J20=""),"",J20-B20) -> 2 | BA20: =IF(OR(J20="",P20=""),"",P20-J20) -> 4 | BB20: =IF(OR(P20="",AY20=""),"",AY20-P20) -> 21 | BC20: =IF(OR(B20="",AY20=""),"",AY20-B20) -> 27 | BD20: =IF(OR(AR20="",O20=""),"",MAX(0,IF(AY20="",Settings!$B$4,AY20)-AR20)) -> 0 | BE20: =IF(OR(AY20="",AR20=""),"",IF(AND(AY20<=AR20,N(AU20)>=Settings!$B$6),"OTIF","Not OTIF")) -> OTIF | BF20: Approved | BG20: Photos\PSIL-PR-2026-0015.jpg | BI20: =IF(A20="","",IF(K20="Rejected","Rejected",IF(K20<>"Approved","Awaiting Approval",IF(O20="","Approved - PO Pending",IF(AY20<>"",IF(N(AJ20)>=0.999,"Closed","In-house Closed - Payment Due"),IF(AS20<>"","Receiving In-house","PO Issued - Awaiting Delivery")))))) -> Closed | BJ20: =IF(A20="","",IF(IF(AND(A20<>"",OR(B20="",C20="",E20="",F20="",H20="")),"PR info missing; ","")&IF(AND(K20="Approved",OR(J20="",I20="")),"Approval ref/date missing; ","")&IF(AND(O20<>"",K20<>"Approved"),"PO without approval; ","")&IF(AND(O20<>"",OR(P20="",M20="",Q20="",S20="",T20="")),"PO details missing; ","")&IF(AND(O20<>"",AR20=""),"Committed date missing; ","")&IF(AND(ISNUMBER(J20),ISNUMBER(B20),N(J20)<N(B20)),"Approval dated before PR; ","")&IF(AND(ISNUMBER(P20),ISNUMBER(J20),N(P20)<N(J20)),"PO dated before approval; ","")&IF(AND(ISNUMBER(AY20),ISNUMBER(AS20),N(AY20)<N(AS20)),"Close before in-house start; ","")&IF(AND(AY20<>"",AS20=""),"In-house start date missing; ","")&IF(AND(AY20<>"",AT20=""),"Qty received missing; ","")&IF(AND(AY20<>"",BF20=""),"QC status missing; ","")&IF(N(AT20)>N(Q20)*1.05,"Received > ordered +5%; ","")&IF(AND(N(AI20)>0,AE20=""),"Payment terms missing; ","")&IF(N(AI20)>N(AD20)+1,"Overpaid vs PO; ","")&IF(AND(N(AK20)>0,AY20<>"",AO20=""),"Payment due date missing; ","")="","OK",IF(AND(A20<>"",OR(B20="",C20="",E20="",F20="",H20="")),"PR info missing; ","")&IF(AND(K20="Approved",OR(J20="",I20="")),"Approval ref/date missing; ","")&IF(AND(O20<>"",K20<>"Approved"),"PO without approval; ","")&IF(AND(O20<>"",OR(P20="",M20="",Q20="",S20="",T20="")),"PO details missing; ","")&IF(AND(O20<>"",AR20=""),"Committed date missing; ","")&IF(AND(ISNUMBER(J20),ISNUMBER(B20),N(J20)<N(B20)),"Approval dated before PR; ","")&IF(AND(ISNUMBER(P20),ISNUMBER(J20),N(P20)<N(J20)),"PO dated before approval; ","")&IF(AND(ISNUMBER(AY20),ISNUMBER(AS20),N(AY20)<N(AS20)),"Close before in-house start; ","")&IF(AND(AY20<>"",AS20=""),"In-house start date missing; ","")&IF(AND(AY20<>"",AT20=""),"Qty received missing; ","")&IF(AND(AY20<>"",BF20=""),"QC status missing; ","")&IF(N(AT20)>N(Q20)*1.05,"Received > ordered +5%; ","")&IF(AND(N(AI20)>0,AE20=""),"Payment terms missing; ","")&IF(N(AI20)>N(AD20)+1,"Overpaid vs PO; ","")&IF(AND(N(AK20)>0,AY20<>"",AO20=""),"Payment due date missing; ",""))) -> OK | BK20: =IF(A20="","",IF(N(AP20)>0,"Pay supplier: "&N(AP20)&" days overdue; ","")&IF(AND(O20<>"",AY20="",N(BD20)>0),"Expedite delivery: "&N(BD20)&" days late; ","")&IF(AND(BI20="Awaiting Approval",ISNUMBER(B20),Settings!$B$4-N(B20)>Settings!$B$19),"Get approval: PR waiting "&(Settings!$B$4-N(B20))&" days; ","")&IF(AND(BI20="Approved - PO Pending",ISNUMBER(J20),Settings!$B$4-N(J20)>Settings!$B$20),"Issue PO: approved "&(Settings!$B$4-N(J20))&" days ago; ","")&IF(AND(OR(BI20="Awaiting Approval",BI20="Approved - PO Pending"),N(AB20)>Settings!$B$7),"Negotiate price: "&TEXT(AB20,"0%")&" above budget; ","")&IF(LEFT(AX20,12)="Short Closed","Short closed: claim balance / credit note"&IF(N(AL20)>0," BDT "&TEXT(AL20,"#,##0"),"")&"; ","")&IF(BF20="Rejected","QC rejected: return / replace; ","")&IF(AND(O20<>"",AY20="",N(AL20)>0,N(BD20)>0),"Advance at risk: BDT "&TEXT(AL20,"#,##0")&" paid, goods late; ","")&IF(AND(BJ20<>"",BJ20<>"OK"),"Fix data entry (see Data Check); ","")) | BL20: =IF(BK20="","",IF(OR(N(AP20)>30,AND(AY20="",N(BD20)>15),BF20="Rejected",AND(LEFT(AX20,12)="Short Closed",N(AL20)>0),AND(O20<>"",AY20="",N(AL20)>0,N(BD20)>0)),"High",IF(OR(N(AP20)>0,AND(AY20="",N(BD20)>7),LEFT(AX20,12)="Short Closed",AND(BI20="Awaiting Approval",ISNUMBER(B20),Settings!$B$4-N(B20)>2*Settings!$B$19),AND(BI20="Approved - PO Pending",ISNUMBER(J20),Settings!$B$4-N(J20)>2*Settings!$B$20)),"Medium","Low"))) | BM20: =IF(BL20="","",IF(BL20="High",1,IF(BL20="Medium",2,3))*10000+ROW())
A21: PSIL-PR-2026-0016 | B21: 46220 | C21: Finishing & Packing | D21: Finishing Manager | E21: Export Carton – 5 Ply | F21: Packaging | G21: 12 pair master | H21: OPEX | I21: OPX-2026-116 | J21: 46223 | K21: Approved | L21: GM Operations | M21: Chattogram Packaging Ltd | N21: Local | O21: PSIL-PO-2026-0016 | P21: 46226 | Q21: 1500 | R21: pcs | S21: 141 | T21: BDT | U21: =IF(AND(T21="",S21=""),"",IF(T21="",1,IFERROR(INDEX(Settings!$B$12:$B$16,MATCH(T21,Settings!$A$12:$A$16,0)),1))) -> 1 | V21: 145.91 | W21: =IF(OR(Q21="",S21=""),"",Q21*S21*U21) -> 211500 | X21: =IF(OR(W21="",N(Q21)=0),"",W21/Q21) -> 141 | Y21: =IF(OR(X21="",P21="",E21=""),"",IF(_xlfn.MAXIFS($P$6:$P$205,$E$6:$E$205,E21,$P$6:$P$205,"<"&P21,$X$6:$X$205,">0")=0,"",IFERROR(AVERAGEIFS($X$6:$X$205,$E$6:$E$205,E21,$P$6:$P$205,_xlfn.MAXIFS($P$6:$P$205,$E$6:$E$205,E21,$P$6:$P$205,"<"&P21,$X$6:$X$205,">0"),$X$6:$X$205,">0"),""))) | Z21: =IF(OR(Y21="",X21=""),"",X21/Y21-1) | AA21: =IF(OR(W21="",V21=""),"",W21-Q21*V21) -> -7365 | AB21: =IF(AA21="","",IF(N(V21)*N(Q21)=0,"",AA21/(Q21*V21))) -> -0.033650881 | AC21: 0.05 | AD21: =IF(W21="","",W21*(1+N(AC21))) -> 222075 | AE21: 30% Advance / 70% after In-house | AF21: 66622.5 | AH21: 155452.5 | AI21: =IF(A21="","",N(AF21)+N(AG21)+N(AH21)) -> 222075 | AJ21: =IF(AD21="","",IF(N(AD21)=0,"",AI21/AD21)) -> 1 | AK21: =IF(AD21="","",IF(AD21-AI21<1,0,ROUND(AD21-AI21,2))) -> 0 | AL21: =IF(OR(O21="",AD21=""),"",MAX(0,ROUND(N(AI21)-(AD21-N(AW21)),0))) -> 0 | AM21: =IF(A21="","",IF(O21="","No PO Yet",IF(AI21=0,"Not Paid",IF(N(AJ21)>=0.999,"Fully Paid",IF(N(AG21)+N(AH21)>0,"Partially Paid","Initial / Advance Paid"))))) -> Fully Paid | AN21: 46253 | AP21: =IF(AK21="","",IF(OR(N(AK21)=0,AO21=""),"",MAX(0,Settings!$B$4-AO21))) | AQ21: =IF(AK21="","",IF(N(AK21)<=0,"",IF(AO21="","No Due Date",IF(Settings!$B$4<=AO21,"Not Yet Due",IF(Settings!$B$4-AO21<=30,"1-30 Days",IF(Settings!$B$4-AO21<=60,"31-60 Days",IF(Settings!$B$4-AO21<=90,"61-90 Days","90+ Days"))))))) | AR21: 46241 | AS21: 46238 | AT21: 1500 | AU21: =IF(Q21="","",IF(N(Q21)=0,"",N(AT21)/Q21)) -> 1 | AV21: =IF(OR(A21="",O21="",Q21=""),"",MAX(0,Q21-N(AT21))) -> 0 | AW21: =IF(OR(AV21="",W21=""),"",IF(N(Q21)=0,0,AV21/Q21*AD21)) -> 0 | AX21: =IF(A21="","",IF(O21="","No PO Yet",IF(Q21="","Order Qty Missing",IF(N(AT21)>=Q21,IF(N(AT21)>Q21,"All In-house (+"&TEXT(N(AT21)-Q21,"#,##0")&" "&R21&" excess)","All In-house"),IF(AY21<>"","Short Closed - "&TEXT(AV21,"#,##0")&" "&R21&" not received",IF(N(AT21)=0,"Not Started - "&TEXT(AV21,"#,##0")&" "&R21&" pending","Pending "&TEXT(AV21,"#,##0")&" "&R21&" ("&TEXT(AU21,"0%")&" received)")))))) -> All In-house | AY21: 46238 | AZ21: =IF(OR(B21="",J21=""),"",J21-B21) -> 3 | BA21: =IF(OR(J21="",P21=""),"",P21-J21) -> 3 | BB21: =IF(OR(P21="",AY21=""),"",AY21-P21) -> 12 | BC21: =IF(OR(B21="",AY21=""),"",AY21-B21) -> 18 | BD21: =IF(OR(AR21="",O21=""),"",MAX(0,IF(AY21="",Settings!$B$4,AY21)-AR21)) -> 0 | BE21: =IF(OR(AY21="",AR21=""),"",IF(AND(AY21<=AR21,N(AU21)>=Settings!$B$6),"OTIF","Not OTIF")) -> OTIF | BF21: Approved | BG21: Photos\PSIL-PR-2026-0016.jpg | BI21: =IF(A21="","",IF(K21="Rejected","Rejected",IF(K21<>"Approved","Awaiting Approval",IF(O21="","Approved - PO Pending",IF(AY21<>"",IF(N(AJ21)>=0.999,"Closed","In-house Closed - Payment Due"),IF(AS21<>"","Receiving In-house","PO Issued - Awaiting Delivery")))))) -> Closed | BJ21: =IF(A21="","",IF(IF(AND(A21<>"",OR(B21="",C21="",E21="",F21="",H21="")),"PR info missing; ","")&IF(AND(K21="Approved",OR(J21="",I21="")),"Approval ref/date missing; ","")&IF(AND(O21<>"",K21<>"Approved"),"PO without approval; ","")&IF(AND(O21<>"",OR(P21="",M21="",Q21="",S21="",T21="")),"PO details missing; ","")&IF(AND(O21<>"",AR21=""),"Committed date missing; ","")&IF(AND(ISNUMBER(J21),ISNUMBER(B21),N(J21)<N(B21)),"Approval dated before PR; ","")&IF(AND(ISNUMBER(P21),ISNUMBER(J21),N(P21)<N(J21)),"PO dated before approval; ","")&IF(AND(ISNUMBER(AY21),ISNUMBER(AS21),N(AY21)<N(AS21)),"Close before in-house start; ","")&IF(AND(AY21<>"",AS21=""),"In-house start date missing; ","")&IF(AND(AY21<>"",AT21=""),"Qty received missing; ","")&IF(AND(AY21<>"",BF21=""),"QC status missing; ","")&IF(N(AT21)>N(Q21)*1.05,"Received > ordered +5%; ","")&IF(AND(N(AI21)>0,AE21=""),"Payment terms missing; ","")&IF(N(AI21)>N(AD21)+1,"Overpaid vs PO; ","")&IF(AND(N(AK21)>0,AY21<>"",AO21=""),"Payment due date missing; ","")="","OK",IF(AND(A21<>"",OR(B21="",C21="",E21="",F21="",H21="")),"PR info missing; ","")&IF(AND(K21="Approved",OR(J21="",I21="")),"Approval ref/date missing; ","")&IF(AND(O21<>"",K21<>"Approved"),"PO without approval; ","")&IF(AND(O21<>"",OR(P21="",M21="",Q21="",S21="",T21="")),"PO details missing; ","")&IF(AND(O21<>"",AR21=""),"Committed date missing; ","")&IF(AND(ISNUMBER(J21),ISNUMBER(B21),N(J21)<N(B21)),"Approval dated before PR; ","")&IF(AND(ISNUMBER(P21),ISNUMBER(J21),N(P21)<N(J21)),"PO dated before approval; ","")&IF(AND(ISNUMBER(AY21),ISNUMBER(AS21),N(AY21)<N(AS21)),"Close before in-house start; ","")&IF(AND(AY21<>"",AS21=""),"In-house start date missing; ","")&IF(AND(AY21<>"",AT21=""),"Qty received missing; ","")&IF(AND(AY21<>"",BF21=""),"QC status missing; ","")&IF(N(AT21)>N(Q21)*1.05,"Received > ordered +5%; ","")&IF(AND(N(AI21)>0,AE21=""),"Payment terms missing; ","")&IF(N(AI21)>N(AD21)+1,"Overpaid vs PO; ","")&IF(AND(N(AK21)>0,AY21<>"",AO21=""),"Payment due date missing; ",""))) -> OK | BK21: =IF(A21="","",IF(N(AP21)>0,"Pay supplier: "&N(AP21)&" days overdue; ","")&IF(AND(O21<>"",AY21="",N(BD21)>0),"Expedite delivery: "&N(BD21)&" days late; ","")&IF(AND(BI21="Awaiting Approval",ISNUMBER(B21),Settings!$B$4-N(B21)>Settings!$B$19),"Get approval: PR waiting "&(Settings!$B$4-N(B21))&" days; ","")&IF(AND(BI21="Approved - PO Pending",ISNUMBER(J21),Settings!$B$4-N(J21)>Settings!$B$20),"Issue PO: approved "&(Settings!$B$4-N(J21))&" days ago; ","")&IF(AND(OR(BI21="Awaiting Approval",BI21="Approved - PO Pending"),N(AB21)>Settings!$B$7),"Negotiate price: "&TEXT(AB21,"0%")&" above budget; ","")&IF(LEFT(AX21,12)="Short Closed","Short closed: claim balance / credit note"&IF(N(AL21)>0," BDT "&TEXT(AL21,"#,##0"),"")&"; ","")&IF(BF21="Rejected","QC rejected: return / replace; ","")&IF(AND(O21<>"",AY21="",N(AL21)>0,N(BD21)>0),"Advance at risk: BDT "&TEXT(AL21,"#,##0")&" paid, goods late; ","")&IF(AND(BJ21<>"",BJ21<>"OK"),"Fix data entry (see Data Check); ","")) | BL21: =IF(BK21="","",IF(OR(N(AP21)>30,AND(AY21="",N(BD21)>15),BF21="Rejected",AND(LEFT(AX21,12)="Short Closed",N(AL21)>0),AND(O21<>"",AY21="",N(AL21)>0,N(BD21)>0)),"High",IF(OR(N(AP21)>0,AND(AY21="",N(BD21)>7),LEFT(AX21,12)="Short Closed",AND(BI21="Awaiting Approval",ISNUMBER(B21),Settings!$B$4-N(B21)>2*Settings!$B$19),AND(BI21="Approved - PO Pending",ISNUMBER(J21),Settings!$B$4-N(J21)>2*Settings!$B$20)),"Medium","Low"))) | BM21: =IF(BL21="","",IF(BL21="High",1,IF(BL21="Medium",2,3))*10000+ROW())
A22: PSIL-PR-2026-0017 | B22: 46224 | C22: Maintenance | D22: Maintenance Manager | E22: Sewing Machine Needles & Spares | F22: Spare Parts | G22: Post-bed, assorted | H22: OPEX | I22: OPX-2026-117 | J22: 46225 | K22: Approved | L22: CFO | M22: Dhaka Spares & Tools | N22: Local | O22: PSIL-PO-2026-0017 | P22: 46229 | Q22: 40 | R22: set | S22: 1872 | T22: BDT | U22: =IF(AND(T22="",S22=""),"",IF(T22="",1,IFERROR(INDEX(Settings!$B$12:$B$16,MATCH(T22,Settings!$A$12:$A$16,0)),1))) -> 1 | V22: 1866.98 | W22: =IF(OR(Q22="",S22=""),"",Q22*S22*U22) -> 74880 | X22: =IF(OR(W22="",N(Q22)=0),"",W22/Q22) -> 1872 | Y22: =IF(OR(X22="",P22="",E22=""),"",IF(_xlfn.MAXIFS($P$6:$P$205,$E$6:$E$205,E22,$P$6:$P$205,"<"&P22,$X$6:$X$205,">0")=0,"",IFERROR(AVERAGEIFS($X$6:$X$205,$E$6:$E$205,E22,$P$6:$P$205,_xlfn.MAXIFS($P$6:$P$205,$E$6:$E$205,E22,$P$6:$P$205,"<"&P22,$X$6:$X$205,">0"),$X$6:$X$205,">0"),""))) | Z22: =IF(OR(Y22="",X22=""),"",X22/Y22-1) | AA22: =IF(OR(W22="",V22=""),"",W22-Q22*V22) -> 200.8 | AB22: =IF(AA22="","",IF(N(V22)*N(Q22)=0,"",AA22/(Q22*V22))) -> 0.0026888344 | AC22: 0.075 | AD22: =IF(W22="","",W22*(1+N(AC22))) -> 80496 | AE22: Credit 30 Days | AG22: 40248 | AI22: =IF(A22="","",N(AF22)+N(AG22)+N(AH22)) -> 40248 | AJ22: =IF(AD22="","",IF(N(AD22)=0,"",AI22/AD22)) -> 0.5 | AK22: =IF(AD22="","",IF(AD22-AI22<1,0,ROUND(AD22-AI22,2))) -> 40248 | AL22: =IF(OR(O22="",AD22=""),"",MAX(0,ROUND(N(AI22)-(AD22-N(AW22)),0))) -> 0 | AM22: =IF(A22="","",IF(O22="","No PO Yet",IF(AI22=0,"Not Paid",IF(N(AJ22)>=0.999,"Fully Paid",IF(N(AG22)+N(AH22)>0,"Partially Paid","Initial / Advance Paid"))))) -> Partially Paid | AN22: 46285 | AO22: 46285 | AP22: =IF(AK22="","",IF(OR(N(AK22)=0,AO22=""),"",MAX(0,Settings!$B$4-AO22))) -> 25 | AQ22: =IF(AK22="","",IF(N(AK22)<=0,"",IF(AO22="","No Due Date",IF(Settings!$B$4<=AO22,"Not Yet Due",IF(Settings!$B$4-AO22<=30,"1-30 Days",IF(Settings!$B$4-AO22<=60,"31-60 Days",IF(Settings!$B$4-AO22<=90,"61-90 Days","90+ Days"))))))) -> 1-30 Days | AR22: 46251 | AS22: 46254 | AT22: 40 | AU22: =IF(Q22="","",IF(N(Q22)=0,"",N(AT22)/Q22)) -> 1 | AV22: =IF(OR(A22="",O22="",Q22=""),"",MAX(0,Q22-N(AT22))) -> 0 | AW22: =IF(OR(AV22="",W22=""),"",IF(N(Q22)=0,0,AV22/Q22*AD22)) -> 0 | AX22: =IF(A22="","",IF(O22="","No PO Yet",IF(Q22="","Order Qty Missing",IF(N(AT22)>=Q22,IF(N(AT22)>Q22,"All In-house (+"&TEXT(N(AT22)-Q22,"#,##0")&" "&R22&" excess)","All In-house"),IF(AY22<>"","Short Closed - "&TEXT(AV22,"#,##0")&" "&R22&" not received",IF(N(AT22)=0,"Not Started - "&TEXT(AV22,"#,##0")&" "&R22&" pending","Pending "&TEXT(AV22,"#,##0")&" "&R22&" ("&TEXT(AU22,"0%")&" received)")))))) -> All In-house | AY22: 46255 | AZ22: =IF(OR(B22="",J22=""),"",J22-B22) -> 1 | BA22: =IF(OR(J22="",P22=""),"",P22-J22) -> 4 | BB22: =IF(OR(P22="",AY22=""),"",AY22-P22) -> 26 | BC22: =IF(OR(B22="",AY22=""),"",AY22-B22) -> 31 | BD22: =IF(OR(AR22="",O22=""),"",MAX(0,IF(AY22="",Settings!$B$4,AY22)-AR22)) -> 4 | BE22: =IF(OR(AY22="",AR22=""),"",IF(AND(AY22<=AR22,N(AU22)>=Settings!$B$6),"OTIF","Not OTIF")) -> Not OTIF | BF22: Rejected | BI22: =IF(A22="","",IF(K22="Rejected","Rejected",IF(K22<>"Approved","Awaiting Approval",IF(O22="","Approved - PO Pending",IF(AY22<>"",IF(N(AJ22)>=0.999,"Closed","In-house Closed - Payment Due"),IF(AS22<>"","Receiving In-house","PO Issued - Awaiting Delivery")))))) -> In-house Closed - Payment Due | BJ22: =IF(A22="","",IF(IF(AND(A22<>"",OR(B22="",C22="",E22="",F22="",H22="")),"PR info missing; ","")&IF(AND(K22="Approved",OR(J22="",I22="")),"Approval ref/date missing; ","")&IF(AND(O22<>"",K22<>"Approved"),"PO without approval; ","")&IF(AND(O22<>"",OR(P22="",M22="",Q22="",S22="",T22="")),"PO details missing; ","")&IF(AND(O22<>"",AR22=""),"Committed date missing; ","")&IF(AND(ISNUMBER(J22),ISNUMBER(B22),N(J22)<N(B22)),"Approval dated before PR; ","")&IF(AND(ISNUMBER(P22),ISNUMBER(J22),N(P22)<N(J22)),"PO dated before approval; ","")&IF(AND(ISNUMBER(AY22),ISNUMBER(AS22),N(AY22)<N(AS22)),"Close before in-house start; ","")&IF(AND(AY22<>"",AS22=""),"In-house start date missing; ","")&IF(AND(AY22<>"",AT22=""),"Qty received missing; ","")&IF(AND(AY22<>"",BF22=""),"QC status missing; ","")&IF(N(AT22)>N(Q22)*1.05,"Received > ordered +5%; ","")&IF(AND(N(AI22)>0,AE22=""),"Payment terms missing; ","")&IF(N(AI22)>N(AD22)+1,"Overpaid vs PO; ","")&IF(AND(N(AK22)>0,AY22<>"",AO22=""),"Payment due date missing; ","")="","OK",IF(AND(A22<>"",OR(B22="",C22="",E22="",F22="",H22="")),"PR info missing; ","")&IF(AND(K22="Approved",OR(J22="",I22="")),"Approval ref/date missing; ","")&IF(AND(O22<>"",K22<>"Approved"),"PO without approval; ","")&IF(AND(O22<>"",OR(P22="",M22="",Q22="",S22="",T22="")),"PO details missing; ","")&IF(AND(O22<>"",AR22=""),"Committed date missing; ","")&IF(AND(ISNUMBER(J22),ISNUMBER(B22),N(J22)<N(B22)),"Approval dated before PR; ","")&IF(AND(ISNUMBER(P22),ISNUMBER(J22),N(P22)<N(J22)),"PO dated before approval; ","")&IF(AND(ISNUMBER(AY22),ISNUMBER(AS22),N(AY22)<N(AS22)),"Close before in-house start; ","")&IF(AND(AY22<>"",AS22=""),"In-house start date missing; ","")&IF(AND(AY22<>"",AT22=""),"Qty received missing; ","")&IF(AND(AY22<>"",BF22=""),"QC status missing; ","")&IF(N(AT22)>N(Q22)*1.05,"Received > ordered +5%; ","")&IF(AND(N(AI22)>0,AE22=""),"Payment terms missing; ","")&IF(N(AI22)>N(AD22)+1,"Overpaid vs PO; ","")&IF(AND(N(AK22)>0,AY22<>"",AO22=""),"Payment due date missing; ",""))) -> OK | BK22: =IF(A22="","",IF(N(AP22)>0,"Pay supplier: "&N(AP22)&" days overdue; ","")&IF(AND(O22<>"",AY22="",N(BD22)>0),"Expedite delivery: "&N(BD22)&" days late; ","")&IF(AND(BI22="Awaiting Approval",ISNUMBER(B22),Settings!$B$4-N(B22)>Settings!$B$19),"Get approval: PR waiting "&(Settings!$B$4-N(B22))&" days; ","")&IF(AND(BI22="Approved - PO Pending",ISNUMBER(J22),Settings!$B$4-N(J22)>Settings!$B$20),"Issue PO: approved "&(Settings!$B$4-N(J22))&" days ago; ","")&IF(AND(OR(BI22="Awaiting Approval",BI22="Approved - PO Pending"),N(AB22)>Settings!$B$7),"Negotiate price: "&TEXT(AB22,"0%")&" above budget; ","")&IF(LEFT(AX22,12)="Short Closed","Short closed: claim balance / credit note"&IF(N(AL22)>0," BDT "&TEXT(AL22,"#,##0"),"")&"; ","")&IF(BF22="Rejected","QC rejected: return / replace; ","")&IF(AND(O22<>"",AY22="",N(AL22)>0,N(BD22)>0),"Advance at risk: BDT "&TEXT(AL22,"#,##0")&" paid, goods late; ","")&IF(AND(BJ22<>"",BJ22<>"OK"),"Fix data entry (see Data Check); ","")) -> Pay supplier: 25 days overdue; QC rejected: return / replace; | BL22: =IF(BK22="","",IF(OR(N(AP22)>30,AND(AY22="",N(BD22)>15),BF22="Rejected",AND(LEFT(AX22,12)="Short Closed",N(AL22)>0),AND(O22<>"",AY22="",N(AL22)>0,N(BD22)>0)),"High",IF(OR(N(AP22)>0,AND(AY22="",N(BD22)>7),LEFT(AX22,12)="Short Closed",AND(BI22="Awaiting Approval",ISNUMBER(B22),Settings!$B$4-N(B22)>2*Settings!$B$19),AND(BI22="Approved - PO Pending",ISNUMBER(J22),Settings!$B$4-N(J22)>2*Settings!$B$20)),"Medium","Low"))) -> High | BM22: =IF(BL22="","",IF(BL22="High",1,IF(BL22="Medium",2,3))*10000+ROW()) -> 10022
A23: PSIL-PR-2026-0018 | B23: 46226 | C23: Compliance & HSE | D23: HSE Officer | E23: Safety PPE (Masks, Gloves, Goggles) | F23: Safety & Facility | G23: Chemical area kit | H23: OPEX | I23: OPX-2026-118 | J23: 46228 | K23: Approved | L23: CFO | M23: Dhaka Spares & Tools | N23: Local | O23: PSIL-PO-2026-0018 | P23: 46230 | Q23: 200 | R23: set | S23: 999 | T23: BDT | U23: =IF(AND(T23="",S23=""),"",IF(T23="",1,IFERROR(INDEX(Settings!$B$12:$B$16,MATCH(T23,Settings!$A$12:$A$16,0)),1))) -> 1 | V23: 926.34 | W23: =IF(OR(Q23="",S23=""),"",Q23*S23*U23) -> 199800 | X23: =IF(OR(W23="",N(Q23)=0),"",W23/Q23) -> 999 | Y23: =IF(OR(X23="",P23="",E23=""),"",IF(_xlfn.MAXIFS($P$6:$P$205,$E$6:$E$205,E23,$P$6:$P$205,"<"&P23,$X$6:$X$205,">0")=0,"",IFERROR(AVERAGEIFS($X$6:$X$205,$E$6:$E$205,E23,$P$6:$P$205,_xlfn.MAXIFS($P$6:$P$205,$E$6:$E$205,E23,$P$6:$P$205,"<"&P23,$X$6:$X$205,">0"),$X$6:$X$205,">0"),""))) | Z23: =IF(OR(Y23="",X23=""),"",X23/Y23-1) | AA23: =IF(OR(W23="",V23=""),"",W23-Q23*V23) -> 14532 | AB23: =IF(AA23="","",IF(N(V23)*N(Q23)=0,"",AA23/(Q23*V23))) -> 0.078437723 | AC23: 0.075 | AD23: =IF(W23="","",W23*(1+N(AC23))) -> 214785 | AE23: Credit 30 Days | AG23: 107392.5 | AI23: =IF(A23="","",N(AF23)+N(AG23)+N(AH23)) -> 107392.5 | AJ23: =IF(AD23="","",IF(N(AD23)=0,"",AI23/AD23)) -> 0.5 | AK23: =IF(AD23="","",IF(AD23-AI23<1,0,ROUND(AD23-AI23,2))) -> 107392.5 | AL23: =IF(OR(O23="",AD23=""),"",MAX(0,ROUND(N(AI23)-(AD23-N(AW23)),0))) -> 0 | AM23: =IF(A23="","",IF(O23="","No PO Yet",IF(AI23=0,"Not Paid",IF(N(AJ23)>=0.999,"Fully Paid",IF(N(AG23)+N(AH23)>0,"Partially Paid","Initial / Advance Paid"))))) -> Partially Paid | AN23: 46274 | AO23: 46274 | AP23: =IF(AK23="","",IF(OR(N(AK23)=0,AO23=""),"",MAX(0,Settings!$B$4-AO23))) -> 36 | AQ23: =IF(AK23="","",IF(N(AK23)<=0,"",IF(AO23="","No Due Date",IF(Settings!$B$4<=AO23,"Not Yet Due",IF(Settings!$B$4-AO23<=30,"1-30 Days",IF(Settings!$B$4-AO23<=60,"31-60 Days",IF(Settings!$B$4-AO23<=90,"61-90 Days","90+ Days"))))))) -> 31-60 Days | AR23: 46240 | AS23: 46243 | AT23: 200 | AU23: =IF(Q23="","",IF(N(Q23)=0,"",N(AT23)/Q23)) -> 1 | AV23: =IF(OR(A23="",O23="",Q23=""),"",MAX(0,Q23-N(AT23))) -> 0 | AW23: =IF(OR(AV23="",W23=""),"",IF(N(Q23)=0,0,AV23/Q23*AD23)) -> 0 | AX23: =IF(A23="","",IF(O23="","No PO Yet",IF(Q23="","Order Qty Missing",IF(N(AT23)>=Q23,IF(N(AT23)>Q23,"All In-house (+"&TEXT(N(AT23)-Q23,"#,##0")&" "&R23&" excess)","All In-house"),IF(AY23<>"","Short Closed - "&TEXT(AV23,"#,##0")&" "&R23&" not received",IF(N(AT23)=0,"Not Started - "&TEXT(AV23,"#,##0")&" "&R23&" pending","Pending "&TEXT(AV23,"#,##0")&" "&R23&" ("&TEXT(AU23,"0%")&" received)")))))) -> All In-house | AY23: 46244 | AZ23: =IF(OR(B23="",J23=""),"",J23-B23) -> 2 | BA23: =IF(OR(J23="",P23=""),"",P23-J23) -> 2 | BB23: =IF(OR(P23="",AY23=""),"",AY23-P23) -> 14 | BC23: =IF(OR(B23="",AY23=""),"",AY23-B23) -> 18 | BD23: =IF(OR(AR23="",O23=""),"",MAX(0,IF(AY23="",Settings!$B$4,AY23)-AR23)) -> 4 | BE23: =IF(OR(AY23="",AR23=""),"",IF(AND(AY23<=AR23,N(AU23)>=Settings!$B$6),"OTIF","Not OTIF")) -> Not OTIF | BF23: Approved with Deviation | BI23: =IF(A23="","",IF(K23="Rejected","Rejected",IF(K23<>"Approved","Awaiting Approval",IF(O23="","Approved - PO Pending",IF(AY23<>"",IF(N(AJ23)>=0.999,"Closed","In-house Closed - Payment Due"),IF(AS23<>"","Receiving In-house","PO Issued - Awaiting Delivery")))))) -> In-house Closed - Payment Due | BJ23: =IF(A23="","",IF(IF(AND(A23<>"",OR(B23="",C23="",E23="",F23="",H23="")),"PR info missing; ","")&IF(AND(K23="Approved",OR(J23="",I23="")),"Approval ref/date missing; ","")&IF(AND(O23<>"",K23<>"Approved"),"PO without approval; ","")&IF(AND(O23<>"",OR(P23="",M23="",Q23="",S23="",T23="")),"PO details missing; ","")&IF(AND(O23<>"",AR23=""),"Committed date missing; ","")&IF(AND(ISNUMBER(J23),ISNUMBER(B23),N(J23)<N(B23)),"Approval dated before PR; ","")&IF(AND(ISNUMBER(P23),ISNUMBER(J23),N(P23)<N(J23)),"PO dated before approval; ","")&IF(AND(ISNUMBER(AY23),ISNUMBER(AS23),N(AY23)<N(AS23)),"Close before in-house start; ","")&IF(AND(AY23<>"",AS23=""),"In-house start date missing; ","")&IF(AND(AY23<>"",AT23=""),"Qty received missing; ","")&IF(AND(AY23<>"",BF23=""),"QC status missing; ","")&IF(N(AT23)>N(Q23)*1.05,"Received > ordered +5%; ","")&IF(AND(N(AI23)>0,AE23=""),"Payment terms missing; ","")&IF(N(AI23)>N(AD23)+1,"Overpaid vs PO; ","")&IF(AND(N(AK23)>0,AY23<>"",AO23=""),"Payment due date missing; ","")="","OK",IF(AND(A23<>"",OR(B23="",C23="",E23="",F23="",H23="")),"PR info missing; ","")&IF(AND(K23="Approved",OR(J23="",I23="")),"Approval ref/date missing; ","")&IF(AND(O23<>"",K23<>"Approved"),"PO without approval; ","")&IF(AND(O23<>"",OR(P23="",M23="",Q23="",S23="",T23="")),"PO details missing; ","")&IF(AND(O23<>"",AR23=""),"Committed date missing; ","")&IF(AND(ISNUMBER(J23),ISNUMBER(B23),N(J23)<N(B23)),"Approval dated before PR; ","")&IF(AND(ISNUMBER(P23),ISNUMBER(J23),N(P23)<N(J23)),"PO dated before approval; ","")&IF(AND(ISNUMBER(AY23),ISNUMBER(AS23),N(AY23)<N(AS23)),"Close before in-house start; ","")&IF(AND(AY23<>"",AS23=""),"In-house start date missing; ","")&IF(AND(AY23<>"",AT23=""),"Qty received missing; ","")&IF(AND(AY23<>"",BF23=""),"QC status missing; ","")&IF(N(AT23)>N(Q23)*1.05,"Received > ordered +5%; ","")&IF(AND(N(AI23)>0,AE23=""),"Payment terms missing; ","")&IF(N(AI23)>N(AD23)+1,"Overpaid vs PO; ","")&IF(AND(N(AK23)>0,AY23<>"",AO23=""),"Payment due date missing; ",""))) -> OK | BK23: =IF(A23="","",IF(N(AP23)>0,"Pay supplier: "&N(AP23)&" days overdue; ","")&IF(AND(O23<>"",AY23="",N(BD23)>0),"Expedite delivery: "&N(BD23)&" days late; ","")&IF(AND(BI23="Awaiting Approval",ISNUMBER(B23),Settings!$B$4-N(B23)>Settings!$B$19),"Get approval: PR waiting "&(Settings!$B$4-N(B23))&" days; ","")&IF(AND(BI23="Approved - PO Pending",ISNUMBER(J23),Settings!$B$4-N(J23)>Settings!$B$20),"Issue PO: approved "&(Settings!$B$4-N(J23))&" days ago; ","")&IF(AND(OR(BI23="Awaiting Approval",BI23="Approved - PO Pending"),N(AB23)>Settings!$B$7),"Negotiate price: "&TEXT(AB23,"0%")&" above budget; ","")&IF(LEFT(AX23,12)="Short Closed","Short closed: claim balance / credit note"&IF(N(AL23)>0," BDT "&TEXT(AL23,"#,##0"),"")&"; ","")&IF(BF23="Rejected","QC rejected: return / replace; ","")&IF(AND(O23<>"",AY23="",N(AL23)>0,N(BD23)>0),"Advance at risk: BDT "&TEXT(AL23,"#,##0")&" paid, goods late; ","")&IF(AND(BJ23<>"",BJ23<>"OK"),"Fix data entry (see Data Check); ","")) -> Pay supplier: 36 days overdue; | BL23: =IF(BK23="","",IF(OR(N(AP23)>30,AND(AY23="",N(BD23)>15),BF23="Rejected",AND(LEFT(AX23,12)="Short Closed",N(AL23)>0),AND(O23<>"",AY23="",N(AL23)>0,N(BD23)>0)),"High",IF(OR(N(AP23)>0,AND(AY23="",N(BD23)>7),LEFT(AX23,12)="Short Closed",AND(BI23="Awaiting Approval",ISNUMBER(B23),Settings!$B$4-N(B23)>2*Settings!$B$19),AND(BI23="Approved - PO Pending",ISNUMBER(J23),Settings!$B$4-N(J23)>2*Settings!$B$20)),"Medium","Low"))) -> High | BM23: =IF(BL23="","",IF(BL23="High",1,IF(BL23="Medium",2,3))*10000+ROW()) -> 10023
A24: PSIL-PR-2026-0019 | B24: 46230 | C24: Maintenance | D24: Maintenance Manager | E24: Computerised Post-bed Sewing Machine | F24: Machinery & Equipment | G24: Single needle, servo | H24: CAPEX | I24: CPX-2026-119 | J24: 46235 | K24: Approved | L24: MD | M24: Jiangsu Footwear Machinery Co. | N24: Import | O24: PSIL-PO-2026-0019 | P24: 46240 | Q24: 16 | R24: unit | S24: 2543.07 | T24: USD | U24: =IF(AND(T24="",S24=""),"",IF(T24="",1,IFERROR(INDEX(Settings!$B$12:$B$16,MATCH(T24,Settings!$A$12:$A$16,0)),1))) -> 122 | V24: 313877.28 | W24: =IF(OR(Q24="",S24=""),"",Q24*S24*U24) -> 4964072.6 | X24: =IF(OR(W24="",N(Q24)=0),"",W24/Q24) -> 310254.54 | Y24: =IF(OR(X24="",P24="",E24=""),"",IF(_xlfn.MAXIFS($P$6:$P$205,$E$6:$E$205,E24,$P$6:$P$205,"<"&P24,$X$6:$X$205,">0")=0,"",IFERROR(AVERAGEIFS($X$6:$X$205,$E$6:$E$205,E24,$P$6:$P$205,_xlfn.MAXIFS($P$6:$P$205,$E$6:$E$205,E24,$P$6:$P$205,"<"&P24,$X$6:$X$205,">0"),$X$6:$X$205,">0"),""))) | Z24: =IF(OR(Y24="",X24=""),"",X24/Y24-1) | AA24: =IF(OR(W24="",V24=""),"",W24-Q24*V24) -> -57963.84 | AB24: =IF(AA24="","",IF(N(V24)*N(Q24)=0,"",AA24/(Q24*V24))) -> -0.011541899 | AC24: 0.12 | AD24: =IF(W24="","",W24*(1+N(AC24))) -> 5559761.4 | AE24: 50% Advance / 50% after Installation | AF24: 2779880.7 | AI24: =IF(A24="","",N(AF24)+N(AG24)+N(AH24)) -> 2779880.7 | AJ24: =IF(AD24="","",IF(N(AD24)=0,"",AI24/AD24)) -> 0.5 | AK24: =IF(AD24="","",IF(AD24-AI24<1,0,ROUND(AD24-AI24,2))) -> 2779880.7 | AL24: =IF(OR(O24="",AD24=""),"",MAX(0,ROUND(N(AI24)-(AD24-N(AW24)),0))) -> 0 | AM24: =IF(A24="","",IF(O24="","No PO Yet",IF(AI24=0,"Not Paid",IF(N(AJ24)>=0.999,"Fully Paid",IF(N(AG24)+N(AH24)>0,"Partially Paid","Initial / Advance Paid"))))) -> Initial / Advance Paid | AN24: 46243 | AO24: 46327 | AP24: =IF(AK24="","",IF(OR(N(AK24)=0,AO24=""),"",MAX(0,Settings!$B$4-AO24))) -> 0 | AQ24: =IF(AK24="","",IF(N(AK24)<=0,"",IF(AO24="","No Due Date",IF(Settings!$B$4<=AO24,"Not Yet Due",IF(Settings!$B$4-AO24<=30,"1-30 Days",IF(Settings!$B$4-AO24<=60,"31-60 Days",IF(Settings!$B$4-AO24<=90,"61-90 Days","90+ Days"))))))) -> Not Yet Due | AR24: 46298 | AS24: 46294 | AT24: 15 | AU24: =IF(Q24="","",IF(N(Q24)=0,"",N(AT24)/Q24)) -> 0.9375 | AV24: =IF(OR(A24="",O24="",Q24=""),"",MAX(0,Q24-N(AT24))) -> 1 | AW24: =IF(OR(AV24="",W24=""),"",IF(N(Q24)=0,0,AV24/Q24*AD24)) -> 347485.08 | AX24: =IF(A24="","",IF(O24="","No PO Yet",IF(Q24="","Order Qty Missing",IF(N(AT24)>=Q24,IF(N(AT24)>Q24,"All In-house (+"&TEXT(N(AT24)-Q24,"#,##0")&" "&R24&" excess)","All In-house"),IF(AY24<>"","Short Closed - "&TEXT(AV24,"#,##0")&" "&R24&" not received",IF(N(AT24)=0,"Not Started - "&TEXT(AV24,"#,##0")&" "&R24&" pending","Pending "&TEXT(AV24,"#,##0")&" "&R24&" ("&TEXT(AU24,"0%")&" received)")))))) -> Short Closed - 1 unit not received | AY24: 46297 | AZ24: =IF(OR(B24="",J24=""),"",J24-B24) -> 5 | BA24: =IF(OR(J24="",P24=""),"",P24-J24) -> 5 | BB24: =IF(OR(P24="",AY24=""),"",AY24-P24) -> 57 | BC24: =IF(OR(B24="",AY24=""),"",AY24-B24) -> 67 | BD24: =IF(OR(AR24="",O24=""),"",MAX(0,IF(AY24="",Settings!$B$4,AY24)-AR24)) -> 0 | BE24: =IF(OR(AY24="",AR24=""),"",IF(AND(AY24<=AR24,N(AU24)>=Settings!$B$6),"OTIF","Not OTIF")) -> Not OTIF | BF24: Approved with Deviation | BI24: =IF(A24="","",IF(K24="Rejected","Rejected",IF(K24<>"Approved","Awaiting Approval",IF(O24="","Approved - PO Pending",IF(AY24<>"",IF(N(AJ24)>=0.999,"Closed","In-house Closed - Payment Due"),IF(AS24<>"","Receiving In-house","PO Issued - Awaiting Delivery")))))) -> In-house Closed - Payment Due | BJ24: =IF(A24="","",IF(IF(AND(A24<>"",OR(B24="",C24="",E24="",F24="",H24="")),"PR info missing; ","")&IF(AND(K24="Approved",OR(J24="",I24="")),"Approval ref/date missing; ","")&IF(AND(O24<>"",K24<>"Approved"),"PO without approval; ","")&IF(AND(O24<>"",OR(P24="",M24="",Q24="",S24="",T24="")),"PO details missing; ","")&IF(AND(O24<>"",AR24=""),"Committed date missing; ","")&IF(AND(ISNUMBER(J24),ISNUMBER(B24),N(J24)<N(B24)),"Approval dated before PR; ","")&IF(AND(ISNUMBER(P24),ISNUMBER(J24),N(P24)<N(J24)),"PO dated before approval; ","")&IF(AND(ISNUMBER(AY24),ISNUMBER(AS24),N(AY24)<N(AS24)),"Close before in-house start; ","")&IF(AND(AY24<>"",AS24=""),"In-house start date missing; ","")&IF(AND(AY24<>"",AT24=""),"Qty received missing; ","")&IF(AND(AY24<>"",BF24=""),"QC status missing; ","")&IF(N(AT24)>N(Q24)*1.05,"Received > ordered +5%; ","")&IF(AND(N(AI24)>0,AE24=""),"Payment terms missing; ","")&IF(N(AI24)>N(AD24)+1,"Overpaid vs PO; ","")&IF(AND(N(AK24)>0,AY24<>"",AO24=""),"Payment due date missing; ","")="","OK",IF(AND(A24<>"",OR(B24="",C24="",E24="",F24="",H24="")),"PR info missing; ","")&IF(AND(K24="Approved",OR(J24="",I24="")),"Approval ref/date missing; ","")&IF(AND(O24<>"",K24<>"Approved"),"PO without approval; ","")&IF(AND(O24<>"",OR(P24="",M24="",Q24="",S24="",T24="")),"PO details missing; ","")&IF(AND(O24<>"",AR24=""),"Committed date missing; ","")&IF(AND(ISNUMBER(J24),ISNUMBER(B24),N(J24)<N(B24)),"Approval dated before PR; ","")&IF(AND(ISNUMBER(P24),ISNUMBER(J24),N(P24)<N(J24)),"PO dated before approval; ","")&IF(AND(ISNUMBER(AY24),ISNUMBER(AS24),N(AY24)<N(AS24)),"Close before in-house start; ","")&IF(AND(AY24<>"",AS24=""),"In-house start date missing; ","")&IF(AND(AY24<>"",AT24=""),"Qty received missing; ","")&IF(AND(AY24<>"",BF24=""),"QC status missing; ","")&IF(N(AT24)>N(Q24)*1.05,"Received > ordered +5%; ","")&IF(AND(N(AI24)>0,AE24=""),"Payment terms missing; ","")&IF(N(AI24)>N(AD24)+1,"Overpaid vs PO; ","")&IF(AND(N(AK24)>0,AY24<>"",AO24=""),"Payment due date missing; ",""))) -> OK | BK24: =IF(A24="","",IF(N(AP24)>0,"Pay supplier: "&N(AP24)&" days overdue; ","")&IF(AND(O24<>"",AY24="",N(BD24)>0),"Expedite delivery: "&N(BD24)&" days late; ","")&IF(AND(BI24="Awaiting Approval",ISNUMBER(B24),Settings!$B$4-N(B24)>Settings!$B$19),"Get approval: PR waiting "&(Settings!$B$4-N(B24))&" days; ","")&IF(AND(BI24="Approved - PO Pending",ISNUMBER(J24),Settings!$B$4-N(J24)>Settings!$B$20),"Issue PO: approved "&(Settings!$B$4-N(J24))&" days ago; ","")&IF(AND(OR(BI24="Awaiting Approval",BI24="Approved - PO Pending"),N(AB24)>Settings!$B$7),"Negotiate price: "&TEXT(AB24,"0%")&" above budget; ","")&IF(LEFT(AX24,12)="Short Closed","Short closed: claim balance / credit note"&IF(N(AL24)>0," BDT "&TEXT(AL24,"#,##0"),"")&"; ","")&IF(BF24="Rejected","QC rejected: return / replace; ","")&IF(AND(O24<>"",AY24="",N(AL24)>0,N(BD24)>0),"Advance at risk: BDT "&TEXT(AL24,"#,##0")&" paid, goods late; ","")&IF(AND(BJ24<>"",BJ24<>"OK"),"Fix data entry (see Data Check); ","")) -> Short closed: claim balance / credit note; | BL24: =IF(BK24="","",IF(OR(N(AP24)>30,AND(AY24="",N(BD24)>15),BF24="Rejected",AND(LEFT(AX24,12)="Short Closed",N(AL24)>0),AND(O24<>"",AY24="",N(AL24)>0,N(BD24)>0)),"High",IF(OR(N(AP24)>0,AND(AY24="",N(BD24)>7),LEFT(AX24,12)="Short Closed",AND(BI24="Awaiting Approval",ISNUMBER(B24),Settings!$B$4-N(B24)>2*Settings!$B$19),AND(BI24="Approved - PO Pending",ISNUMBER(J24),Settings!$B$4-N(J24)>2*Settings!$B$20)),"Medium","Low"))) -> Medium | BM24: =IF(BL24="","",IF(BL24="High",1,IF(BL24="Medium",2,3))*10000+ROW()) -> 20024
A25: PSIL-PR-2026-0020 | B25: 46232 | C25: Maintenance | D25: Maintenance Manager | E25: Leather Skiving Machine | F25: Machinery & Equipment | G25: Bell-knife type | H25: CAPEX | I25: CPX-2026-120 | J25: 46239 | K25: Approved | L25: MD | M25: Jiangsu Footwear Machinery Co. | N25: Import | O25: PSIL-PO-2026-0020 | P25: 46242 | Q25: 3 | R25: unit | S25: 3837.39 | T25: USD | U25: =IF(AND(T25="",S25=""),"",IF(T25="",1,IFERROR(INDEX(Settings!$B$12:$B$16,MATCH(T25,Settings!$A$12:$A$16,0)),1))) -> 122 | V25: 468392.92 | W25: =IF(OR(Q25="",S25=""),"",Q25*S25*U25) -> 1404484.7 | X25: =IF(OR(W25="",N(Q25)=0),"",W25/Q25) -> 468161.58 | Y25: =IF(OR(X25="",P25="",E25=""),"",IF(_xlfn.MAXIFS($P$6:$P$205,$E$6:$E$205,E25,$P$6:$P$205,"<"&P25,$X$6:$X$205,">0")=0,"",IFERROR(AVERAGEIFS($X$6:$X$205,$E$6:$E$205,E25,$P$6:$P$205,_xlfn.MAXIFS($P$6:$P$205,$E$6:$E$205,E25,$P$6:$P$205,"<"&P25,$X$6:$X$205,">0"),$X$6:$X$205,">0"),""))) | Z25: =IF(OR(Y25="",X25=""),"",X25/Y25-1) | AA25: =IF(OR(W25="",V25=""),"",W25-Q25*V25) -> -694.02 | AB25: =IF(AA25="","",IF(N(V25)*N(Q25)=0,"",AA25/(Q25*V25))) -> -0.00049390157 | AC25: 0.12 | AD25: =IF(W25="","",W25*(1+N(AC25))) -> 1573022.9 | AE25: 50% Advance / 50% after Installation | AF25: 786511.45 | AI25: =IF(A25="","",N(AF25)+N(AG25)+N(AH25)) -> 786511.45 | AJ25: =IF(AD25="","",IF(N(AD25)=0,"",AI25/AD25)) -> 0.5 | AK25: =IF(AD25="","",IF(AD25-AI25<1,0,ROUND(AD25-AI25,2))) -> 786511.46 | AL25: =IF(OR(O25="",AD25=""),"",MAX(0,ROUND(N(AI25)-(AD25-N(AW25)),0))) -> 0 | AM25: =IF(A25="","",IF(O25="","No PO Yet",IF(AI25=0,"Not Paid",IF(N(AJ25)>=0.999,"Fully Paid",IF(N(AG25)+N(AH25)>0,"Partially Paid","Initial / Advance Paid"))))) -> Initial / Advance Paid | AN25: 46245 | AO25: 46325 | AP25: =IF(AK25="","",IF(OR(N(AK25)=0,AO25=""),"",MAX(0,Settings!$B$4-AO25))) -> 0 | AQ25: =IF(AK25="","",IF(N(AK25)<=0,"",IF(AO25="","No Due Date",IF(Settings!$B$4<=AO25,"Not Yet Due",IF(Settings!$B$4-AO25<=30,"1-30 Days",IF(Settings!$B$4-AO25<=60,"31-60 Days",IF(Settings!$B$4-AO25<=90,"61-90 Days","90+ Days"))))))) -> Not Yet Due | AR25: 46294 | AS25: 46294 | AT25: 3 | AU25: =IF(Q25="","",IF(N(Q25)=0,"",N(AT25)/Q25)) -> 1 | AV25: =IF(OR(A25="",O25="",Q25=""),"",MAX(0,Q25-N(AT25))) -> 0 | AW25: =IF(OR(AV25="",W25=""),"",IF(N(Q25)=0,0,AV25/Q25*AD25)) -> 0 | AX25: =IF(A25="","",IF(O25="","No PO Yet",IF(Q25="","Order Qty Missing",IF(N(AT25)>=Q25,IF(N(AT25)>Q25,"All In-house (+"&TEXT(N(AT25)-Q25,"#,##0")&" "&R25&" excess)","All In-house"),IF(AY25<>"","Short Closed - "&TEXT(AV25,"#,##0")&" "&R25&" not received",IF(N(AT25)=0,"Not Started - "&TEXT(AV25,"#,##0")&" "&R25&" pending","Pending "&TEXT(AV25,"#,##0")&" "&R25&" ("&TEXT(AU25,"0%")&" received)")))))) -> All In-house | AY25: 46295 | AZ25: =IF(OR(B25="",J25=""),"",J25-B25) -> 7 | BA25: =IF(OR(J25="",P25=""),"",P25-J25) -> 3 | BB25: =IF(OR(P25="",AY25=""),"",AY25-P25) -> 53 | BC25: =IF(OR(B25="",AY25=""),"",AY25-B25) -> 63 | BD25: =IF(OR(AR25="",O25=""),"",MAX(0,IF(AY25="",Settings!$B$4,AY25)-AR25)) -> 1 | BE25: =IF(OR(AY25="",AR25=""),"",IF(AND(AY25<=AR25,N(AU25)>=Settings!$B$6),"OTIF","Not OTIF")) -> Not OTIF | BF25: Approved | BI25: =IF(A25="","",IF(K25="Rejected","Rejected",IF(K25<>"Approved","Awaiting Approval",IF(O25="","Approved - PO Pending",IF(AY25<>"",IF(N(AJ25)>=0.999,"Closed","In-house Closed - Payment Due"),IF(AS25<>"","Receiving In-house","PO Issued - Awaiting Delivery")))))) -> In-house Closed - Payment Due | BJ25: =IF(A25="","",IF(IF(AND(A25<>"",OR(B25="",C25="",E25="",F25="",H25="")),"PR info missing; ","")&IF(AND(K25="Approved",OR(J25="",I25="")),"Approval ref/date missing; ","")&IF(AND(O25<>"",K25<>"Approved"),"PO without approval; ","")&IF(AND(O25<>"",OR(P25="",M25="",Q25="",S25="",T25="")),"PO details missing; ","")&IF(AND(O25<>"",AR25=""),"Committed date missing; ","")&IF(AND(ISNUMBER(J25),ISNUMBER(B25),N(J25)<N(B25)),"Approval dated before PR; ","")&IF(AND(ISNUMBER(P25),ISNUMBER(J25),N(P25)<N(J25)),"PO dated before approval; ","")&IF(AND(ISNUMBER(AY25),ISNUMBER(AS25),N(AY25)<N(AS25)),"Close before in-house start; ","")&IF(AND(AY25<>"",AS25=""),"In-house start date missing; ","")&IF(AND(AY25<>"",AT25=""),"Qty received missing; ","")&IF(AND(AY25<>"",BF25=""),"QC status missing; ","")&IF(N(AT25)>N(Q25)*1.05,"Received > ordered +5%; ","")&IF(AND(N(AI25)>0,AE25=""),"Payment terms missing; ","")&IF(N(AI25)>N(AD25)+1,"Overpaid vs PO; ","")&IF(AND(N(AK25)>0,AY25<>"",AO25=""),"Payment due date missing; ","")="","OK",IF(AND(A25<>"",OR(B25="",C25="",E25="",F25="",H25="")),"PR info missing; ","")&IF(AND(K25="Approved",OR(J25="",I25="")),"Approval ref/date missing; ","")&IF(AND(O25<>"",K25<>"Approved"),"PO without approval; ","")&IF(AND(O25<>"",OR(P25="",M25="",Q25="",S25="",T25="")),"PO details missing; ","")&IF(AND(O25<>"",AR25=""),"Committed date missing; ","")&IF(AND(ISNUMBER(J25),ISNUMBER(B25),N(J25)<N(B25)),"Approval dated before PR; ","")&IF(AND(ISNUMBER(P25),ISNUMBER(J25),N(P25)<N(J25)),"PO dated before approval; ","")&IF(AND(ISNUMBER(AY25),ISNUMBER(AS25),N(AY25)<N(AS25)),"Close before in-house start; ","")&IF(AND(AY25<>"",AS25=""),"In-house start date missing; ","")&IF(AND(AY25<>"",AT25=""),"Qty received missing; ","")&IF(AND(AY25<>"",BF25=""),"QC status missing; ","")&IF(N(AT25)>N(Q25)*1.05,"Received > ordered +5%; ","")&IF(AND(N(AI25)>0,AE25=""),"Payment terms missing; ","")&IF(N(AI25)>N(AD25)+1,"Overpaid vs PO; ","")&IF(AND(N(AK25)>0,AY25<>"",AO25=""),"Payment due date missing; ",""))) -> OK | BK25: =IF(A25="","",IF(N(AP25)>0,"Pay supplier: "&N(AP25)&" days overdue; ","")&IF(AND(O25<>"",AY25="",N(BD25)>0),"Expedite delivery: "&N(BD25)&" days late; ","")&IF(AND(BI25="Awaiting Approval",ISNUMBER(B25),Settings!$B$4-N(B25)>Settings!$B$19),"Get approval: PR waiting "&(Settings!$B$4-N(B25))&" days; ","")&IF(AND(BI25="Approved - PO Pending",ISNUMBER(J25),Settings!$B$4-N(J25)>Settings!$B$20),"Issue PO: approved "&(Settings!$B$4-N(J25))&" days ago; ","")&IF(AND(OR(BI25="Awaiting Approval",BI25="Approved - PO Pending"),N(AB25)>Settings!$B$7),"Negotiate price: "&TEXT(AB25,"0%")&" above budget; ","")&IF(LEFT(AX25,12)="Short Closed","Short closed: claim balance / credit note"&IF(N(AL25)>0," BDT "&TEXT(AL25,"#,##0"),"")&"; ","")&IF(BF25="Rejected","QC rejected: return / replace; ","")&IF(AND(O25<>"",AY25="",N(AL25)>0,N(BD25)>0),"Advance at risk: BDT "&TEXT(AL25,"#,##0")&" paid, goods late; ","")&IF(AND(BJ25<>"",BJ25<>"OK"),"Fix data entry (see Data Check); ","")) | BL25: =IF(BK25="","",IF(OR(N(AP25)>30,AND(AY25="",N(BD25)>15),BF25="Rejected",AND(LEFT(AX25,12)="Short Closed",N(AL25)>0),AND(O25<>"",AY25="",N(AL25)>0,N(BD25)>0)),"High",IF(OR(N(AP25)>0,AND(AY25="",N(BD25)>7),LEFT(AX25,12)="Short Closed",AND(BI25="Awaiting Approval",ISNUMBER(B25),Settings!$B$4-N(B25)>2*Settings!$B$19),AND(BI25="Approved - PO Pending",ISNUMBER(J25),Settings!$B$4-N(J25)>2*Settings!$B$20)),"Medium","Low"))) | BM25: =IF(BL25="","",IF(BL25="High",1,IF(BL25="Medium",2,3))*10000+ROW())
A26: PSIL-PR-2026-0021 | B26: 46235 | C26: Maintenance | D26: Maintenance Manager | E26: Hydraulic Sole Pressing Machine | F26: Machinery & Equipment | G26: Twin station | H26: CAPEX | I26: CPX-2026-121 | J26: 46243 | K26: Approved | L26: MD | M26: Jiangsu Footwear Machinery Co. | N26: Import | O26: PSIL-PO-2026-0021 | P26: 46248 | Q26: 3 | R26: unit | S26: 53430.12 | T26: CNY | U26: =IF(AND(T26="",S26=""),"",IF(T26="",1,IFERROR(INDEX(Settings!$B$12:$B$16,MATCH(T26,Settings!$A$12:$A$16,0)),1))) -> 17 | V26: 905443.9 | W26: =IF(OR(Q26="",S26=""),"",Q26*S26*U26) -> 2724936.1 | X26: =IF(OR(W26="",N(Q26)=0),"",W26/Q26) -> 908312.04 | Y26: =IF(OR(X26="",P26="",E26=""),"",IF(_xlfn.MAXIFS($P$6:$P$205,$E$6:$E$205,E26,$P$6:$P$205,"<"&P26,$X$6:$X$205,">0")=0,"",IFERROR(AVERAGEIFS($X$6:$X$205,$E$6:$E$205,E26,$P$6:$P$205,_xlfn.MAXIFS($P$6:$P$205,$E$6:$E$205,E26,$P$6:$P$205,"<"&P26,$X$6:$X$205,">0"),$X$6:$X$205,">0"),""))) | Z26: =IF(OR(Y26="",X26=""),"",X26/Y26-1) | AA26: =IF(OR(W26="",V26=""),"",W26-Q26*V26) -> 8604.42 | AB26: =IF(AA26="","",IF(N(V26)*N(Q26)=0,"",AA26/(Q26*V26))) -> 0.0031676617 | AC26: 0.12 | AD26: =IF(W26="","",W26*(1+N(AC26))) -> 3051928.5 | AE26: 50% Advance / 50% after Installation | AF26: 1525964.2 | AI26: =IF(A26="","",N(AF26)+N(AG26)+N(AH26)) -> 1525964.2 | AJ26: =IF(AD26="","",IF(N(AD26)=0,"",AI26/AD26)) -> 0.5 | AK26: =IF(AD26="","",IF(AD26-AI26<1,0,ROUND(AD26-AI26,2))) -> 1525964.2 | AL26: =IF(OR(O26="",AD26=""),"",MAX(0,ROUND(N(AI26)-(AD26-N(AW26)),0))) -> 0 | AM26: =IF(A26="","",IF(O26="","No PO Yet",IF(AI26=0,"Not Paid",IF(N(AJ26)>=0.999,"Fully Paid",IF(N(AG26)+N(AH26)>0,"Partially Paid","Initial / Advance Paid"))))) -> Initial / Advance Paid | AN26: 46251 | AO26: 46326 | AP26: =IF(AK26="","",IF(OR(N(AK26)=0,AO26=""),"",MAX(0,Settings!$B$4-AO26))) -> 0 | AQ26: =IF(AK26="","",IF(N(AK26)<=0,"",IF(AO26="","No Due Date",IF(Settings!$B$4<=AO26,"Not Yet Due",IF(Settings!$B$4-AO26<=30,"1-30 Days",IF(Settings!$B$4-AO26<=60,"31-60 Days",IF(Settings!$B$4-AO26<=90,"61-90 Days","90+ Days"))))))) -> Not Yet Due | AR26: 46287 | AS26: 46295 | AT26: 3 | AU26: =IF(Q26="","",IF(N(Q26)=0,"",N(AT26)/Q26)) -> 1 | AV26: =IF(OR(A26="",O26="",Q26=""),"",MAX(0,Q26-N(AT26))) -> 0 | AW26: =IF(OR(AV26="",W26=""),"",IF(N(Q26)=0,0,AV26/Q26*AD26)) -> 0 | AX26: =IF(A26="","",IF(O26="","No PO Yet",IF(Q26="","Order Qty Missing",IF(N(AT26)>=Q26,IF(N(AT26)>Q26,"All In-house (+"&TEXT(N(AT26)-Q26,"#,##0")&" "&R26&" excess)","All In-house"),IF(AY26<>"","Short Closed - "&TEXT(AV26,"#,##0")&" "&R26&" not received",IF(N(AT26)=0,"Not Started - "&TEXT(AV26,"#,##0")&" "&R26&" pending","Pending "&TEXT(AV26,"#,##0")&" "&R26&" ("&TEXT(AU26,"0%")&" received)")))))) -> All In-house | AY26: 46296 | AZ26: =IF(OR(B26="",J26=""),"",J26-B26) -> 8 | BA26: =IF(OR(J26="",P26=""),"",P26-J26) -> 5 | BB26: =IF(OR(P26="",AY26=""),"",AY26-P26) -> 48 | BC26: =IF(OR(B26="",AY26=""),"",AY26-B26) -> 61 | BD26: =IF(OR(AR26="",O26=""),"",MAX(0,IF(AY26="",Settings!$B$4,AY26)-AR26)) -> 9 | BE26: =IF(OR(AY26="",AR26=""),"",IF(AND(AY26<=AR26,N(AU26)>=Settings!$B$6),"OTIF","Not OTIF")) -> Not OTIF | BF26: Approved | BI26: =IF(A26="","",IF(K26="Rejected","Rejected",IF(K26<>"Approved","Awaiting Approval",IF(O26="","Approved - PO Pending",IF(AY26<>"",IF(N(AJ26)>=0.999,"Closed","In-house Closed - Payment Due"),IF(AS26<>"","Receiving In-house","PO Issued - Awaiting Delivery")))))) -> In-house Closed - Payment Due | BJ26: =IF(A26="","",IF(IF(AND(A26<>"",OR(B26="",C26="",E26="",F26="",H26="")),"PR info missing; ","")&IF(AND(K26="Approved",OR(J26="",I26="")),"Approval ref/date missing; ","")&IF(AND(O26<>"",K26<>"Approved"),"PO without approval; ","")&IF(AND(O26<>"",OR(P26="",M26="",Q26="",S26="",T26="")),"PO details missing; ","")&IF(AND(O26<>"",AR26=""),"Committed date missing; ","")&IF(AND(ISNUMBER(J26),ISNUMBER(B26),N(J26)<N(B26)),"Approval dated before PR; ","")&IF(AND(ISNUMBER(P26),ISNUMBER(J26),N(P26)<N(J26)),"PO dated before approval; ","")&IF(AND(ISNUMBER(AY26),ISNUMBER(AS26),N(AY26)<N(AS26)),"Close before in-house start; ","")&IF(AND(AY26<>"",AS26=""),"In-house start date missing; ","")&IF(AND(AY26<>"",AT26=""),"Qty received missing; ","")&IF(AND(AY26<>"",BF26=""),"QC status missing; ","")&IF(N(AT26)>N(Q26)*1.05,"Received > ordered +5%; ","")&IF(AND(N(AI26)>0,AE26=""),"Payment terms missing; ","")&IF(N(AI26)>N(AD26)+1,"Overpaid vs PO; ","")&IF(AND(N(AK26)>0,AY26<>"",AO26=""),"Payment due date missing; ","")="","OK",IF(AND(A26<>"",OR(B26="",C26="",E26="",F26="",H26="")),"PR info missing; ","")&IF(AND(K26="Approved",OR(J26="",I26="")),"Approval ref/date missing; ","")&IF(AND(O26<>"",K26<>"Approved"),"PO without approval; ","")&IF(AND(O26<>"",OR(P26="",M26="",Q26="",S26="",T26="")),"PO details missing; ","")&IF(AND(O26<>"",AR26=""),"Committed date missing; ","")&IF(AND(ISNUMBER(J26),ISNUMBER(B26),N(J26)<N(B26)),"Approval dated before PR; ","")&IF(AND(ISNUMBER(P26),ISNUMBER(J26),N(P26)<N(J26)),"PO dated before approval; ","")&IF(AND(ISNUMBER(AY26),ISNUMBER(AS26),N(AY26)<N(AS26)),"Close before in-house start; ","")&IF(AND(AY26<>"",AS26=""),"In-house start date missing; ","")&IF(AND(AY26<>"",AT26=""),"Qty received missing; ","")&IF(AND(AY26<>"",BF26=""),"QC status missing; ","")&IF(N(AT26)>N(Q26)*1.05,"Received > ordered +5%; ","")&IF(AND(N(AI26)>0,AE26=""),"Payment terms missing; ","")&IF(N(AI26)>N(AD26)+1,"Overpaid vs PO; ","")&IF(AND(N(AK26)>0,AY26<>"",AO26=""),"Payment due date missing; ",""))) -> OK | BK26: =IF(A26="","",IF(N(AP26)>0,"Pay supplier: "&N(AP26)&" days overdue; ","")&IF(AND(O26<>"",AY26="",N(BD26)>0),"Expedite delivery: "&N(BD26)&" days late; ","")&IF(AND(BI26="Awaiting Approval",ISNUMBER(B26),Settings!$B$4-N(B26)>Settings!$B$19),"Get approval: PR waiting "&(Settings!$B$4-N(B26))&" days; ","")&IF(AND(BI26="Approved - PO Pending",ISNUMBER(J26),Settings!$B$4-N(J26)>Settings!$B$20),"Issue PO: approved "&(Settings!$B$4-N(J26))&" days ago; ","")&IF(AND(OR(BI26="Awaiting Approval",BI26="Approved - PO Pending"),N(AB26)>Settings!$B$7),"Negotiate price: "&TEXT(AB26,"0%")&" above budget; ","")&IF(LEFT(AX26,12)="Short Closed","Short closed: claim balance / credit note"&IF(N(AL26)>0," BDT "&TEXT(AL26,"#,##0"),"")&"; ","")&IF(BF26="Rejected","QC rejected: return / replace; ","")&IF(AND(O26<>"",AY26="",N(AL26)>0,N(BD26)>0),"Advance at risk: BDT "&TEXT(AL26,"#,##0")&" paid, goods late; ","")&IF(AND(BJ26<>"",BJ26<>"OK"),"Fix data entry (see Data Check); ","")) | BL26: =IF(BK26="","",IF(OR(N(AP26)>30,AND(AY26="",N(BD26)>15),BF26="Rejected",AND(LEFT(AX26,12)="Short Closed",N(AL26)>0),AND(O26<>"",AY26="",N(AL26)>0,N(BD26)>0)),"High",IF(OR(N(AP26)>0,AND(AY26="",N(BD26)>7),LEFT(AX26,12)="Short Closed",AND(BI26="Awaiting Approval",ISNUMBER(B26),Settings!$B$4-N(B26)>2*Settings!$B$19),AND(BI26="Approved - PO Pending",ISNUMBER(J26),Settings!$B$4-N(J26)>2*Settings!$B$20)),"Medium","Low"))) | BM26: =IF(BL26="","",IF(BL26="High",1,IF(BL26="Medium",2,3))*10000+ROW())
A27: PSIL-PR-2026-0022 | B27: 46238 | C27: Maintenance | D27: Maintenance Manager | E27: Screw Air Compressor 30 HP | F27: Machinery & Equipment | G27: With dryer & tank | H27: CAPEX | I27: CPX-2026-122 | J27: 46244 | K27: Approved | L27: MD | M27: Dhaka Spares & Tools | N27: Local | O27: PSIL-PO-2026-0022 | P27: 46246 | Q27: 1 | R27: unit | S27: 1495361 | T27: BDT | U27: =IF(AND(T27="",S27=""),"",IF(T27="",1,IFERROR(INDEX(Settings!$B$12:$B$16,MATCH(T27,Settings!$A$12:$A$16,0)),1))) -> 1 | V27: 1474015.4 | W27: =IF(OR(Q27="",S27=""),"",Q27*S27*U27) -> 1495361 | X27: =IF(OR(W27="",N(Q27)=0),"",W27/Q27) -> 1495361 | Y27: =IF(OR(X27="",P27="",E27=""),"",IF(_xlfn.MAXIFS($P$6:$P$205,$E$6:$E$205,E27,$P$6:$P$205,"<"&P27,$X$6:$X$205,">0")=0,"",IFERROR(AVERAGEIFS($X$6:$X$205,$E$6:$E$205,E27,$P$6:$P$205,_xlfn.MAXIFS($P$6:$P$205,$E$6:$E$205,E27,$P$6:$P$205,"<"&P27,$X$6:$X$205,">0"),$X$6:$X$205,">0"),""))) | Z27: =IF(OR(Y27="",X27=""),"",X27/Y27-1) | AA27: =IF(OR(W27="",V27=""),"",W27-Q27*V27) -> 21345.61 | AB27: =IF(AA27="","",IF(N(V27)*N(Q27)=0,"",AA27/(Q27*V27))) -> 0.014481267 | AC27: 0.075 | AD27: =IF(W27="","",W27*(1+N(AC27))) -> 1607513.1 | AE27: 50% Advance / 50% after Installation | AF27: 803756.54 | AH27: 803756.54 | AI27: =IF(A27="","",N(AF27)+N(AG27)+N(AH27)) -> 1607513.1 | AJ27: =IF(AD27="","",IF(N(AD27)=0,"",AI27/AD27)) -> 1 | AK27: =IF(AD27="","",IF(AD27-AI27<1,0,ROUND(AD27-AI27,2))) -> 0 | AL27: =IF(OR(O27="",AD27=""),"",MAX(0,ROUND(N(AI27)-(AD27-N(AW27)),0))) -> 0 | AM27: =IF(A27="","",IF(O27="","No PO Yet",IF(AI27=0,"Not Paid",IF(N(AJ27)>=0.999,"Fully Paid",IF(N(AG27)+N(AH27)>0,"Partially Paid","Initial / Advance Paid"))))) -> Fully Paid | AN27: 46291 | AP27: =IF(AK27="","",IF(OR(N(AK27)=0,AO27=""),"",MAX(0,Settings!$B$4-AO27))) | AQ27: =IF(AK27="","",IF(N(AK27)<=0,"",IF(AO27="","No Due Date",IF(Settings!$B$4<=AO27,"Not Yet Due",IF(Settings!$B$4-AO27<=30,"1-30 Days",IF(Settings!$B$4-AO27<=60,"31-60 Days",IF(Settings!$B$4-AO27<=90,"61-90 Days","90+ Days"))))))) | AR27: 46258 | AS27: 46261 | AT27: 1 | AU27: =IF(Q27="","",IF(N(Q27)=0,"",N(AT27)/Q27)) -> 1 | AV27: =IF(OR(A27="",O27="",Q27=""),"",MAX(0,Q27-N(AT27))) -> 0 | AW27: =IF(OR(AV27="",W27=""),"",IF(N(Q27)=0,0,AV27/Q27*AD27)) -> 0 | AX27: =IF(A27="","",IF(O27="","No PO Yet",IF(Q27="","Order Qty Missing",IF(N(AT27)>=Q27,IF(N(AT27)>Q27,"All In-house (+"&TEXT(N(AT27)-Q27,"#,##0")&" "&R27&" excess)","All In-house"),IF(AY27<>"","Short Closed - "&TEXT(AV27,"#,##0")&" "&R27&" not received",IF(N(AT27)=0,"Not Started - "&TEXT(AV27,"#,##0")&" "&R27&" pending","Pending "&TEXT(AV27,"#,##0")&" "&R27&" ("&TEXT(AU27,"0%")&" received)")))))) -> All In-house | AY27: 46261 | AZ27: =IF(OR(B27="",J27=""),"",J27-B27) -> 6 | BA27: =IF(OR(J27="",P27=""),"",P27-J27) -> 2 | BB27: =IF(OR(P27="",AY27=""),"",AY27-P27) -> 15 | BC27: =IF(OR(B27="",AY27=""),"",AY27-B27) -> 23 | BD27: =IF(OR(AR27="",O27=""),"",MAX(0,IF(AY27="",Settings!$B$4,AY27)-AR27)) -> 3 | BE27: =IF(OR(AY27="",AR27=""),"",IF(AND(AY27<=AR27,N(AU27)>=Settings!$B$6),"OTIF","Not OTIF")) -> Not OTIF | BF27: Approved | BI27: =IF(A27="","",IF(K27="Rejected","Rejected",IF(K27<>"Approved","Awaiting Approval",IF(O27="","Approved - PO Pending",IF(AY27<>"",IF(N(AJ27)>=0.999,"Closed","In-house Closed - Payment Due"),IF(AS27<>"","Receiving In-house","PO Issued - Awaiting Delivery")))))) -> Closed | BJ27: =IF(A27="","",IF(IF(AND(A27<>"",OR(B27="",C27="",E27="",F27="",H27="")),"PR info missing; ","")&IF(AND(K27="Approved",OR(J27="",I27="")),"Approval ref/date missing; ","")&IF(AND(O27<>"",K27<>"Approved"),"PO without approval; ","")&IF(AND(O27<>"",OR(P27="",M27="",Q27="",S27="",T27="")),"PO details missing; ","")&IF(AND(O27<>"",AR27=""),"Committed date missing; ","")&IF(AND(ISNUMBER(J27),ISNUMBER(B27),N(J27)<N(B27)),"Approval dated before PR; ","")&IF(AND(ISNUMBER(P27),ISNUMBER(J27),N(P27)<N(J27)),"PO dated before approval; ","")&IF(AND(ISNUMBER(AY27),ISNUMBER(AS27),N(AY27)<N(AS27)),"Close before in-house start; ","")&IF(AND(AY27<>"",AS27=""),"In-house start date missing; ","")&IF(AND(AY27<>"",AT27=""),"Qty received missing; ","")&IF(AND(AY27<>"",BF27=""),"QC status missing; ","")&IF(N(AT27)>N(Q27)*1.05,"Received > ordered +5%; ","")&IF(AND(N(AI27)>0,AE27=""),"Payment terms missing; ","")&IF(N(AI27)>N(AD27)+1,"Overpaid vs PO; ","")&IF(AND(N(AK27)>0,AY27<>"",AO27=""),"Payment due date missing; ","")="","OK",IF(AND(A27<>"",OR(B27="",C27="",E27="",F27="",H27="")),"PR info missing; ","")&IF(AND(K27="Approved",OR(J27="",I27="")),"Approval ref/date missing; ","")&IF(AND(O27<>"",K27<>"Approved"),"PO without approval; ","")&IF(AND(O27<>"",OR(P27="",M27="",Q27="",S27="",T27="")),"PO details missing; ","")&IF(AND(O27<>"",AR27=""),"Committed date missing; ","")&IF(AND(ISNUMBER(J27),ISNUMBER(B27),N(J27)<N(B27)),"Approval dated before PR; ","")&IF(AND(ISNUMBER(P27),ISNUMBER(J27),N(P27)<N(J27)),"PO dated before approval; ","")&IF(AND(ISNUMBER(AY27),ISNUMBER(AS27),N(AY27)<N(AS27)),"Close before in-house start; ","")&IF(AND(AY27<>"",AS27=""),"In-house start date missing; ","")&IF(AND(AY27<>"",AT27=""),"Qty received missing; ","")&IF(AND(AY27<>"",BF27=""),"QC status missing; ","")&IF(N(AT27)>N(Q27)*1.05,"Received > ordered +5%; ","")&IF(AND(N(AI27)>0,AE27=""),"Payment terms missing; ","")&IF(N(AI27)>N(AD27)+1,"Overpaid vs PO; ","")&IF(AND(N(AK27)>0,AY27<>"",AO27=""),"Payment due date missing; ",""))) -> OK | BK27: =IF(A27="","",IF(N(AP27)>0,"Pay supplier: "&N(AP27)&" days overdue; ","")&IF(AND(O27<>"",AY27="",N(BD27)>0),"Expedite delivery: "&N(BD27)&" days late; ","")&IF(AND(BI27="Awaiting Approval",ISNUMBER(B27),Settings!$B$4-N(B27)>Settings!$B$19),"Get approval: PR waiting "&(Settings!$B$4-N(B27))&" days; ","")&IF(AND(BI27="Approved - PO Pending",ISNUMBER(J27),Settings!$B$4-N(J27)>Settings!$B$20),"Issue PO: approved "&(Settings!$B$4-N(J27))&" days ago; ","")&IF(AND(OR(BI27="Awaiting Approval",BI27="Approved - PO Pending"),N(AB27)>Settings!$B$7),"Negotiate price: "&TEXT(AB27,"0%")&" above budget; ","")&IF(LEFT(AX27,12)="Short Closed","Short closed: claim balance / credit note"&IF(N(AL27)>0," BDT "&TEXT(AL27,"#,##0"),"")&"; ","")&IF(BF27="Rejected","QC rejected: return / replace; ","")&IF(AND(O27<>"",AY27="",N(AL27)>0,N(BD27)>0),"Advance at risk: BDT "&TEXT(AL27,"#,##0")&" paid, goods late; ","")&IF(AND(BJ27<>"",BJ27<>"OK"),"Fix data entry (see Data Check); ","")) | BL27: =IF(BK27="","",IF(OR(N(AP27)>30,AND(AY27="",N(BD27)>15),BF27="Rejected",AND(LEFT(AX27,12)="Short Closed",N(AL27)>0),AND(O27<>"",AY27="",N(AL27)>0,N(BD27)>0)),"High",IF(OR(N(AP27)>0,AND(AY27="",N(BD27)>7),LEFT(AX27,12)="Short Closed",AND(BI27="Awaiting Approval",ISNUMBER(B27),Settings!$B$4-N(B27)>2*Settings!$B$19),AND(BI27="Approved - PO Pending",ISNUMBER(J27),Settings!$B$4-N(J27)>2*Settings!$B$20)),"Medium","Low"))) | BM27: =IF(BL27="","",IF(BL27="High",1,IF(BL27="Medium",2,3))*10000+ROW())
